Workbook

Sheet Overview of Everything
B2: Games | C2: Songs Released | D2: Total Songs | E2: Percentage Completion | G2: Special Thanks To:
B3: Rock Band 1 (Rewind Only) | C3: ='RB1'!C63 -> 27 | D3: ='RB1'!C64 -> 58 | E3: ='RB1'!C65 -> 0.46551724 | G3: Harmonix
B4: Rock Band 2 (Rewind Only) | C4: ='RB2'!C89 -> 34 | D4: ='RB2'!C90 -> 84 | E4: ='RB2'!C91 -> 0.4047619 | G4: =HYPERLINK("http://www.rockbandaide.com/","Rock Band Aide") -> Rock Band Aide
B5: Rock Band 3 (Rewind Only) | C5: ='RB3'!C88 -> 15 | D5: ='RB3'!C89 -> 83 | E5: ='RB3'!C90 -> 0.18072289 | G5: =HYPERLINK("http://rbdb.online/","rbdb.online") -> rbdb.online
B6: Lego Rock Band (Rewind Only) | C6: ='LEGO RB'!C50 -> 10 | D6: ='LEGO RB'!C51 -> 45 | E6: ='LEGO RB'!C52 -> 0.22222222 | G6: Whoever is that guy updating
B7: Rock Band Network (Rewind Only) | C7: =RBN!C1919 -> 194 | D7: =RBN!C1920 -> 1914 | E7: =RBN!C1921 -> 0.10135841 | G7: Rock Band DLC Wikipedia Page
B8: ~~~~~~~~~~~~~~~~~~~~~~~~~~~~~~~~~~~~~~~~~~
B9: Rock Band VR | C9: ='Rock Band VR'!C65 -> 53 | D9: ='Rock Band VR'!C66 -> 60 | E9: ='Rock Band VR'!C67 -> 0.88333333
B10: DLC | C10: ='Rock Band VR DLC'!C27 -> 22 | D10: ='Rock Band VR DLC'!C28 -> 22 | E10: ='Rock Band VR DLC'!C29 -> 1
B11: ~~~~~~~~~~~~~~~~~~~~~~~~~~~~~~~~~~~~~~~~~~
B12: Dropmix | C12: =Dropmix!C118 -> 44 | D12: =Dropmix!C119 -> 113 | E12: =Dropmix!C120 -> 0.38938053
B13: Fuser | C13: =Fuser!C93 -> 32 | D13: =Fuser!C94 -> 89 | E13: =Fuser!C95 -> 0.35955056 | G13: Made By:
B14: DLC | C14: ='Fuser DLC'!C144 -> 42 | D14: ='Fuser DLC'!C145 -> 139 | E14: ='Fuser DLC'!C146 -> 0.30215827 | G14: JMilla Potato
B15: ~~~~~~~~~~~~~~~~~~~~~~~~~~~~~~~~~~~~~~~~~~
B16: Guitar Hero | C16: ='GH1'!C52 -> 26 | D16: ='GH1'!C53 -> 47 | E16: ='GH1'!C54 -> 0.55319149
B17: Guitar Hero II | C17: ='GH2'!C79 -> 32 | D17: ='GH2'!C80 -> 74 | E17: ='GH2'!C81 -> 0.43243243
B18: DLC | C18: ='GH2 DLC'!C29 -> 11 | D18: ='GH2 DLC'!C30 -> 24 | E18: ='GH2 DLC'!C31 -> 0.45833333
B19: Guitar Hero III: Legends of Rock | C19: ='GH3'!C76 -> 42 | D19: ='GH3'!C77 -> 71 | E19: ='GH3'!C78 -> 0.5915493
B20: DLC | C20: ='GH3 DLC'!C70 -> 21 | D20: ='GH3 DLC'!C71 -> 65 | E20: ='GH3 DLC'!C72 -> 0.32307692
B21: Guitar Hero: World Tour | C21: ='GH World Tour'!C89 -> 54 | D21: ='GH World Tour'!C90 -> 84 | E21: ='GH World Tour'!C91 -> 0.64285714 | G21: My Links
B22: Guitar Hero 5 | C22: ='GH 5'!C90 -> 42 | D22: ='GH 5'!C91 -> 85 | E22: ='GH 5'!C92 -> 0.49411765 | G22: =HYPERLINK("https://www.youtube.com/channel/UC-1LzD9LF-Knd67UJBpG0rQ?view_as=public","YouTube") -> YouTube
B23: Guitar Hero: Warriors of Rock | C23: ='GH Warriors of Rock'!C92 -> 39 | D23: ='GH Warriors of Rock'!C93 -> 87 | E23: ='GH Warriors of Rock'!C94 -> 0.44827586 | G23: =HYPERLINK("https://twitter.com/JMilla_Potato?lang=en","Twitter") -> Twitter
B24: DLC | C24: ='Guitar Hero 456 DLC'!C399 -> 164 | D24: ='Guitar Hero 456 DLC'!C400 -> 394 | E24: ='Guitar Hero 456 DLC'!C401 -> 0.41624365
B25: ~~~~~~~~~~~~~~~~~~~~~~~~~~~~~~~~~~~~~~~~~~
B26: Guitar Hero: Live | C26: ='GH Live'!C47 -> 18 | D26: ='GH Live'!C48 -> 42 | E26: ='GH Live'!C49 -> 0.42857143 | G26: Let's Play Rock Band 4 Together!!
B27: Guitar Hero: TV | C27: ='GH TV'!C522 -> 171 | D27: ='GH TV'!C523 -> 517 | E27: ='GH TV'!C524 -> 0.33075435 | G27: XBox gt: ya AMERICA
B28: ~~~~~~~~~~~~~~~~~~~~~~~~~~~~~~~~~~~~~~~~~~
B29: Guitar Hero: Aerosmith | C29: ='GH Aerosmith'!C45 -> 17 | D29: ='GH Aerosmith'!C46 -> 40 | E29: ='GH Aerosmith'!C47 -> 0.425
B30: Guitar Hero: Metallica | C30: ='GH Metallica'!C57 -> 10 | D30: ='GH Metallica'!C58 -> 52 | E30: ='GH Metallica'!C59 -> 0.19230769
B31: Guitar Hero: Van Halen | C31: ='GH Van Halen'!C52 -> 21 | D31: ='GH Van Halen'!C53 -> 47 | E31: ='GH Van Halen'!C54 -> 0.44680851
B32: ~~~~~~~~~~~~~~~~~~~~~~~~~~~~~~~~~~~~~~~~~~
B33: Guitar Hero Encore: Rocks the 80s | C33: ='Rocks the 80s'!C35 -> 21 | D33: ='Rocks the 80s'!C36 -> 30 | E33: ='Rocks the 80s'!C37 -> 0.7
B34: Guitar Hero: Smash/Greatest Hits | C34: ='GH Smash Hits'!C53 -> 40 | D34: ='GH Smash Hits'!C54 -> 48 | E34: ='GH Smash Hits'!C55 -> 0.83333333
B35: Band Hero | C35: ='Band Hero'!C70 -> 33 | D35: ='Band Hero'!C71 -> 65 | E35: ='Band Hero'!C72 -> 0.50769231
B36: ~~~~~~~~~~~~~~~~~~~~~~~~~~~~~~~~~~~~~~~~~~
B37: Guitar Hero: On Tour | C37: ='Guitar Hero On Tour'!C36 -> 16 | D37: ='Guitar Hero On Tour'!C37 -> 31 | E37: ='Guitar Hero On Tour'!C38 -> 0.51612903
B38: Guitar Hero On Tour: Decades | C38: ='Guitar Hero On Tour Decades'!C40 -> 25 | D38: ='Guitar Hero On Tour Decades'!C41 -> 35 | E38: ='Guitar Hero On Tour Decades'!C42 -> 0.71428571
B39: Guitar Hero On Tour: Modern Hits | C39: ='Guitar Hero On Tour Modern Hits'!C45 -> 13 | D39: ='Guitar Hero On Tour Modern Hits'!C46 -> 40 | E39: ='Guitar Hero On Tour Modern Hits'!C47 -> 0.325
B40: Band Hero DS | C40: ='Band Hero DS'!C50 -> 25 | D40: ='Band Hero DS'!C51 -> 45 | E40: ='Band Hero DS'!C52 -> 0.55555556
B41: ~~~~~~~~~~~~~~~~~~~~~~~~~~~~~~~~~~~~~~~~~~
B42: Guitar Hero 3 Mobile | C42: ='GH 3 Mobile'!C20 -> 12 | D42: ='GH 3 Mobile'!C21 -> 15 | E42: ='GH 3 Mobile'!C22 -> 0.8
B43: DLC | C43: ='GH 3 Mobile DLC'!C41 -> 21 | D43: ='GH 3 Mobile DLC'!C42 -> 36 | E43: ='GH 3 Mobile DLC'!C43 -> 0.58333333
B44: Guitar Hero World Tour Mobile | C44: ='GH World Tour Mobile'!C20 -> 10 | D44: ='GH World Tour Mobile'!C21 -> 15 | E44: ='GH World Tour Mobile'!C22 -> 0.66666667
B45: DLC | C45: ='GH World Tour Mobile DLC'!C15 -> 4 | D45: ='GH World Tour Mobile DLC'!C16 -> 10 | E45: ='GH World Tour Mobile DLC'!C17 -> 0.4
B46: Guitar Hero 5 Mobile | C46: ='GH 5 Mobile'!C24 -> 11 | D46: ='GH 5 Mobile'!C25 -> 20 | E46: ='GH 5 Mobile'!C26 -> 0.55
B47: ~~~~~~~~~~~~~~~~~~~~~~~~~~~~~~~~~~~~~~~~~~
B48: Guitar Hero Arcade | C48: ='GH Arcade'!C55 -> 30 | D48: ='GH Arcade'!C56 -> 50 | E48: ='GH Arcade'!C57 -> 0.6
B49: ~~~~~~~~~~~~~~~~~~~~~~~~~~~~~~~~~~~~~~~~~~
B50: DJ Hero | C50: ='DJ Hero'!C114 -> 19 | D50: ='DJ Hero'!C115 -> 109 | E50: ='DJ Hero'!C116 -> 0.17431193
B51: DJ Hero 2 | C51: ='DJ Hero 2'!C110 -> 9 | D51: ='DJ Hero 2'!C111 -> 105 | E51: ='DJ Hero 2'!C112 -> 0.085714286
B52: DLC | C52: ='DJ Hero 12 DLC'!C72 -> 5 | D52: ='DJ Hero 12 DLC'!C73 -> 67 | E52: ='DJ Hero 12 DLC'!C74 -> 0.074626866
B53: ~~~~~~~~~~~~~~~~~~~~~~~~~~~~~~~~~~~~~~~~~~
B54: Rocksmith | C54: =Rocksmith!C62 -> 16 | D54: =Rocksmith!C63 -> 57 | E54: =Rocksmith!C64 -> 0.28070175
B55: DLC | C55: ='Rocksmith DLC'!C148 -> 106 | D55: ='Rocksmith DLC'!C149 -> 142 | E55: ='Rocksmith DLC'!C150 -> 0.74647887
B56: Rocksmith 2014 | C56: ='Rocksmith 2014'!C71 -> 27 | D56: ='Rocksmith 2014'!C72 -> 66 | E56: ='Rocksmith 2014'!C73 -> 0.40909091
B57: DLC | C57: ='Rocksmith 2014 DLC'!C1244 -> 619 | D57: ='Rocksmith 2014 DLC'!C1245 -> 1239 | E57: ='Rocksmith 2014 DLC'!C1246 -> 0.49959645
B58: ~~~~~~~~~~~~~~~~~~~~~~~~~~~~~~~~~~~~~~~~~~
B59: Rock Revolution | C59: ='Rock Revolution'!C46 -> 36 | D59: ='Rock Revolution'!C47 -> 41 | E59: ='Rock Revolution'!C48 -> 0.87804878
B60: DLC | C60: ='Rock Revolution DLC'!C17 -> 3 | D60: ='Rock Revolution DLC'!C18 -> 12 | E60: ='Rock Revolution DLC'!C19 -> 0.25
B61: Powergig: Rise of the Sixstring | C61: =Powergig!C75 -> 19 | D61: =Powergig!C76 -> 70 | E61: =Powergig!C77 -> 0.27142857
B62: DLC | C62: ='Powergig DLC'!C8 -> 1 | D62: ='Powergig DLC'!C9 -> 3 | E62: ='Powergig DLC'!C10 -> 0.33333333
B63: Bandfuse: Rock Legends | C63: =Bandfuse!C60 -> 43 | D63: =Bandfuse!C61 -> 55 | E63: =Bandfuse!C62 -> 0.78181818
B64: DLC | C64: ='Bandfuse DLC'!C26 -> 20 | D64: ='Bandfuse DLC'!C27 -> 21 | E64: ='Bandfuse DLC'!C28 -> 0.95238095
B65: ~~~~~~~~~~~~~~~~~~~~~~~~~~~~~~~~~~~~~~~~~~
B66: Rock of the Dead | C66: ='Rock of the Dead'!C27 -> 4 | D66: ='Rock of the Dead'!C28 -> 21 | E66: ='Rock of the Dead'!C29 -> 0.19047619
B67: KickBeat | C67: =KickBeat!C29 -> 3 | D67: =KickBeat!C30 -> 25 | E67: =KickBeat!C31 -> 0.12
B68: Guitar Rock Tour | C68: ='Guitar Rock Tour'!C24 -> 9 | D68: ='Guitar Rock Tour'!C25 -> 19 | E68: ='Guitar Rock Tour'!C26 -> 0.47368421
B69: Guitar Rock Tour 2 | C69: ='Guitar Rock Tour 2'!C23 -> 12 | D69: ='Guitar Rock Tour 2'!C24 -> 18 | E69: ='Guitar Rock Tour 2'!C25 -> 0.66666667
B70: Ultimate Band | C70: ='Ultimate Band'!C43 -> 28 | D70: ='Ultimate Band'!C44 -> 38 | E70: ='Ultimate Band'!C45 -> 0.73684211
B71: Elite Beat Agents | C71: ='Elite Beat Agents'!C24 -> 8 | D71: ='Elite Beat Agents'!C25 -> 19 | E71: ='Elite Beat Agents'!C26 -> 0.42105263
B72: Guitar Praise | C72: ='Guitar Praise'!B56 -> 2 | D72: ='Guitar Praise'!B57 -> 52 | E72: ='Guitar Praise'!B58 -> 0.038461538
B73: We Rock: Drum King | C73: ='We Rock Drum King'!C34 -> 16 | D73: ='We Rock Drum King'!C35 -> 29 | E73: ='We Rock Drum King'!C36 -> 0.55172414
B74: ~~~~~~~~~~~~~~~~~~~~~~~~~~~~~~~~~~~~~~~~~~
B75: Frequency | C75: =Frequency!B31 -> 2 | D75: =Frequency!B32 -> 27 | E75: =Frequency!B33 -> 0.074074074
B76: Amplitude | C76: =Amplitude!B30 -> 6 | D76: =Amplitude!B31 -> 26 | E76: =Amplitude!B32 -> 0.23076923
B77: Amplitude (2016) | C77: ='Amplitude (2016)'!B34 -> 1 | D77: ='Amplitude (2016)'!B35 -> 30 | E77: ='Amplitude (2016)'!B36 -> 0.033333333
B78: Phase | C78: =Phase!B11 -> 3 | D78: =Phase!B12 -> 7 | E78: =Phase!B13 -> 0.42857143
B79: ~~~~~~~~~~~~~~~~~~~~~~~~~~~~~~~~~~~~~~~~~~
B80: Fantasia: Music Evolved | C80: =Fantasia!C38 -> 14 | D80: =Fantasia!C39 -> 33 | E80: =Fantasia!C40 -> 0.42424242
B81: DLC | C81: ='Fantasia DLC'!C23 -> 7 | D81: ='Fantasia DLC'!C24 -> 18 | E81: ='Fantasia DLC'!C25 -> 0.38888889
B82: Audica | C82: =Audica!C38 -> 3 | D82: =Audica!C39 -> 33 | E82: =Audica!C40 -> 0.090909091
B83: DLC | C83: ='Audica DLC'!C28 -> 12 | D83: ='Audica DLC'!C29 -> 23 | E83: ='Audica DLC'!C30 -> 0.52173913
B84: ~~~~~~~~~~~~~~~~~~~~~~~~~~~~~~~~~~~~~~~~~~
B85: Dance Central | C85: ='Dance Central'!B36 -> 6 | D85: ='Dance Central'!B37 -> 31 | E85: ='Dance Central'!B38 -> 0.19354839
B86: Dance Central 2 | C86: ='Dance Central 2'!B48 -> 5 | D86: ='Dance Central 2'!B49 -> 44 | E86: ='Dance Central 2'!B50 -> 0.11363636
B87: Dance Central 3 | C87: ='Dance Central 3'!B50 -> 6 | D87: ='Dance Central 3'!B51 -> 46 | E87: ='Dance Central 3'!B52 -> 0.13043478
B88: DLC | C88: ='Dance Central 123 DLC'!B72 -> 7 | D88: ='Dance Central 123 DLC'!B73 -> 69 | E88: ='Dance Central 123 DLC'!B74 -> 0.10144928
B89: Dance Central Spotlight | C89: ='Dance Central Spotlight'!C15 -> 4 | D89: ='Dance Central Spotlight'!C16 -> 10 | E89: ='Dance Central Spotlight'!C17 -> 0.4
B90: DLC | C90: ='Dance Central Spotlight DLC'!B54 -> 16 | D90: ='Dance Central Spotlight DLC'!B55 -> 50 | E90: ='Dance Central Spotlight DLC'!B56 -> 0.32
B91: Dance Central (2019) | C91: ='Dance Central 2019'!C37 -> 5 | D91: ='Dance Central 2019'!C38 -> 32 | E91: ='Dance Central 2019'!C39 -> 0.15625
B92: ~~~~~~~~~~~~~~~~~~~~~~~~~~~~~~~~~~~~~~~~~~
B93: Just Dance | C93: ='Just Dance'!B36 -> 5 | D93: ='Just Dance'!B37 -> 32 | E93: ='Just Dance'!B38 -> 0.15625
B94: Just Dance 2 | C94: ='Just Dance 2'!B52 -> 9 | D94: ='Just Dance 2'!B53 -> 48 | E94: ='Just Dance 2'!B54 -> 0.1875
B95: Just Dance 3 | C95: ='Just Dance 3'!B57 -> 6 | D95: ='Just Dance 3'!B58 -> 53 | E95: ='Just Dance 3'!B59 -> 0.11320755
B96: Just Dance 4 | C96: ='Just Dance 4'!C55 -> 11 | D96: ='Just Dance 4'!C56 -> 50 | E96: ='Just Dance 4'!C57 -> 0.22
B97: Just Dance 2014 | C97: ='Just Dance 2014'!B54 -> 8 | D97: ='Just Dance 2014'!B55 -> 50 | E97: ='Just Dance 2014'!B56 -> 0.16
B98: Just Dance 2015 | C98: ='Just Dance 2015'!B48 -> 4 | D98: ='Just Dance 2015'!B49 -> 44 | E98: ='Just Dance 2015'!B50 -> 0.090909091
B99: Just Dance 2016 | C99: ='Just Dance 2016'!B47 -> 6 | D99: ='Just Dance 2016'!B48 -> 43 | E99: ='Just Dance 2016'!B49 -> 0.13953488
B100: Just Dance 2017 | C100: ='Just Dance 2017'!B44 -> 7 | D100: ='Just Dance 2017'!B45 -> 40 | E100: ='Just Dance 2017'!B46 -> 0.175
B101: Just Dance 2018 | C101: ='Just Dance 2018'!B44 -> 5 | D101: ='Just Dance 2018'!B45 -> 41 | E101: ='Just Dance 2018'!B46 -> 0.12195122
...

Sheet Spotlight Passes
D2: Season 2 | J2: Season 3 | P2: Season 4 Plus
B4: Week | C4: Song | D4: Artist | E4: Genre | F4: Year | H4: Week | I4: Song | J4: Artist | K4: Genre | L4: Year | N4: Week | O4: Song | P4: Artist | Q4: Genre | R4: Year
B5: 1 | C5: Stupid Girl | D5: Garbage | E5: Alternative | F5: 1995 | H5: 1 | I5: Johnny B. Goode | J5: Chuck Berry | K5: Classic Rock | L5: 1959 | N5: 1 | O5: 18 and Life | P5: Skid Row | Q5: Glam | R5: 1989
B6: 2 | C6: Stranglehold | D6: Ted Nugent | E6: Classic Rock | F6: 1975 | H6: 2 | I6: Play That Funky Music | J6: Wild Cherry | K6: R&B/Soul/Funk | L6: 1976 | N6: 2 | O6: Hooked On A Feeling | P6: Blue Suede | Q6: Classic Rock | R6: 1974
B7: 3 | C7: Ice Ice Baby | D7: Vanilla Ice | E7: Hip Hop/Rap | F7: 1990 | H7: 3 | I7: Blister In The Sun | J7: Violent Femmes | K7: Punk | L7: 1983 | N7: 3 | O7: Enjoy The Silence | P7: Depeche Mode | Q7: Pop/Dance/Electronic | R7: 1990
B8: 4 | C8: God Damn | D8: Avenged Sevenfold | E8: Metal | F8: 2016 | H8: 4 | I8: Karma Police | J8: Radiohead | K8: Alternative | L8: 1997 | N8: 4 | O8: I Remember You | P8: Skid Row | Q8: Glam | R8: 1989
B9: 5 | C9: Super Freak | D9: Rick James | E9: R&B/Soul/Funk | F9: 1981 | H9: 5 | I9: Save a Horse (Ride a Cowboy) | J9: Big & Rich | K9: Country | L9: 2004 | N9: 5 | O9: That Don't Impress Me Much | P9: Shania Twain | Q9: Country | R9: 1997
B10: 6 | C10: Burnin' for You | D10: Blue Oyster Cult | E10: Classic Rock | F10: 1981 | H10: 6 | I10: Twilght of the Thunder God | J10: Amon Amarth | K10: Metal | L10: 2008 | N10: 6 | O10: Lonely Is The Night | P10: Billy Squire | Q10: Classic Rock | R10: 1981
B11: 7 | C11: Heart of the Moment | D11: Asia | E11: Classic Rock | F11: 1982 | H11: 7 | I11: The Way You Used To Do | J11: Queens of the Stone Age | K11: Alternative | L11: 2017 | N11: 7 | O11: A Sky Full of Stars | P11: Coldplay | Q11: Alternative | R11: 2014
B12: 8 | C12: Down In a Hole | D12: Alice in Chains | E12: Grunge | F12: 1992 | H12: 8 | I12: Feel It Still | J12: Portugal. The Man | K12: Alternative | L12: 2017 | N12: 8 | O12: Absolutely (Story of a Girl) | P12: Nine Days | Q12: Alternative | R12: 2000
N13: 9 | O13: Unwell | P13: Matchbox Twenty | Q13: Alternative | R13: 2002
N14: 10 | O14: Broken | P14: Seether ft. Amy Lee | Q14: Rock | R14: 2004
D16: Season 5 | J16: Season 8 | P16: Season 9
B18: Week | C18: Song | D18: Artist | E18: Genre | F18: Year | H18: Week | I18: Song | J18: Artist | K18: Genre | L18: Year | N18: Week | O18: Song | P18: Artist | Q18: Genre | R18: Year
B19: 1 | C19: Unwritten | D19: Natasha Bedingfield | E19: Pop-Rock | F19: 2004 | H19: 1 | I19: Pictures of Girls | J19: Wallows | K19: Alternative | L19: 2018 | N19: 1 | O19: Girls Like You | P19: Maroon 5 | Q19: Pop-Rock | R19: 2017
B20: 2 | C20: Roll To Me | D20: Del Amitri | E20: Alternative | F20: 1995 | H20: 1 | I20: Simplify | J20: Young the Giant | K20: Alternative | L20: 2018 | N20: 2 | O20: Crazy On You | P20: Heart | Q20: Classic Rock | R20: 1976
B21: 3 | C21: Is She Really Going Out With Him | D21: Joe Jackson | E21: Classic Rock | F21: 1978 | H21: 2 | I21: HTML Rulez D00d | J21: The Devil Wears Prada | K21: Metal | L21: 2007 | N21: 3 | O21: Lose It | P21: Kane Brown | Q21: Country | R21: 2018
B22: 4 | C22: I Want You | D22: Savage Garden | E22: Pop-Rock | F22: 1997 | H22: 3 | I22: Unheavenly Creatures | J22: Coheed and Cambria | K22: Prog | L22: 2018 | N22: 3 | O22: Hotel Key | P22: Old Domination | Q22: Country | R22: 2018
B23: 5 | C23: Run-Around | D23: Blues Traveler | E23: Rock | F23: 1994 | H23: 3 | I23: When The Curtain Fall | J23: Greta Van Fleet | K23: Rock | L23: 2018 | N23: 4 | O23: Semi-Charmed Life '09 | P23: Third Eye Blind | Q23: Alternative | R23: 2009
B24: 6 | C24: Torn In Two | D24: Breaking Benjamin | E24: Rock | F24: 2018 | H24: 4 | I24: Business Time | J24: Flight of the Conchords | K24: Novelty | L24: 2008 | N24: 5 | O24: 99 | P24: Barns Country | Q24: Alternative | R24: 2018
B25: 7 | C25: Pictures of Matchstick Men | D25: Status Quo | E25: Classic Rock | F25: 1968 | H25: 5 | I25: Uncomfortable | J25: Halestorm | K25: Rock | L25: 2018 | N25: 5 | O25: Music Is Worth Living For | P25: Andrew W.K. | Q25: Rock | R25: 2018
B26: 8 | C26: Right Here, Right Now | D26: Jesus Jones | E26: Alternative | F26: 1990 | H26: 5 | I26: Graffiti | J26: CHVRCHES | K26: Alternative | L26: 2018 | N26: 6 | O26: Angel of Death | P26: Slayer | Q26: Metal | R26: 1986
H27: 6 | I27: Back to Me | J27: Of Mice & Men | K27: Metal | L27: 2018 | N27: 7 | O27: Starlight | P27: BABYMETAL | Q27: Metal | R27: 2018
H28: 7 | I28: Three Lives | J28: Octavision | K28: Prog | L28: 2016 | N28: 7 | O28: When Legends Rise | P28: Godsmack | Q28: Nu-Metal | R28: 2018
H29: 7 | I29: My Demons | J29: Starset | K29: Rock | L29: 2014 | N29: 8 | O29: Remedy | P29: Seether | Q29: Metal | R29: 2005
H30: 8 | I30: Little Black Backpack '09 | J30: Stroke 9 | K30: Rock | L30: 2010
D34: Season 10 | J34: Season 11 | P34: Season 12
B37: Week | C37: Song | D37: Artist | E37: Genre | F37: Year | H37: Week | I37: Song | J37: Artist | K37: Genre | L37: Year | N37: Week | O37: Song | P37: Artist | Q37: Genre | R37: Year
B38: 1 | C38: Shame | D38: Ellie King | E38: Alternative | F38: 2018 | H38: 1 | I38: I'm Gonna Be (500 Miles) | J38: The Proclaimers | K38: Rock | L38: 1988 | N38: 1 | O38: High Hopes | P38: Panic! At The Disco | Q38: Emo | R38: 2018
B39: 1 | C39: Body Talks | D39: The Struts | E39: Rock | F39: 2018 | H39: 2 | I39: Do Not Disturb | J39: Halestorm | K39: Rock | L39: 2018 | N39: 2 | O39: Change | P39: The Revivalists | Q39: Alternative | R39: 2018
B40: 2 | C40: The Triumph | D40: Jeff Williams ft. Casey Lee Williams | E40: Rock | F40: 2018 | H40: 3 | I40: Harmony Hall | J40: Vampire Weekend | K40: Indie Rock | L40: 2019 | N40: 3 | O40: 100 Days | P40: AJR | Q40: Pop-Rock | R40: 2019
B41: 3 | C41: The Reason | D41: Hoobastank | E41: Alternative | F41: 2004 | H41: 4 | I41: Longshot | J41: Catfish and the Bottlemen | K41: Indie Rock | L41: 2019 | N41: 4 | O41: Alligator | P41: Of Monsters and Men | Q41: Indie Rock | R41: 2019
B42: 4 | C42: Wagon Wheel | D42: Darius Rucker | E42: Country | F42: 2013 | H42: 5 | I42: Over My Head | J42: Judas & the Lion | K42: Alternative | L42: 2019 | N42: 5 | O42: Blame It On My Youth | P42: blink-182 | Q42: Punk | R42: 2019
B43: 5 | C43: Farewell, Mona Lisa | D43: The Dillinger Escape Plan | E43: Metal | F43: 2010 | H43: 6 | I43: Salvation | J43: The Strumbellas | K43: Alternative | L43: 2019 | N43: 6 | O43: Gloria | P43: The Lumineers | Q43: Indie Rock | R43: 2019
B44: 5 | C44: Bleed | D44: Meshuggah | E44: Metal | F44: 2008 | H44: 7 | I44: Tourniquet | J44: Breaking Benjamin | K44: Rock | L44: 2018 | N44: 7 | O44: Hurt | P44: Oliver Tree | Q44: Alternative | R44: 2019
B45: 6 | C45: MANTRA | D45: Bring Me The Horizon | E45: Nu-Metal | F45: 2019 | H45: 8 | I45: When Am I Going To Lose You? | J45: Local Natives | K45: Alternative | L45: 2019 | N45: 8 | O45: Missed Connections | P45: The Head and the Heart | Q45: Alternative | R45: 2019
B46: 7 | C46: Paradise | D46: Coldplay | E46: Alternative | F46: 2011 | H46: ??? | I46: ??? | J46: ??? | K46: ??? | L46: ???
B47: 8 | C47: When the Seasons Change | D47: Five Finger Death Punch | E47: Metal | F47: 2018
B48: 8 | C48: Superposition | D48: Young the Giant | E48: Alternative | F48: 2018
D52: Season 13 | J52: Apple Music Season | P52: Season 15
B54: Week | C54: Song | D54: Artist | E54: Genre | F54: Year | H54: Week | I54: Song | J54: Artist | K54: Genre | L54: Year | N54: Week | O54: Song | P54: Artist | Q54: Genre | R54: Year
B55: 1 | C55: sugar, honey, ice & tea | D55: Bring Me The Horizon | E55: Nu-Metal | F55: 2019 | H55: 1 | I55: Back Foot | J55: Dinosaur Pile-Up | K55: Rock | L55: 2019 | N55: 1 | O55: The End of the Game | P55: Weezer | Q55: Alternative | R55: 2020
B56: 1 | C56: When I'm Gone | D56: Dirty Honey | E56: Rock | F56: 2019 | H56: 1 | I56: Welcome Home | J56: HELLYEAH | K56: Rock | L56: 2019 | N56: 2 | O56: I Just Wanna Shine | P56: Fitz & The Tantrums | Q56: Pop-Rock | R56: 2019
B57: 2 | C57: Highway to Oblivion | D57: Dragonforce | E57: Metal | F57: 2019 | H57: 1 | I57: Taste of Regret | J57: Of Mice & Men | K57: Metal | L57: 2019 | N57: 3 | O57: All The Way (Stay) | P57: Jimmy Eat World | Q57: Alternative | R57: 2019
B58: 3 | C58: This City Made Us | D58: The Protomen | E58: Rock | F58: 2015 | H58: 2 | I58: Prom Queen | J58: Beach Bunny | K58: Alternative | L58: 2018 | N58: 4 | O58: Circles | P58: Post Malone | Q58: Pop-Rock | R58: 2019
B59: 4 | C59: Blue on Black | D59: Five Finger Death Punch | E59: Metal | F59: 2017 | H59: 2 | I59: Panic Attack | J59: The Glorious Songs | K59: Rock | L59: 2019 | N59: 5 | O59: Where I Belong (Ft. We The Kings) | P59: Simple Plan & The State Champs | Q59: Alternative | R59: 2019
B60: 6 | C60: Might Be Right | D60: White Reaper | E60: Alternative | F60: 2019 | H60: 2 | I60: 16 | J60: Highly Suspect | K60: Alternative | L60: 2019 | N60: 6 | O60: No More Mr. Nice Guy | P60: Alice Cooper | Q60: Rock | R60: 1973
B61: 6 | C61: You're Gonna Say Yeah! | D61: Hushpuppies | E61: Rock | F61: 2005 | H61: 3 | I61: Crush | J61: Dave Matthews Band | K61: Rock | L61: 1998 | N61: 7 | O61: 50,000 Unstoppable Watts | P61: Clutch | Q61: Rock | R61: 2009
B62: 7 | C62: Feed My Frankenstein | D62: Alice Cooper | E62: Rock | F62: 1991 | H62: 3 | I62: Blind Leading the Blind | J62: Mumford & Sons | K62: Rock | L62: 2018 | N62: 8 | O62: Inside Out | P62: Five Finger Death Punch | Q62: Metal | R62: 2020
B63: 7 | C63: Unsainted | D63: Slipknot | E63: Nu-Metal | F63: 2019 | H63: 3 | I63: One Kind of Solomon | J63: The New Pornographers | K63: Alternative | L63: 2019 | N63: 8 | O63: Novocaine | P63: The Unlikely Candidates | Q63: Alternative | R63: 2019
B64: 8 | C64: CHAMPION | D64: Bishop Briggs | E64: Alternative | F64: 2019 | H64: 4 | I64: Bad Guy | J64: Billie Eillish | K64: Pop/Dance/Electronic | L64: 2019
B65: 8 | C65: Good Things Fall Apart | D65: ILLENIUM & Jon Bellion | E65: Pop/Dance/Electronic | F65: 2019 | H65: 4 | I65: Orphans | J65: Coldplay | K65: Alternative | L65: 2019
H66: 4 | I66: Take What You Want | J66: Post Malone ft. Ozzy Osbourne and Travis Scott | K66: Pop-Rock | L66: 2019
D69: Season 16 | J69: Season 16 Plus | P69: Season 17 Plus
B71: Week | C71: Song | D71: Artist | E71: Genre | F71: Year | H71: Week | I71: Song | J71: Artist | K71: Genre | L71: Year | N71: Week | O71: Song | P71: Artist | Q71: Genre | R71: Year
B72: 1 | C72: The Best | D72: AWOLNATION | E72: Alternative | F72: 2019 | H72: 1 | I72: The Best | J72: AWOLNATION | K72: Alternative | L72: 2019 | N72: 1 | O72: Far Away | P72: Breaking Benjamin ft. Scooter Ward of COLD | Q72: Rock | R72: 2020
B73: 1 | C73: Colors | D73: Black Pumas | E73: Alternative | F73: 2019 | H73: 1 | I73: Colors | J73: Black Pumas | K73: Alternative | L73: 2019 | N73: 1 | O73: Level of Concern | P73: Twenty One Pilots | Q73: Alternative | R73: 2020
B74: 2 | C74: Some Kind of Diaster | D74: All Time Low | E74: Emo | F74: 2020 | H74: 2 | I74: Some Kind of Disaster | J74: All Time Low | K74: Emo | L74: 2020 | N74: 2 | O74: Where Were You | P74: Every Avenue | Q74: Alternative | R74: 2008
B75: 3 | C75: Abigail | D75: Motionless in White | E75: Metal | F75: 2010 | H75: 2 | I75: Better Off This Way | J75: A Day to Remember | K75: Punk | L75: 2010 | N75: 2 | O75: Falling | P75: Trevor Daniel | Q75: Pop/Dance/Electronic | R75: 2020
B76: 4 | C76: Simmer | D76: Hayley Williams | E76: Alternative | F76: 2020 | H76: 3 | I76: Abigail | J76: Motionless in White | K76: Metal | L76: 2010 | N76: 3 | O76: I Think We're Alone Now | P76: Bille Joe Armstrong | Q76: Alternative | R76: 2020
B77: 5 | C77: One Man Band | D77: Old Dominion | E77: Country | F77: 2019 | H77: 3 | I77: Approach the Podium | J77: Winds of Plague | K77: Metal | L77: 2009 | N77: 3 | O77: Van Horn | P77: Saint Motel | Q77: Indie Rock | R77: 2019
B78: 6 | C78: Bad Decisions | D78: The Strokes | E78: Rock | F78: 2020 | H78: 4 | I78: Simmer | J78: Hayley Williams | K78: Alternative | L78: 2020 | N78: 4 | O78: Dark Horse | P78: Converge | Q78: Metal | R78: 2009
B79: 7 | C79: Born to be Wild | D79: Steppenwolf | E79: Classic Rock | F79: 1968 | H79: 4 | I79: Don't Start Now | J79: Dua Lipa | K79: Pop/Dance/Electronic | L79: 2019 | N79: 4 | O79: Popular Monstar | P79: Falling in Reverse | Q79: Metal | R79: 2019
B80: 8 | C80: Rolling 7's | D80: Dirty Honey | E80: Rock | F80: 2019 | H80: 5 | I80: One Man Band | J80: Old Dominion | K80: Country | L80: 2019 | N80: 5 | O80: 10,000 Hours | P80: Dan + Shay & Justin Bieber | Q80: Country | R80: 2019
H81: 5 | I81: Boy | J81: Ra Ra Riot | K81: Indie Rock | L81: 2010 | N81: 5 | O81: Used to Like | P81: Neon Trees | Q81: Alternative | R81: 2019
H82: 6 | I82: Bad Decisions | J82: The Strokes | K82: Alternative | L82: 2020 | N82: 6 | O82: Bang! | P82: AJR | Q82: Pop-Rock | R82: 2020
H83: 6 | I83: Juice | J83: Lizzo | K83: Pop/Dance/Electronic | L83: 2019 | N83: 6 | O83: Incubus | P83: Amberian Dawn | Q83: Metal | R83: 2009
H84: 7 | I84: Born to be Wild | J84: Steppenwolf | K84: Classic Rock | L84: 1968 | N84: 7 | O84: Adore You | P84: Harry Styles | Q84: Pop/Dance/Electronic | R84: 2019
H85: 7 | I85: Alive & Kicking | J85: Nonpoint | K85: Rock | L85: 2005 | N85: 7 | O85: Wars | P85: Of Monsters and Men | Q85: Indie Rock | R85: 2019
H86: 8 | I86: Rolling 7's | J86: Dirty Honey | K86: Rock | L86: 2019 | N86: 8 | O86: Killing Me Slowly | P86: Bad Wolves | Q86: Rock | R86: 2019
H87: 8 | I87: Special Effects | J87: Freezepop | K87: Pop/Dance/Electronic | L87: 2010 | N87: 8 | O87: Learn to Live | P87: Architects | Q87: Metal | R87: 2012
D91: Season 18 | J91: Season 19 | P91: Season 20
B93: Week | C93: Song | D93: Artist | E93: Genre | F93: Year | H93: Week | I93: Song | J93: Artist | K93: Genre | L93: Year | N93: Week | O93: Song | P93: Artist | Q93: Genre | R93: Year
B94: 1 | C94: Cradles | D94: Sub Urdban | E94: Pop/Dance/Electronic | F94: 2019 | H94: 1 | I94: The Devil Went Down to Georgia | J94: Nickelback | K94: Rock | L94: 2020 | N94: 1 | O94: Let the Games Begin | P94: Anarbor | Q94: Alternative | R94: 2010
B95: 1 | C95: Blinding Lights | D95: The Weeknd | E95: Pop/Dance/Electronic | F95: 2020 | H95: 1 | I95: A Little Bit Off | J95: Five Finger Death Punch | K95: Metal | L95: 2020 | N95: 1 | O95: bloody valentine | P95: Machine Gun Kelly | Q95: Alternative | R95: 2020
B96: 2 | C96: We Are The One | D96: Anti-Flag | E96: Punk | F96: 2009 | H96: 2 | I96: CITY OF ANGELS | J96: 24kGoldn | K96: Hip-Hop/Rap | L96: 2019 | N96: 2 | O96: All Downhill from Here | P96: New Found Glory | Q96: Punk | R96: 2004
B97: 2 | C97: Hostory of Violence | D97: Theory of a Deadman | E97: Rock | F97: 2020 | H97: 2 | I97: Spin | J97: We the Kings | K97: Alternative | L97: 2009 | N97: 2 | O97: Greatest of All Time | P97: New Found Glory | Q97: Punk | R97: 2020
B98: 3 | C98: Antisocialist | D98: Asking Alexandria | E98: Metal | F98: 2020 | H98: 3 | I98: White Knuckles | J98: OK Go | K98: Alternative | L98: 2010 | N98: 2 | O98: My Friends Over You | P98: New Found Glory | Q98: Punk | R98: 2002
B99: 3 | C99: Deathbead Atheist | D99: Norma Jean | E99: Metal | F99: 2010 | H99: 3 | I99: Caution | J99: The Killers | K99: Alternative | L99: 2020 | N99: 3 | O99: To The Stage | P99: Asking Alexandria | Q99: Metal | R99: 2011
B100: 4 | C100: Monsters | D100: All Time Low ft. Blackbear | E100: Emo | F100: 2020 | H100: 4 | I100: Cute without the 'E' (Cut from the Team) | J100: Taking Back Sunday | K100: Emo | L100: 2002 | N100: 3 | O100: Visitor | P100: Of Mosnters and Men | Q100: Alternative | R100: 2020
B101: 4 | C101: Flightless Bird, American Mouth | D101: Iron & Wine | E101: Indie Rock | F101: 2007 | H101: 4 | I101: Alive With the Glory of Love | J101: Say Anything | K101: Emo | L101: 2004 | N101: 4 | O101: Sick, Sick, Sick | P101: Bayside | Q101: Alternative | R101: 2011
B102: 5 | C102: I Hope | D102: Gaby Barrett | E102: Country | F102: 2020 | H102: 5 | I102: Shot in the Dark | J102: AC/DC | K102: Rock | L102: 2020 | N102: 4 | O102: ily (i love you baby) | P102: Surf Mesa ft Emilee | Q102: Pop/Dance/Electronic | R102: 2019
B103: 5 | C103: I Know What I Am | D103: Band of Skulls | E103: Indie Rock | F103: 2009 | H103: 5 | I103: Death by Rock and Roll | J103: The Pretty Reckless | K103: Rock | L103: 2020 | N103: 4 | O103: Take Me Home, Country Road | P103: John Denvers | Q103: Country | R103: 1971
B104: 6 | C104: Angles & Demons | D104: jxden | E104: Alternative | F104: 2020 | H104: 6 | I104: Rollin' (Air Raid) | J104: Limp Bizkit | K104: Alternative | L104: 2000 | N104: 5 | O104: The Bad Touch | P104: The Bloodhound Gang | Q104: Pop/Dance/Electronic | R104: 1999
B105: 6 | C105: Stand for Something | D105: Skindred | E105: Metal | F105: 2009 | H105: 6 | I105: Come & Go | J105: Juice WRLD & Marshmellow | K105: Hip-Hop/Rap | L105: 2020 | N105: 5 | O105: Let My Love Open The Door | P105: Pete Townshend | Q105: New Wave | R105: 1980
... B107: 8 | C107: Teenage Dirtbag (2020) | D107: Wheatus | E107: Pop-Rock | F107: 2020 | H107: 7 | I107: My Way, Soon | J107: Greta Van Fleet | K107: Rock | L107: 2020 | N107: 6 | O107: Smash the Control Machine | P107: Otep | Q107: Metal | R107: 2009
H108: 8 | I108: Stacy's Mom | J108: Fountains of Wayne | K108: Pop-Rock | L108: 2003 | N108: 7 | O108: Help I'm Alive | P108: Metric | Q108: Alternative | R108: 2009
H109: 8 | I109: Prisoner | J109: Dance Gavin Dance | K109: Indie Rock | L109: 2020 | N109: 7 | O109: Dreamchaser | P109: Amberian Dawn | Q109: Metal | R109: 2008
N110: 8 | O110: Younger Lungs | P110: Less Than Jake | Q110: Reggae/Ska | R110: 2012
N111: 8 | O111: Superman | P111: Goldfinger | Q111: Reggae/Ska | R111: 1997
D113: Season 21 | J113: Season 22 | P113: Season 23
B115: Week | C115: Song | D115: Artist | E115: Genre | F115: Year | H115: Week | I115: Song | J115: Artist | K115: Genre | L115: Year | N115: Week | O115: Song | P115: Artist | Q115: Genre | R115: Year
B116: 1 | C116: Way Less Sad | D116: AJR | E116: Pop-Rock | F116: 2021 | H116: 1 | I116: Shipwrecked | J116: Alestorm | K116: Metal | L116: 2011 | N116: 0 | O116: Far Too Near | P116: AFI | Q116: Rock | R116: 2021
B117: 1 | C117: Aspiration | D117: After the Burial | E117: Metal | F117: 2009 | H117: 1 | I117: Heat Waves | J117: Glass Animals | K117: Alternative | L117: 2020 | N117: 0 | O117: Devil On My Shoulder | P117: Kelsy Karter | Q117: Rock | R117: 2020
B118: 2 | C118: my ex's best friend | D118: Machine Gun Kelly & blackbear | E118: Alternative | F118: 2020 | H118: 2 | I118: And So It Went | J118: The Pretty Reckless ft. Tom Morello | K118: Rock | L118: 2021 | N118: 0 | O118: Shake Me Up | P118: HOUNDS | Q118: Rock | R118: 2017
B119: 2 | C119: Leaderless and Self Enlisted | D119: Norma Jean | E119: Metal | F119: 2010 | H119: 2 | I119: What's Left of Me | J119: blessthefall | K119: Alternative | L119: 2009 | N119: 0 | O119: Kids of Summer | P119: Mayday Parade | Q119: Rock | R119: 2021
B120: 3 | C120: Dear Maria, Count Me In | D120: All Time Low | E120: Emo | F120: 2007 | H120: 3 | I120: Follow You | J120: Imagine Dragons | K120: Alternative | L120: 2021 | N120: 1 | O120: Tailspin | P120: Calling All Captains | Q120: Rock | R120: 2021
B121: 3 | C121: The One You Want | D121: The Get Up Kids | E121: Rock | F121: 2004 | H121: 3 | I121: The Complexity of Light | J121: Children of Nova | K121: Prog | L121: 2009 | N121: 1 | O121: The Bird and The Worm | P121: The Used | Q121: Emo | R121: 2007
B122: 4 | C122: Mindreader | D122: A Day to Remember | E122: Punk | F122: 2021 | H122: 4 | I122: Astronaut In The Ocean | J122: Masked Wolf | K122: Hip-Hop/Rap | L122: 2019 | N122: 2 | O122: take my breath away / / noose | P122: Capstan | Q122: Rock | R122: 2021
B123: 4 | C123: Resentment | D123: A Day to Remember | E123: Punk | F123: 2021 | H123: 4 | I123: Astronaut In The Ocean | J123: Our Last Night | K123: Metal | L123: 2021 | N123: 2 | O123: We Are Between | P123: Modest Mouse | Q123: Indie Rock | R123: 2021
...

Sheet RB1
A1: 88
B2: Song | C2: Artist | D2: Release Date | E2: Source | F2: Notes
B3: Day Late, Dollar Short | C3: The Acro-Brats | D3: 42465 | E3: DLC | F3: Part of "30 Song Mega Pack"
B4: Train Kept A-Rollin' | C4: Aerosmith
B5: Blood Doll | C5: Anarchy Club | D5: 42465 | E5: DLC | F5: Part of "30 Song Mega Pack"
B6: Pleasure (Pleasure) | C6: Bang Camaro | D6: 42465 | E6: DLC | F6: Part of "30 Song Mega Pack"
B7: Sabotage | C7: Beastie Boys | D7: 44882 | E7: DLC | F7: Part of "Rock Band Rewind Pack 01" and "Rock Band 15th Anniversary"
B8: Paranoid | C8: Black Sabbath
B9: (Don't Fear) The Reaper | C9: Blue Öyster Cult | D9: 42754 | E9: DLC | F9: Part of "Solid '70s 01"
B10: Wanted Dead or Alive | C10: Bon Jovi | D10: 40491 | E10: DLC | F10: Part of "Bon Jovi Greatest Hits" Album
B11: Foreplay/Long Time | C11: Boston | D11: 44882 | E11: DLC | F11: Part of "Rock Band Rewind Pack 01" and "Rock Band 15th Anniversary"
B12: Should I Stay or Should I Go | C12: The Clash
B13: Welcome Home | C13: Coheed and Cambria | D13: 44735 | E13: DLC | F13: DLC Single
B14: Nightmare | C14: Crooked X
B15: Suffragette City | C15: David Bowie | D15: 43090 | E15: DLC | F15: DLC Single and part of "Rock Band Hits Pack"
B16: Can't Let Go | C16: Death of the Cool | D16: 42465 | E16: DLC | F16: Part of "30 Song Mega Pack"
B17: Highway Star | C17: Deep Purple
B18: Epic | C18: Faith No More
B19: Dead on Arrival | C19: Fall Out Boy | D19: 44882 | E19: DLC | F19: Part of "Rock Band Rewind Pack 01" and "Rock Band 15th Anniversary"
B20: I'm So Sick | C20: Flyleaf
B21: Learn to Fly | C21: Foo Fighters | D21: 43489 | E21: DLC | F21: DLC Single
B22: Brainpower | C22: Freezepop | D22: 42465 | E22: DLC | F22: Part of "30 Song Mega Pack"
B23: I Think I'm Paranoid | C23: Garbage
B24: Main Offender | C24: The Hives
B25: Celebrity Skin | C25: Hole
B26: I Get By | C26: Honest Bob and the Factory-to-Dealer Incentives | D26: 42465 | E26: DLC | F26: Part of "30 Song Mega Pack"
B27: Run to the Hills | C27: Iron Maiden | D27: 39973 | E27: DLC | F27: Part of "Iron Maiden Pack 01"
B28: Are You Gonna Be My Girl | C28: Jet | H28: Rock Band 1
B29: When You Were Young | C29: The Killers | D29: 43069 | E29: DLC | F29: DLC Single | H29: 39406
B30: Detroit Rock City | C30: Kiss
B31: 29 Fingers | C31: The Konks
B32: Enter Sandman | C32: Metallica
B33: Flirtin' with Disaster | C33: Molly Hatchet
B34: Time We Had | C34: The Mother Hips
B35: Mississippi Queen | C35: Mountain
B36: Electric Version | C36: The New Pornographers
B37: The Hand That Feeds | C37: Nine Inch Nails | D37: 43489 | E37: DLC | F37: DLC Single
B38: In Bloom | C38: Nirvana
B39: Here It Goes Again | C39: OK Go
B40: Green Grass and High Tides | C40: The Outlaws
B41: Wave of Mutilation | C41: Pixies
B42: Next to You | C42: The Police
B43: Go with the Flow | C43: Queens of the Stone Age | D43: 44882 | E43: DLC | F43: Part of "Rock Band Rewind Pack 01" and "Rock Band 15th Anniversary"
B44: Orange Crush | C44: R.E.M.
B45: Creep | C45: Radiohead | D45: 43228 | E45: DLC | F45: DLC Single and part of "Rock Band Hits Pack"
B46: Blitzkrieg Bop | C46: Ramones
B47: Dani California | C47: Red Hot Chili Peppers
B48: Gimme Shelter | C48: The Rolling Stones
B49: Tom Sawyer | C49: Rush | D49: 39714 | E49: DLC | F49: Part of "Moving Pictures" Album
B50: Cherub Rock | C50: Smashing Pumpkins | D50: 44882 | E50: DLC | F50: Part of "Rock Band Rewind Pack 01" and "Rock Band 15th Anniversary"
B51: Black Hole Sun | C51: Soundgarden
B52: Vasoline | C52: Stone Temple Pilots | D52: 45274 | E52: DLC | F52: DLC Single
B53: Reptilia | C53: The Strokes | D53: 43237 | E53: DLC | F53: DLC Single
B54: Ballroom Blitz | C54: Sweet
B55: Timmy and the Lords of the Underworld | C55: Timmy and the Lords of the Underworld
B56: Outside | C56: Tribe | D56: 42465 | E56: DLC | F56: Part of "30 Song Mega Pack"
B57: Seven | C57: Vagiant | D57: 42465 | E57: DLC | F57: Part of "30 Song Mega Pack"
B58: Won't Get Fooled Again | C58: The Who | D58: 42992 | E58: DLC | F58: DLC Single
B59: Say It Ain't So | C59: Weezer | D59: 43055 | E59: DLC | F59: Part of "Back in the '90's Pack 01"
B60: Maps | C60: Yeah Yeah Yeahs
B63: Songs Released | C63: =COUNT(D:D) -> 27
B64: Total Songs | C64: 58
B65: Percent Complete | C65: =IFERROR(__xludf.DUMMYFUNCTION("TO_PERCENT(C63/C64)"),0.46551724137931033) -> 0.46551724

Sheet Spotlight Rating
A1: Love | B1: 2
A2: 1 | B2: Shipwrecked | C2: Alestorm | D2: Metal | E2: 2011
A3: 7 | B3: Feed My Frankenstein | C3: Alice Cooper | D3: Rock | E3: 1991
A4: 6 | B4: No More Mr. Nice Guy | C4: Alice Cooper | D4: Rock | E4: 1973
A5: 3 | B5: Dear Maria, Count Me In | C5: All Time Low | D5: Emo | E5: 2007
A6: 6 | B6: Twilght of the Thunder God | C6: Amon Amarth | D6: Metal | E6: 2008
A7: 5 | B7: Music Is Worth Living For | C7: Andrew W.K. | D7: Rock | E7: 2018
A8: 8 | B8: Learn to Live | C8: Architects | D8: Metal | E8: 2012
A9: 5 | B9: I Know What I Am | C9: Band of Skulls | D9: Indie Rock | E9: 2009
A10: 5 | B10: Fight for Your Right | C10: Beastie Boys | D10: Hip-Hop/Rap | E10: 1986
A11: 1 | B11: Devils Haircut | C11: Beck | D11: Alternative | E11: 1996
A12: 5 | B12: The Bad Touch | C12: The Bloodhound Gang | D12: Pop/Dance/Electronic | E12: 1999
A13: 6 | B13: Burnin' for You | C13: Blue Oyster Cult | D13: Classic Rock | E13: 1981
... A46: 3 | B46: Blister In The Sun | C46: Violent Femmes | D46: Punk | E46: 1983
A50: Like | B50: 1
A51: 2 | B51: CITY OF ANGELS | C51: 24kGoldn | D51: Hip-Hop/Rap | E51: 2019
A52: 0 | B52: Far Too Near | C52: AFI | D52: Rock | E52: 2021
A53: 1 | B53: Aspiration | C53: After the Burial | D53: Metal | E53: 2009
A54: 8 | B54: Down In a Hole | C54: Alice in Chains | D54: Grunge | E54: 1992
A55: 2 | B55: Flavor of the Weak | C55: American Hi-Fi | D55: Punk | E55: 2001
A56: 2 | B56: We Are The One | C56: Anti-Flag | D56: Punk | E56: 2009
A57: 7 | B57: Heart of the Moment | C57: Asia | D57: Classic Rock | E57: 1982
A58: 7 | B58: Starlight | C58: BABYMETAL | D58: Metal | E58: 2018
A59: 4 | B59: Sick, Sick, Sick | C59: Bayside | D59: Alternative | E59: 2011
A60: 2 | B60: Prom Queen | C60: Beach Bunny | D60: Alternative | E60: 2018
A61: 6 | B61: Lonely Is The Night | C61: Billy Squire | D61: Classic Rock | E61: 1981
A62: 8 | B62: CHAMPION | C62: Bishop Briggs | D62: Alternative | E62: 2019
... A122: 1 | B122: Simplify | C122: Young the Giant | D122: Alternative | E122: 2018
A126: Nuetral | B126: 0
A127: 5 | B127: Shot in the Dark | C127: AC/DC | D127: Rock | E127: 2020
A128: 6 | B128: Running With The Wild Things | C128: Against The Current | D128: Pop-Rock | E128: 2016
A129: 2 | B129: Some Kind of Disaster | C129: All Time Low | D129: Emo | E129: 2020
A130: 4 | B130: Monsters | C130: All Time Low ft. Blackbear | D130: Emo | E130: 2020
A131: 7 | B131: Dreamchaser | C131: Amberian Dawn | D131: Metal | E131: 2008
A132: 7 | B132: Kokko - Eagle of Fire | C132: Amberian Dawn | D132: Metal | E132: 2009
A133: 6 | B133: Incubus | C133: Amberian Dawn | D133: Metal | E133: 2009
A134: 1 | B134: Let the Games Begin | C134: Anarbor | D134: Alternative | E134: 2010
A135: 8 | B135: Energy | C135: The Apples in Stereo | D135: Pop-Rock | E135: 2007
A136: 1 | B136: The Best | C136: AWOLNATION | D136: Alternative | E136: 2019
A137: 9 | B137: Hazy Shade of Winter | C137: The Bangles | D137: Rock | E137: 1987
A138: 5 | B138: Save a Horse (Ride a Cowboy) | C138: Big & Rich | D138: Country | E138: 2004
... A192: 8 | B192: Superposition | C192: Young the Giant | D192: Alternative | E192: 2018
A196: Dislike | B196: -1
A197: 6 | B197: Too Little Too Late | C197: A Skylight Drive | D197: Alternative | E197: 2011
A198: 3 | B198: 100 Days | C198: AJR | D198: Pop-Rock | E198: 2019
A199: 2 | B199: Euphoria | C199: Angels & Airwaves | D199: Alternative | E199: 2021
A200: 8 | B200: Animals | C200: Architects | D200: Metal | E200: 2021
A201: 3 | B201: To The Stage | C201: Asking Alexandria | D201: Metal | E201: 2011
A202: 8 | B202: Someone to You | C202: BANNERS | D202: Alternative | E202: 2019
A203: 5 | B203: 99 | C203: Barns Country | D203: Alternative | E203: 2018
A204: 4 | B204: Bad Guy | C204: Billie Eillish | D204: Pop/Dance/Electronic | E204: 2019
A205: 2 | B205: Hooked On A Feeling | C205: Blue Suede | D205: Classic Rock | E205: 1974
A206: 6 | B206: MANTRA | C206: Bring Me The Horizon | D206: Nu-Metal | E206: 2019
A207: 1 | B207: Tailspin | C207: Calling All Captains | D207: Rock | E207: 2021
A208: 2 | B208: take my breath away / / noose | C208: Capstan | D208: Rock | E208: 2021
A209: 2 | B209: Roll To Me | C209: Del Amitri | D209: Alternative | E209: 1995
A210: 1 | B210: When I'm Gone | C210: Dirty Honey | D210: Rock | E210: 2019
A211: 7 | B211: The Call | C211: Ego Kills Talent | D211: Rock | E211: 2021
A212: 10 | B212: Cold Heart (PNAU Remix) | C212: Elton John - Dua Lipa | D212: Pop/Dance/Electronic | E212: 2021
A213: 8 | B213: Stacy's Mom | C213: Fountains of Wayne | D213: Pop-Rock | E213: 2003
A214: 5 | B214: I Hope | C214: Gaby Barrett | D214: Country | E214: 2020
A215: 1 | B215: Heat Waves | C215: Glass Animals | D215: Alternative | E215: 2020
A216: 2 | B216: 16 | C216: Highly Suspect | D216: Alternative | E216: 2019
A217: 3 | B217: Follow You | C217: Imagine Dragons | D217: Alternative | E217: 2021
A218: 8 | B218: Right Here, Right Now | C218: Jesus Jones | D218: Alternative | E218: 1990
A219: 3 | B219: Is She Really Going Out With Him | C219: Joe Jackson | D219: Classic Rock | E219: 1978
A220: 5 | B220: Over My Head | C220: Judas & the Lion | D220: Alternative | E220: 2019
A221: 0 | B221: Kids of Summer | C221: Mayday Parade | D221: Rock | E221: 2021
A222: 6 | B222: Fatal Illusion | C222: Megadeth | D222: Metal | E222: 2016
A223: 5 | B223: Bleed | C223: Meshuggah | D223: Metal | E223: 2008
A224: 2 | B224: We Are Between | C224: Modest Mouse | D224: Indie Rock | E224: 2021
A225: 3 | B225: Abigail | C225: Motionless in White | D225: Metal | E225: 2010
A226: 1 | B226: The Devil Went Down to Georgia | C226: Nickelback | D226: Rock | E226: 2020
A227: 7 | B227: Alive & Kicking | C227: Nonpoint | D227: Rock | E227: 2005
A228: 3 | B228: Hotel Key | C228: Old Domination | D228: Country | E228: 2018
... A237: 1 | B237: Pictures of Girls | C237: Wallows | D237: Alternative | E237: 2018
A241: Hate | B241: -2
A242: 2 | B242: Better Off This Way | C242: A Day to Remember | D242: Punk | E242: 2010
A243: 4 | B243: Mindreader | C243: A Day to Remember | D243: Punk | E243: 2021
A244: 4 | B244: Paranoia | C244: A Day to Remember | D244: Punk | E244: 2016
A245: 4 | B245: Resentment | C245: A Day to Remember | D245: Punk | E245: 2021
A246: 6 | B246: Bang! | C246: AJR | D246: Pop-Rock | E246: 2020
A247: 1 | B247: Way Less Sad | C247: AJR | D247: Pop-Rock | E247: 2021
A248: 3 | B248: Antisocialist | C248: Asking Alexandria | D248: Metal | E248: 2020
A249: 4 | B249: God Damn | C249: Avenged Sevenfold | D249: Metal | E249: 2016
A250: 8 | B250: Killing Me Slowly | C250: Bad Wolves | D250: Rock | E250: 2019
A251: 2 | B251: What's Left of Me | C251: blessthefall | D251: Alternative | E251: 2009
A252: 5 | B252: Blame It On My Youth | C252: blink-182 | D252: Punk | E252: 2019
A253: 6 | B253: Torn In Two | C253: Breaking Benjamin | D253: Rock | E253: 2018
... A307: 10 | B307: Let Go | C307: Potty Mouth | D307: Pop-Rock | E307: 2021

Sheet RB2
B2: Song | C2: Artist | D2: Release Date | E2: Source | F2: Notes
B3: Visions | C3: Abnormality
B4: Let There Be Rock | C4: AC/DC
B5: Girl's Not Grey | C5: AFI
B6: You Oughta Know | C6: Alanis Morissette | D6: 45092 | E6: DLC | F6: DLC Single
B7: Man in the Box | C7: Alice in Chains | D7: 43020 | E7: DLC | F7: Part of "Alice in Chains Pack 03" and "Guitar Glory Pack"
B8: Ramblin' Man | C8: The Allman Brothers Band
B9: Get Clean | C9: Anarchy Club | D9: 42465 | E9: DLC | F9: Part of "30 Song Mega Pack"
B10: Almost Easy | C10: Avenged Sevenfold
B11: Shooting Star | C11: Bad Company
B12: Night Lies | C12: Bang Camaro | D12: 42465 | E12: DLC | F12: Part of "30 Song Mega Pack"
B13: So What'cha Want | C13: Beastie Boys
B14: E-Pro | C14: Beck
B15: White Wedding (Part 1) | C15: Billy Idol | D15: 45183 | E15: DLC | F15: DLC Single
B16: Rebel Girl | C16: Bikini Kill
B17: One Way or Another | C17: Blondie | D17: 42831 | E17: DLC | F17: DLC Single
B18: Tangled Up in Blue | C18: Bob Dylan
B19: Livin' on a Prayer | C19: Bon Jovi | D19: 41222 | E19: DLC | F19: Part of "Bon Jovi Greatest Hits" Album
B20: Shoulder to the Plow | C20: Breaking Wheel | D20: 42465 | E20: DLC | F20: Part of "30 Song Mega Pack"
B21: Hello There | C21: Cheap Trick | D21: 44917 | E21: DLC | F21: DLC Single
B22: Uncontrollable Urge | C22: Devo
B23: Feel the Pain | C23: Dinosaur Jr.
B24: Down with the Sickness | C24: Disturbed | D24: 42922 | E24: DLC | F24: DLC Single
B25: New Kid in School | C25: The Donnas
B26: Panic Attack | C26: Dream Theater
B27: Hungry Like the Wolf | C27: Duran Duran | D27: 43228 | E27: DLC | F27: DLC Single
B28: Pump It Up | C28: Elvis Costello | H28: Rock Band 2
B29: Go Your Own Way | C29: Fleetwood Mac | D29: 42915 | E29: DLC | F29: DLC SIngle | H29: 39705
B30: Everlong | C30: Foo Fighters | D30: 43090 | E30: DLC | F30: DLC Single and part of "Rock Band Hits Pack"
B31: We Got the Beat | C31: Go-Go's | D31: 43104 | E31: DLC | F31: DLC Single
B32: Alabama Getaway | C32: The Grateful Dead
B33: American Woman | C33: The Guess Who
B34: Shackler's Revenge | C34: Guns N' Roses
B35: PDA | C35: Interpol
B36: Mountain Song | C36: Jane's Addiction
B37: Aqualung | C37: Jethro Tull
B38: Bad Reputation | C38: Joan Jett | D38: 43048 | E38: DLC | F38: DLC Single
B39: The Middle | C39: Jimmy Eat World | D39: 43060 | E39: DLC | F39: DLC Single
B40: Any Way You Want It | C40: Journey
B41: Painkiller | C41: Judas Priest
B42: Carry On Wayward Son | C42: Kansas | D42: 42754 | E42: DLC | F42: Part of "Solid '70s Pack 01"
B43: Pretend We're Dead | C43: L7
B44: Our Truth | C44: Lacuna Coil
B45: Welcome to the Neighborhood | C45: Libyans
B46: One Step Closer | C46: Linkin Park | D46: 43426 | E46: DLC | F46: DLC Single
B47: My Own Worst Enemy | C47: Lit | D47: 42796 | E47: DLC | F47: DLC Single
B48: De-Luxe | C48: Lush
B49: A Jagged Gorgeous Winter | C49: The Main Drag | D49: 42465 | E49: DLC | F49: Part of "30 Song Mega Pack"
B50: Colony of Birchmen | C50: Mastodon
B51: Peace Sells | C51: Megadeth | D51: 43468 | E51: DLC | F51: DLC Single
B52: Battery | C52: Metallica
B53: Where'd You Go? | C53: The Mighty Mighty Bosstones
B54: Float On | C54: Modest Mouse
B55: Ace of Spades '08 | C55: Motörhead | D55: 42789 | E55: DLC | F55: DLC Single
B56: Kids in America | C56: The Muffs
B57: Drain You | C57: Nirvana
B58: Spirit in the Sky | C58: Norman Greenbaum
B59: Come Out and Play (Keep 'Em Separated) | C59: The Offspring | D59: 43426 | E59: DLC | F59: DLC Single
B60: Nine in the Afternoon | C60: Panic! at the Disco | D60: 42782 | E60: DLC | F60: DLC Single
B61: That's What You Get | C61: Paramore | D61: 42803 | E61: DLC | F61: DLC Single
B62: Alive | C62: Pearl Jam
B63: Lump | C63: Presidents of the United States of America
B64: Testify | C64: Rage Against the Machine | D64: 42943 | E64: DLC | F64: DLC Single
B65: Round and Round | C65: Ratt | D65: 42768 | E65: DLC | F65: DLC Single and part of "Guitar Glory Pack"
B66: Give It Away | C66: Red Hot Chili Peppers | D66: 41338 | E66: DLC | F66: DELISTED
B67: Alex Chilton | C67: The Replacements
B68: Give It All | C68: Rise Against
B69: The Trees (Vault Edition) | C69: Rush
B70: Lazy Eye | C70: Silversun Pickups
B71: Today | C71: The Smashing Pumpkins
B72: I Was Wrong | C72: Social Distortion
B73: Teen Age Riot | C73: Sonic Youth
B74: Spoonman | C74: Soundgarden | D74: 41149 | E74: DLC | F74: DLC Single and part of "Rock Band Blitz"
B75: Conventional Lover | C75: Speck | D75: 42465 | E75: DLC | F75: Part of "30 Song Mega Pack"
B76: Cool for Cats | C76: Squeeze
B77: Bodhisattva | C77: Steely Dan
B78: Rock'n Me | C78: Steve Miller Band
B79: Supreme Girl | C79: The Sterns
B80: Eye of the Tiger | C80: Survivor | D80: 43013 | E80: DLC | F80: DLC Single
B81: Chop Suey | C81: System of a Down | D81: 42705 | E81: DLC | F81: DLC Single
B82: Psycho Killer | C82: Talking Heads
B83: Master Exploder | C83: Tenacious D | D83: 45183 | E83: DLC | F83: DLC Single
B84: Souls of Black | C84: Testament
B85: Rob the Prez-O-Dent | C85: That Handsome Devil | D85: 42465 | E85: DLC | F85: Part of "30 Song Mega Pack"
B86: Pinball Wizard | C86: The Who
B89: Songs Released | C89: =COUNT(D:D) -> 34
B90: Total Songs | C90: 84
B91: Percent Complete | C91: =IFERROR(__xludf.DUMMYFUNCTION("TO_PERCENT(C89/C90)"),0.40476190476190477) -> 0.4047619

Sheet LEGO RB
B2: Song | C2: Artist | D2: Release Date | E2: Source | F2: Notes
B3: Swing, Swing | C3: The All-American Rejects | D3: 42747 | E3: DLC | F3: DLC Single
B4: Monster | C4: The Automatic
B5: Aliens Exist | C5: Blink-182
B6: Song 2 | C6: Blur | D6: 45064 | E6: DLC | F6: DLC Single
B7: You Give Love a Bad Name | C7: Bon Jovi | D7: 40491 | E7: DLC | F7: Part of "Bon Jovi Greatest Hits" Album
B8: Thunder | C8: Boys Like Girls
B9: Summer of '69 | C9: Bryan Adams
B10: Kung Fu Fighting | C10: Carl Douglas
B11: Dreaming of You | C11: The Coral
B12: Accidentally in Love | C12: Counting Crows
B13: Let's Dance | C13: David Bowie
B14: Crocodile Rock | C14: Elton John
B15: The Final Countdown | C15: Europe | D15: 43097 | E15: DLC | F15: Part of "New Year's Eve 2017 Pack"
B16: Real Wild Child | C16: Everlife
B17: Breakout | C17: Foo Fighters
B18: Girls & Boys | C18: Good Charlotte
B19: Tick Tick Boom | C19: The Hives
B20: The Passenger | C20: Iggy Pop
B21: Dig | C21: Incubus
B22: I Want You Back | C22: Jackson 5 | D22: 43034 | E22: DLC | F22: DLC Single
B23: Fire | C23: The Jimi Hendrix Experience
B24: Ruby | C24: Kaiser Chiefs
B25: Walking on Sunshine | C25: Katrina & the Waves
B26: Naïve | C26: The Kooks
B27: Word Up! | C27: Korn
B28: Suddenly I See | C28: KT Tunstall
B29: Rooftops (A Liberation Broadcast) | C29: Lostprophets
B30: So What | C30: Pink
B31: Every Little Thing She Does Is Magic | C31: The Police
B32: Crash | C32: The Primitives
B33: We Are the Champions | C33: Queen | D33: 40120 | E33: DLC | F33: Part of "Queen Extravaganza Pack 01"
B34: We Will Rock You | C34: Queen | D34: 40120 | E34: DLC | F34: Part of "Queen Extravaganza Pack 01"
B35: Life Is a Highway | C35: Rascal Flatts
B36: Ghostbusters | C36: Ray Parker Jr.
B37: Stumble and Fall | C37: Razorlight
B38: Two Princes | C38: Spin Doctors | D38: 43160 | E38: DLC | F38: DLC Single
B39: Short and Sweet | C39: Spinal Tap
B40: Make Me Smile (Come Up and See Me) | C40: Steve Harley & Cockney Rebel
B41: In Too Deep | C41: Sum 41 | D41: 42782 | E41: DLC | F41: DLC Single
B42: Grace | C42: Supergrass
B43: Ride a White Swan | C43: T. Rex
B44: Free Fallin' | C44: Tom Petty
B45: A-Punk | C45: Vampire Weekend
B46: Check Yes Juliet | C46: We the Kings | D46: 45232 | E46: DLC | F46: DLC Single
B47: Valerie | C47: The Zutons
B50: Songs Released | C50: =COUNT(D:D) -> 10
B51: Total Songs | C51: 45
B52: Percent Complete | C52: =IFERROR(__xludf.DUMMYFUNCTION("TO_PERCENT(C50/C51)"),0.2222222222222222) -> 0.22222222

Sheet RB3
B2: Song | C2: Artist | D2: Release Date | E2: Source | F2: Notes
B3: Rehab | C3: Amy Winehouse | D3: 45253 | E3: DLC | F3: DLC Single
B4: Caught in a Mosh | C4: Anthrax
B5: One Armed Scissor | C5: At the Drive-In
B6: Beast and the Harlot | C6: Avenged Sevenfold | D6: 42852 | E6: DLC | F6: DLC Single
B7: Rock Lobster | C7: The B-52's
B8: Good Vibrations (Live) | C8: The Beach Boys
B9: In a Big Country | C9: Big Country | D9: 45288 | E9: DLC | F9: DLC Single
B10: Heart of Glass | C10: Blondie
B11: Get Up, Stand Up | C11: Bob Marley and the Wailers
B12: False Alarm | C12: The Bronx
B13: 25 or 6 to 4 | C13: Chicago
B14: Just Like Heaven | C14: The Cure
B15: Space Oddity | C15: David Bowie | D15: 45036 | E15: DLC | F15: DLC Single
B16: Smoke on the Water | C16: Deep Purple
B17: Foolin' | C17: Def Leppard
B18: Whip It | C18: Devo
B19: Rainbow in the Dark | C19: Dio | D19: 44875 | E19: DLC | F19: DLC Single
B20: Walk of Life | C20: Dire Straits
B21: China Grove | C21: The Doobie Brothers
B22: Break on Through (To the Other Side) | C22: The Doors
B23: King George | C23: Dover
B24: The Killing Moon | C24: Echo & The Bunnymen
B25: Saturday Night's Alright for Fighting | C25: Elton John | D25: 45288 | E25: DLC | F25: DLC Single
B26: Midlife Crisis | C26: Faith No More
B27: Hey Man, Nice Shot | C27: Filter
B28: Yoshimi Battles the Pink Robots Pt. 1 | C28: The Flaming Lips
B29: Cold as Ice | C29: Foreigner
B30: Radar Love | C30: Golden Earring
B31: Killing Loneliness | C31: H.I.M.
B32: The Power of Love | C32: Huey Lewis and the News
B33: Viva la Resistance | C33: Hypernova
B34: Oh My God | C34: Ida Maria
B35: Need You Tonight | C35: INXS
B36: Centerfold | C36: The J. Geils Band | D36: 45295 | E36: DLC | F36: DLC Single
B37: I Got You (I Feel Good) | C37: James Brown
B38: Been Caught Stealing | C38: Jane's Addiction
B39: Crosstown Traffic | C39: The Jimi Hendrix Experience
B40: I Love Rock N' Roll | C40: Joan Jett & The Blackhearts
B41: Imagine | C41: John Lennon
B42: Me Enamora | C42: Juanes
B43: Free Bird | C43: Lynyrd Skynyrd | D43: 42845 | E43: DLC | F43: DLC Single
B44: Oye Mi Amor | C44: Maná
B45: The Beautiful People | C45: Marilyn Manson
B46: Combat Baby | C46: Metric
B47: Outer Space | C47: The Muffs
B48: Sister Christian | C48: Night Ranger
B49: Crazy Train | C49: Ozzy Osbourne
B50: Misery Business | C50: Paramore | D50: 45015 | E50: DLC | F50: DLC Single
B51: Llama | C51: Phish
B52: Lasso | C52: Phoenix
B53: Don't Stand So Close to Me | C53: The Police
B54: Antibodies | C54: Poni Hoax
B55: Something Bigger, Something Brighter | C55: Pretty Girls Make Graves
B56: Jerry Was a Race Car Driver | C56: Primus
B57: Bohemian Rhapsody | C57: Queen
B58: No One Knows | C58: Queens of the Stone Age
B59: Du Hast | C59: Rammstein
B60: I Wanna Be Sedated | C60: Ramones | D60: 43041 | E60: DLC | F60: Part of "Solid '70s Pack 2" and "Guitar Glory Pack"
B61: Last Dance | C61: The Raveonettes
B62: Portions for Foxes | C62: Rilo Kiley
B63: Don't Bury Me... I'm Still Not Dead | C63: Riverboat Gamblers
B64: The Look | C64: Roxette
B65: Before I Forget | C65: Slipknot
B66: Walking on the Sun | C66: Smash Mouth
B67: Stop Me If You Think You've Heard This One Before | C67: The Smiths
B68: Living in America | C68: The Sounds
B69: In the Meantime | C69: Spacehog
B70: Fly Like an Eagle | C70: Steve Miller Band
B71: Plush | C71: Stone Temple Pilots | D71: 43090 | E71: DLC | F71: DLC Single
B72: This Bastard's Life | C72: Swingin' Utters
B73: 20th Century Boy | C73: T. Rex
B74: Everybody Wants to Rule the World | C74: Tears for Fears
B75: The Con | C75: Tegan and Sara
B76: Dead End Friends | C76: Them Crooked Vultures
B77: Humanoid | C77: Tokio Hotel
B78: I Need to Know | C78: Tom Petty and the Heartbreakers
B79: Get Free | C79: The Vines
B80: Low Rider | C80: WAR | D80: 45295 | E80: DLC | F80: DLC Single
B81: Werewolves of London | C81: Warren Zevon
B82: The Hardest Button to Button | C82: The White Stripes
B83: Here I Go Again | C83: Whitesnake | D83: 42746 | E83: DLC | F83: DLC Single
B84: I Can See for Miles | C84: The Who | D84: 45106 | E84: DLC | F84: DLC Single
B85: Roundabout | C85: Yes | D85: 45197 | E85: DLC | F85: DLC Single
B88: Songs Released | C88: =COUNT(D:D) -> 15
B89: Total Songs | C89: 83
B90: Percent Complete | C90: =IFERROR(__xludf.DUMMYFUNCTION("TO_PERCENT(C88/C89)"),0.18072289156626506) -> 0.18072289

Sheet RBN
B2: Song | C2: Artist | D2: Release Date | E2: Source | F2: Notes
B3: !I | C3: !I!
B4: Latest Heartbreak | C4: 22-20s
B5: Just Hang On | C5: 2nd Thought
B6: Battles and Brotherhood | C6: 3 Inches of Blood | D6: 43699 | E6: DLC | F6: DLC Single
B7: All My Friends Are Crazy | C7: 500 Miles to Memphis
B8: Doomed | C8: 8 Inch Betsy
B9: Automatic Doors | C9: A'tris
B10: Secondary Gain | C10: Abraham Nixon
B11: Dr. Doom | C11: The Acacia Strain
B12: Hair Trigger | C12: The Acro-Brats | D12: 43059 | E12: DLC | F12: Part of "Rock Band 10th Anniversary Pack"
B13: Masters of Puppet Rock | C13: Action Action
B14: The Ones Who Get It | C14: Action Action
B15: Dance Battle Alpha | C15: Active Knowledge
B16: The Fractal Reason | C16: Active Knowledge
B17: Reality Down | C17: Active Knowledge
B18: Supertronic Lazering | C18: Active Knowledge
B19: Liberated by Blasphemy | C19: Adam Evil
B20: Bitten by the Rattlesnake | C20: Admiral of Black
B21: Skeleton | C21: Adora
B22: The Devil's in the Details | C22: Aesthetic Perfection
B23: Crusader | C23: AFD Shift
B24: Call to the Warrior | C24: Affiance
B25: Aspiration | C25: After the Burial | D25: 44280 | E25: DLC | F25: DLC Single and Temporarily Part of "Rivals Season 21 Pass"
B26: Berzerker | C26: After the Burial | D26: 43636 | E26: DLC | F26: DLC Single
B27: Cursing Akhenaten | C27: After the Burial
B28: My Frailty | C28: After the Burial
B29: Pendulum | C29: After the Burial
B30: Your Troubles Will Cease and Fortune Will Smile Upon You | C30: After the Burial
B31: Stay Up With Me | C31: After the Fall
B32: Thank You, Pain. | C32: The Agonist | D32: 44931 | E32: DLC | F32: Part of "Riffing In The New Year 2023"
B33: Broken Bones | C33: Aiden
B34: Hysteria | C34: Aiden
B35: Scavengers of the Damned | C35: Aiden
B36: Filthy Dog | C36: Aittala
B37: Numb | C37: Aittala
B38: Steven Wells (He Was the Greatest) | C38: Akira the Don
B39: Bleeder | C39: Alchemilla
B40: Back Through Time | C40: Alestorm | D40: 44490 | E40: DLC | F40: DLC Single
B41: Shipwrecked | C41: Alestorm | D41: 44350 | E41: DLC | F41: DLC Single and Temporarily Part of "Rivals Season 22 Pass"
B42: Top Back | C42: Alias Unknown
B43: Courage | C43: Alien Ant Farm
B44: Glow | C44: Alien Ant Farm
B45: Movies | C45: Alien Ant Farm
B46: I Wanna Be An Alien's Pet | C46: Alien Downlink
B47: Heavy Plastic | C47: Alien Downlink
B48: Wake Up Fall | C48: All City Elite
B49: The Cold Taste of Nickel Plated Steel | C49: All Hallow's Evil
B50: The Death Plague | C50: All Shall Perish
B51: Embrace the Curse | C51: All Shall Perish
B52: In This Life of Pain | C52: All Shall Perish
B53: My Retaliation | C53: All Shall Perish
... B59: There is Nothing Left | C59: All Shall Perish
B60: Days Without | C60: All That Remains | D60: 43657 | E60: DLC | F60: DLC Single
B61: Forever in Your Hands | C61: All That Remains | D61: 43482 | E61: DLC | F61: DLC Single
B62: For We Are Many | C62: All That Remains | D62: 43671 | E62: DLC | F62: DLC Single
B63: Hold On | C63: All That Remains | D63: 43587 | E63: DLC | F63: DLC Single
B64: Undone | C64: All That Remains | D64: 43685 | E64: DLC | F64: DLC Single
B65: The Waiting One | C65: All That Remains | D65: 43622 | E65: DLC | F65: DLC Single
B66: Walls | C66: All Time Low
B67: Pylo the Pylon | C67: Alternative Deficit Disorder
B68: Arctica | C68: Amberian Dawn
B69: Blackbird | C69: Amberian Dawn
B70: Charnel's Ball | C70: Amberian Dawn
B71: Circus Black | C71: Amberian Dawn
B72: City of Corruption | C72: Amberian Dawn
B73: Cold Kiss | C73: Amberian Dawn
B74: Come Now Follow | C74: Amberian Dawn
B75: The Curse | C75: Amberian Dawn
B76: Dreamchaser | C76: Amberian Dawn | D76: 44252 | E76: DLC | F76: DLC Single and Temporarily Part of "Rivals Season 20 Pass"
B77: Evil Inside Me | C77: Amberian Dawn
B78: Fate of the Maiden | C78: Amberian Dawn | D78: 44126 | E78: DLC | F78: DLC Single
B79: Field of Serpents | C79: Amberian Dawn
B80: Ghostly Echoes | C80: Amberian Dawn
B81: He Sleeps in a Grove | C81: Amberian Dawn
B82: Incubus | C82: Amberian Dawn | D82: 44021 | E82: DLC | F82: DLC Single and Temporarily Part of "Rivals Season 17 Pass Plus"
B83: Kokko - Eagle of Fire | C83: Amberian Dawn | D83: 44322 | E83: DLC | F83: DLC Single and Temporarily Part of "Rivals Season 21 Pass"
B84: Lionheart | C84: Amberian Dawn
B85: Lost Soul | C85: Amberian Dawn
B86: Lullaby | C86: Amberian Dawn
B87: Morning Star | C87: Amberian Dawn
B88: My Only Star | C88: Amberian Dawn
B89: My Wings Are My Eyes | C89: Amberian Dawn
B90: Passing Bells | C90: Amberian Dawn
B91: River of Tuoni | C91: Amberian Dawn | D91: 43342 | E91: DLC | F91: DLC Single
B92: Saga | C92: Amberian Dawn
B93: Sampo | C93: Amberian Dawn
B94: Shallow Waters | C94: Amberian Dawn | D94: 43643 | E94: DLC | F94: DLC Single
B95: Snowmaiden | C95: Amberian Dawn
B96: Sons of Seven Stars | C96: Amberian Dawn
B97: Sunrise | C97: Amberian Dawn
B98: Talisman | C98: Amberian Dawn
B99: Valkyries | C99: Amberian Dawn
B100: War in Heaven | C100: Amberian Dawn
B101: Willow of Tears | C101: Amberian Dawn
B102: Drag Me Away | C102: Aminal
B103: Shiver | C103: Amy Courts
B104: I Can't Explain It | C104: Analogue Revolution feat. Bryan Steele
B105: R U Ready For This | C105: Analogue Revolution feat. Bryan Steele
B106: What a Trip | C106: Analogue Revolution feat. First Be
...

Sheet Rock Band VR
B2: Song | C2: Artist | D2: Released Date | E2: Source | F2: Notes
B3: Walk This Way | C3: Aerosmith | D3: 41303 | E3: DLC | F3: Part of "Aerosmith's Greatest Dimension Pack"
B4: Running With The Wild Things | C4: Against The Current | D4: 44315 | E4: DLC | F4: DLC Single and Temporarily Part of "Rivals Season 21 Pass"
B5: Man in the Box | C5: Alice In Chains | D5: 39705 | E5: RB2 Export/DLC | F5: Export Has Expired, but re-released in "Alice in Chains Pack 03" and "Guitar Glory Pack"
B6: Black Seas | C6: Arctic Horror | D6: 42964 | E6: DLC | F6: Free DLC to Rivals Owners
B7: Lights Out | C7: AudioDamn!
B8: Beast and the Harlot | C8: Avenged Sevenfold | D8: 40477 | E8: RB3 Export/DLC | F8: Export Has Expired, but re-released as a Single
B9: Casual Party | C9: Band of Horses
B10: Promise Everything | C10: Basement | D10: 42824 | E10: DLC | F10: DLC Single
B11: (You're) Breakin' Up | C11: The Black Cheers | D11: 42964 | E11: DLC | F11: Free DLC to Rivals Owners
B12: Gold On The Ceiling | C12: The Black Keys | D12: 42936 | E12: DLC | F12: DLC Single
B13: Bored to Death | C13: blink-182 | D13: 42880 | E13: DLC | F13: DLC Single
B14: True Confessions | C14: Blondfire | D14: 42950 | E14: DLC | F14: DLC Single
B15: One Way or Another | C15: Blondie | D15: 39705 | E15: RB2 Export/DLC | F15: Export Has Expired, but re-released as a DLC single
B16: Livin' On A Prayer | C16: Bon Jovi | D16: 39705 | E16: RB2 Export/DLC | F16: Export Has Expired but re-released as part of "Bon Jovi's Greatest Hit" Album
B17: Church Bells | C17: Carrie Underwood | F17: Leaked Single?
B18: Postpone | C18: Catfish and the Bottlemen | D18: 42976 | E18: DLC | F18: DLC Single
B19: Birds | C19: Coldplay
B20: Suffragette City | C20: David Bowie | D20: 39406 | E20: RB1 Export/DLC | F20: Export Has Expired, but re-released as a DLC single and part of "Rock Band Hits Pack"
B21: Down With The Sickness | C21: Disturbed | D21: 39705 | E21: RB2 Export/DLC | F21: Export Has Expired, but re-released as a DLC single
B22: Through The Fire And Flames | C22: Dragonforce | D22: 40631 | E22: DLC | F22: DLC Single and part of "Rock Band Hits Pack"
B23: Pull Me Under | C23: Dream Theater | D23: 42894 | E23: DLC | F23: DLC Single
B24: The Final Coutdown | C24: Europe | D24: 40120 | E24: LEGO Export/DLC | F24: Export Has Expired but re-released in the "New Year's Eve 2017 Pack"
B25: Go Your Own Way | C25: Fleetwood Mac | D25: 39705 | E25: RB2 Export/DLC | F25: Export Has Expired, but re-released as a DLC single and part of "Rock Band Hits Pack"
B26: Everlong | C26: Foo Fighters | D26: 39705 | E26: RB2 Export/DLC | F26: Export Has Expired, but re-released as a DLC single
B27: Cirice | C27: Ghost | D27: 42922 | E27: DLC | F27: DLC Single
B28: We Got The Beat | C28: The Go-Go's | D28: 39705 | E28: RB2 Export/DLC | F28: Export Has Expired, but re-released as a DLC single | I28: Rock Band VR
B29: Holiday | C29: Green Day | D29: 40337 | E29: Green Day Export/DLC | F29: Export Has Expired, but was Re-Released as a Part of "American Idiot" Album | I29: 42817
B30: You & Me | C30: The Hunna | D30: 42880 | E30: DLC | F30: DLC Single
B31: The Middle | C31: Jimmy Eat World | D31: 39705 | E31: RB2 Export/DLC | F31: Export Has Expired, but re-released as a DLC single
B32: Bad Reputation | C32: Joan Jett | D32: 39705 | E32: RB2 Export/DLC | F32: Export Has Expired, but re-released as a DLC single
B33: Glass House | C33: Kaleo | D33: 42838 | E33: DLC | F33: DLC Single
B34: When You Were Young | C34: The Killers | D34: 39406 | E34: RB1 Export/DLC | F34: Export Has Expired, but re-released as a DLC single
B35: Use Somebody | C35: Kings of Leon | D35: 42817 | E35: DLC | F35: DLC Single
B36: Maps | C36: Maroon 5 | F36: Leaked Single?
B37: Hanger 18 | C37: Megadeth | D37: 40218 | E37: DLC | F37: Part of "Rust in Peace" Album
B38: I Will Wait | C38: Mumford & Sons | D38: 42817 | E38: DLC | F38: DLC Single and part of "Guitar Glory Pack"
B39: Smells Like Teen Spirit | C39: Nirvana | D39: 40148 | E39: DLC | F39: Part of "Nirvana Pack 02"
B40: Champagne Supernova | C40: Oasis | D40: 42845 | E40: DLC | F40: DLC Single
B41: Counting Stars | C41: OneRepublic | D41: 42817 | E41: DLC | F41: DLC Single
B42: Ain't It Fun | C42: Paramore | D42: 42908 | E42: DLC | F42: DLC Single
B43: Sweater Weather | C43: Parks | D43: 42957 | E43: DLC | F43: Free DLC to Rivals Owners
B44: Alive | C44: Pearl Jam | D44: 39705 | E44: RB2 Export | F44: Export Has Expired, but Live version is Available
B45: Circles | C45: Pierce The Veil | D45: 42894 | E45: DLC | F45: DLC Single
B46: Heaven Knows | C46: The Pretty Reckless | D46: 42852 | E46: DLC | F46: DLC Single
B47: Testify | C47: Rage Against The Machine | D47: 39705 | E47: RB2 Export/DLC | F47: Export Has Expired, but re-released as a DLC single
B48: I Wanna Be Sedated | C48: The Ramones | D48: 40477 | E48: RB3 Export/DLC | F48: Export Has Expired but was re-released in "Solid '70's Pack 2" and in "Guitar Glory Pack"
... B51: To My Romeo | C51: Spirit Kid | D51: 42957 | E51: DLC | F51: Free DLC to Rivals Owners
B52: Quitter | C52: The Starting Line
B53: Plush | C53: Stone Temple Pilots | D53: 40477 | E53: RB3 Export/DLC | F53: Export Has Expired but was re-released as a DLC Single
B54: Eye of the Tiger | C54: Survivor | D54: 39705 | E54: RB2 Export/DLC | F54: Export Has Expired, but re-released as a DLC single
B55: Float | C55: Switchfoot | D55: 42999 | E55: DLC | F55: DLC Single
B56: Alive | C56: The Temper Trap | D56: 42943 | E56: DLC | F56: DLC Single
B57: Mother Mother | C57: Tracy Bonham | D57: 42866 | E57: DLC | F57: DLC Single
B58: I Am Alive | C58: Twin Atlantic
B59: Panama | C59: Van Halen | D59: 42283 | E59: RB4 | F59: On-Disc Song
B60: Say It Ain't So | C60: Weezer | D60: 39406 | E60: RB1 Export/DLC | F60: Export Has Expired but has been re-released in the "Back in the '90's Pack 01"
B61: Won't Get Fooled Again | C61: The Who | D61: 39406 | E61: RB1 Export/DLC | F61: Export Has Expired, but re-released as a DLC single
B62: Grand Canyon | C62: The Wind and the Wave | D62: 44532 | E62: DLC | F62: DLC Single and Temporarily Part of "Rivals Season 24 Pass"
B65: Songs Released | C65: =COUNT(D:D) -> 53
B66: Total Songs | C66: 60
B67: Percent Complete | C67: =IFERROR(__xludf.DUMMYFUNCTION("TO_PERCENT(C65/C66)"),0.8833333333333333) -> 0.88333333

Sheet Rock Band VR DLC
B2: Song | C2: Artist | D2: Released Date | E2: Source | F2: Notes | G2: Song
B3: Angel | C3: Aerosmith | D3: 42726 | E3: DLC | F3: Part of "Aerosmith Hits Pack 03"
B4: Crazy | C4: Aerosmith | D4: 42726 | E4: DLC | F4: Part of "Aerosmith Hits Pack 03"
B5: I Don't Want to Miss a Thing | C5: Aerosmith | D5: 42726 | E5: DLC | F5: Part of "Aerosmith Hits Pack 03"
B6: Janie's Got A Gun | C6: Aerosmith | D6: 42726 | E6: DLC | F6: Part of "Aerosmith Hits Pack 03"
B7: Living On The Edge | C7: Aerosmith | D7: 42726 | E7: DLC | F7: Part of "Aerosmith Hits Pack 03"
B8: Rag Doll | C8: Aerosmith | D8: 42726 | E8: DLC | F8: Part of "Aerosmith Hits Pack 03"
B9: You Give Love a Bad Name | C9: Bon Jovi | D9: 40120 | E9: LEGO Export/DLC | F9: Export Has Expired but re-released as part of "Bon Jovi's Greatest Hit" Album
B10: What's My Age Again? | C10: blink-182 | D10: 40099 | E10: DLC | F10: DLC Single
B11: Ex's & Oh's | C11: Elle King | D11: 42353 | E11: DLC | F11: Part of "Off The Charts 02
B12: My Songs Know What You Did In The Dark (Light Em Dark) | C12: Fall Out Boy | D12: 42451 | E12: DLC | F12: Part of "Off The Charts Pack 03"
B13: The Pretender | C13: Foo Fighters | D13: 40120 | E13: DLC | F13: Part of "Foo Fighters Pack 03"
B14: Basket Case | C14: Green Day | D14: 40337 | E14: Green Day Export/DLC | F14: Export Has Expired, but was Re-released as a Part of "American Idiot" Album
... B24: Seven Nation Army | C24: The White Stripes | D24: 40246 | E24: DLC | F24: Part of "The White Stripes Pack 02"
B27: Songs Released | C27: =COUNT(D:D) -> 22
B28: Total Songs | C28: 22
B29: Percent Complete | C29: =IFERROR(__xludf.DUMMYFUNCTION("TO_PERCENT(C27/C28)"),1.0) -> 1

Sheet Dropmix
A1: Dro
B2: Song | C2: Artist | D2: Released Date | E2: Source | F2: Notes
B3: Take Over Controls (Ft. Eva Simons) | C3: Afrojack
B4: Am I Wrong (Ft. Schoolboy Q) | C4: Anderson.Paak
B5: More Than You Know | C5: Axwell /\ Ingrosso
B6: Gimme Chocolate!! | C6: Babymetal | D6: 42283 | E6: DLC | F6: DLC Single
B7: Who Let The Dogs Out | C7: Baha Men
B8: Pompeii | C8: Bastille | D8: 42577 | E8: DLC | F8: DLC Single
B9: Poison | C9: Bell Biv Devoe
B10: Satisfaction | C10: Benny Benassi presents The Biz
B11: Save A Horse (Ride A Cowboy) | C11: Big & Rich | D11: 43060 | E11: DLC | F11: DLC Single and Temporarily Part of "Rivals Season 3 Pass"
B12: Boom Boom Pow | C12: The Black Eyed Peas
B13: All The Small Things | C13: blink-182 | D13: 39462 | E13: DLC | F13: DLC Single
B14: Heart of Glass | C14: Blondie | D14: 40477 | E14: RB3 Export | F14: Export Has Expired
B15: 24K Magic | C15: Bruno Mars | D15: 42696 | E15: DLC | F15: DLC Single
B16: Short Skirt/Long Jacket | C16: Cake | D16: 42283 | E16: RB4 | F16: On-Disc Song
B17: Call Me Maybe | C17: Carly Rae Jepsen | D17: 41240 | E17: DLC | F17: DLC Single
B18: Blown Away | C18: Carrie Underwood | D18: 41362 | E18: DLC | F18: Part of "Going Country Pack 09"
B19: Closer (Ft. Halsey) | C19: The Chainsmokers | D19: 42670 | E19: DLC | F19: DLC SIngle
B20: Attention | C20: Charlie Puth | D20: 43083 | E20: DLC | F20: Part of "Off The Charts 06" and "Rock Band Hits Pack"
B21: Heartbeat | C21: Childish Gambino
B22: The Mother We Share | C22: CHVRCHES | D22: 44812 | E22: DLC | F22: DLC Single and Temporarily Part of "Rivals Season 28 Pass"
B23: Brick House | C23: Commodores | D23: 43139 | E23: DLC | F23: DLC Single, and temporarily part of "Season 4 Spotlight Pass Plus"
B24: Up All Night | C24: Connecticut River Boys
B25: Me Rehuso | C25: Danny Ocean
B26: Flutter Fly (From The Pyre Original Soundtrack) | C26: Darren Korb
B27: Down With the Sickness | C27: Disturbed | D27: 39705 | E27: RB2 Export/DLC | F27: Export Has Expired, but re-released as a single
B28: All I Do Is Win (Ft. T-Pain) | C28: DJ Khaled
B29: Guitek | C29: DJ Steve Porter
B30: Jolene | C30: Dolly Parton | D30: 44637 | E30: DLC | F30: DLC Single and Temporarily Part of "Rivals Season 25 Pass"
B31: Barbra Streisand | C31: Duck Sauce
B32: September | C32: Earth, Wind, and Fire | D32: 42283 | E32: DLC | F32: DLC Single
B33: Sing | C33: Ed Sheeran | D33: 42325 | E33: DLC | F33: Available only in the "Ed Sheeran SIng Special Edition" Bundle
B34: When Things Fall Apart | C34: Eddie Japan
B35: Burn | C35: Ellie Goulding
B36: Unbelievable | C36: EMF | D36: 40792 | E36: DLC | F36: Re-record available as a DLC Singlr
B37: The Final Coutdown | C37: Europe | D37: 40120 | E37: LEGO Export/DLC | F37: Export Has Expired but re-released in the "New Year's Eve 2017 Pack"
B38: Bring Me To Life (Ft. Paul McCoy) | C38: Evanescence | D38: 39980 | E38: DLC | F38: Part of "Evanescence Pack 01"
B39: Centuries | C39: Fall Out Boy | D39: 42283 | E39: RB4 | F39: On-Disc Song
B40: Like A G6 (Ft. The Cataracs & Dev) | C40: Far East Movement
B41: 679 (FT. Remy Boyz) | C41: Fetty Wap
B42: Work From Home | C42: Fifth Harmony
B43: I Don't Like It, I Love It (Ft. Robin Thicke, Verdine White) | C43: Flo Rida
B44: Take Me Out | C44: Franz Ferdinand | D44: 39938 | E44: DLC | F44: Part of "Franz Ferdinand Pack 01" and "Guitar Glory Pack"
B45: Main Title Theme (Remix) | C45: G.I. Joe
B46: Pony | C46: Ginuwine
B47: Conga | C47: Gloria Estefan
B48: I Will Survive | C48: Gloria Gaynor | F48: RB has Cake version
B49: What Is Love | C49: Haddaway
B50: I Can't Go For That (No Can Do) | C50: Hall & Oates | D50: 40918 | E50: DLC | F50: Part of "Hall & Oates Pack 01"
B51: Baker Street | C51: Harmonix
B52: Doctor Who Theme | C52: Harmonix
B53: Sanford & Son Theme (The Streetbeater) | C53: Harmonix
B54: Wipe Out | C54: Harmonix
B55: Radioactive | C55: Imagine Dragons | D55: 42542 | E55: DLC | F55: DLC Single
B56: I Want You Back | C56: The Jackson 5 | D56: 40120 | E56: LEGO Export/DLC | F56: Export Has Expired, but re-released as a DLC single
B57: Loud Places (FT. Romy) | C57: Jamie xx
B58: Want To Want Me | C58: Jason DeRulo | D58: 42775 | E58: DLC | F58: Part of "Pack à Trois"
B59: Cello Suite No.1 in G Minor | C59: J.S. Bach
B60: Le Camisa Negra | C60: Juanes | D60: 40386 | E60: DLC | F60: Part of "Juanes Pack 01"
B61: HUMBLE. | C61: Kendrick Lamar
B62: Hideaway | C62: Kiesza
B63: Jungle Boogie | C63: Kool & The Gang | D63: 41149 | E63: Blitz/DLC | F63: Part of "Rock Band Blitz" and as a DLC Single
B64: The Breaks | C64: Kurtis Blow
B65: A-Yo | C65: Lady Gaga | D65: 42761 | E65: DLC | F65: Part of "Lady Gaga Pck 03"
B66: Steal My Sunshine | C66: LEN | D66: 43195 | E66: DLC | F66: DLC Single and part of "Rock Band Sampler Pack"
B67: Sexy and I Know It | C67: LMFAO
B68: Fade Away | C68: Logic
B69: Green Light | C69: Lorde
B70: Can't Let Go | C70: Lucinda Williams | D70: 39868 | E70: DLC | F70: Part of "Alt Country Pack 01" and "Rock Band Country Track Pack 01"
B71: 5th Symphony | C71: Ludwig Van Beethoven
B72: Dang! (FT. Anderson. Paak) | C72: Mac Miller
B73: Good Vibration | C73: Marky Mark & The Funky Bunch
B74: Animals | C74: Maroon 5
B75: Moves Like Jagger (FT. Christina Aguilera) | C75: Maroon 5 | E75: Blitz/DLC
B76: Animals | C76: Martin Garrix
B77: All About That Bass | C77: Meghan Trainor | D77: 42719 | E77: DLC | F77: Part of "Off The Charts 05"
B78: Kids | C78: MGMT | D78: 42866 | E78: DLC | F78: DLC Single
B79: Genghis Khan | C79: Mike Snow
B80: Main Title Theme | C80: Mighty Morphin Power Rangers
B81: Blue Monday | C81: New Order | D81: 40491 | E81: DLC | F81: DLC Single
B82: Levels | C82: Nick Jonas
B83: Say My Name (Ft. Zyra) | C83: Odezsa
B84: Ms. Jackson | C84: Outkast
B85: Emperor's New Clothes | C85: Panic! At The Disco
B86: Straight Up | C86: Paula Abdul
B87: For an Angel | C87: Paul Van Dyke
B88: Fireball (Ft. John Ryan) | C88: Pitbull
B89: Every Rose Has Its Thorn | C89: Poison | D89: 40953 | E89: DLC | F89: Part of "Gold Star My Heart Pack"
B90: Darte Un Beso | C90: Prince Royce
B91: Gangnam Style | C91: PSY
B92: Super Freak | C92: Rick James | D92: 42999 | E92: DLC | F92: DLC Single and Temporarily Part of "Rivals Season 2 Pass"
B93: La Mordidita (Ft. Yotuel) | C93: Ricky Martin
B94: It's Tricky | C94: Run-D.M.C
B95: Push It | C95: Salt-N-Pepa
B96: House Party | C96: Sam Hunt | D96: 41362 | E96: DLC | F96: Part of "Going Country Pack 09"
B97: Man of the Year | C97: ScHoolboy Q
B98: Temperature | C98: Sean Paul
B99: Chandelier | C99: Sia | D99: 42661 | E99: DLC | F99: Part of "Rock Band Rivals Pre-Order Bonus"
B100: Cheap Thrills (Ft. Sean Paul) | C100: Sia
...

Sheet Fuser
B2: Song | C2: Artist | D2: Released Date | E2: Source | F2: Notes
B3: In Da Club | C3: 50 Cent
B4: Can I Kick It? | C4: A Tribe Called Quest
B5: Take On Me | C5: A-ha | D5: 40547 | E5: DLC | F5: DLC Single
B6: The Sign | C6: Ace of Base | D6: 43053 | E6: DLC | F6: Part of "Back in the '90's Pack 01"
B7: Daniel Wiggy | C7: Agent 001
B8: Rehab | C8: Amy Winehouse | D8: 40477 | E8: RB3 Export/DLC | F8: Export Has Expired, but re-released as a DLC single
B9: Blah Blah Blah | C9: Armin van Buuren
B10: Sweet But Psycho | C10: Ava Max
B11: Yo Perreo Sola | C11: Bad Bunny
B12: Where's Your HEad At | C12: Basement Jaxx
B13: Sin Pijama | C13: Becky G & Natti Natasha
B14: Satisfaction | C14: Benny Benassi presents The Biz
B15: Bad Guy | C15: Billie Eilish | D15: 43818 | E15: DLC | F15: Part of "Headliners Pack" and temporaraily part of "Apple Music Spotlight Pass"
B16: Sequence Her | C16: Black Light Odyssey
B17: (Don't Fear) The Reaper | C17: Blue Oyster Cult | D17: 39406 | E17: RB1 Export/DLC | F17: Export Has Expired but Re-Released in "Solid '70s Pack 01"
B18: My Perogative | C18: Bobby Brown
B19: Mud On The Tires | C19: Brad Paisley | D19: 39798 | E19: DLC | F19: Part of "Rock Band Country Track Pack 01" and part of "Going Country Pack 01"
B20: Dot Calm | C20: Cade7
B21: Bodak Yellow | C21: Cardi B
B22: Call Me Maybe | C22: Carly Rae Jepsen | D22: 41240 | E22: DLC | F22: DLC Single
B23: Don't Let Me Down | C23: The Chainsmokers ft. Daya
B24: Bloom | C24: Charm Syndicate
B25: Summertime Magic | C25: Childish Gambino
B26: Rock the Casbah | C26: The Clash
B27: Clocks | C27: Coldplay | D27: 40834 | E27: DLC | F27: Part of "Coldplay Collection 01" and part of "Rock Band Hits Pack 03"
B28: Rupture Academy | C28: CrackCase
B29: Ghosts 'n' Stuff | C29: deadmau5 ft. Rob Swire
B30: X Gon' Give It To Ya | C30: DMX
B31: Jolene | C31: Dolly Parton | D31: 44637 | E31: DLC | F31: DLC Single and Temporarily Part of "Rivals Season 25 Pass"
B32: Hot Stuff | C32: Donna Summer
B33: Don't Start Now | C33: Dua Lipa | D33: 43930 | E33: DLC | F33: DLC Single and temporaraly part of "Season 16 Spotlight Pass Plus"
B34: Summer Hair | C34: Eddie Japan
B35: Don't Sweat the Technique | C35: Eric B. & Rakim
B36: The Rockafeller Shank | C36: Fatboy Slim
B37: G.D.F.R | C37: Flo Rida ft. Sage the Gemini & Lookas
B38: The Message (2012) | C38: Grand Master Melle Mel
B39: This Isn't Enough | C39: Greg LeBeau
B40: Tongue Tied | C40: Grouplove | D40: 42283 | E40: RB4 | F40: On-Disc Song
B41: Thunder | C41: Imagine Dragons | D41: 43083 | E41: DLC | F41: Part of "Off the Charts Pack 06"
B42: Mi Gente | C42: J. Balvin & Willy William
B43: Groove on Lockdown | C43: Joliet
B44: Sucker | C44: Jonas Brothers | D44: 43650 | E44: DLC | F44: DLC Single
B45: Can't Stop The Feeling | C45: Justin Timberlake
B46: Tusa | C46: Karol G ft. Nicki Minaj
B47: The Man | C47: The Killers
B48: Lady Marmalade | C48: LaBelle
B49: Born this Way | C49: Lady Gaga | D49: 40686 | E49: DLC | F49: Part of "Lady Gaga Pack 02"
B50: Old Town Road (Remix) | C50: Lil Nas X ft. Billy Ray Cyrus | D50: 43713 | E50: DLC | F50: DLC Single
B51: Good As Hell | C51: Lizzo
B52: Party Rock Anthem | C52: LMFAO ft. Lauren Bennett & GoonRock | D52: 42733 | E52: DLC | F52: Part of "New Year's Eve 2016 Pack"
B53: Studio 54 | C53: Lord Felix
B54: Thrift Shop | C54: Macklemore & Ryan Lewis ft. Wanz
B55: Moves Like Jagger | C55: Maroon 5 ft. Christina Aguilera | D55: 41149 | E55: Blitz/DLC | F55: Part of "Rock Band Blitz" and as a DLC Single
B56: Symphony Of Destruction | C56: Megadeth | D56: 40960 | E56: DLC | F56: Part of "Megadeth Pack 01"
B57: Me Too | C57: Meghan Trainor
B58: Stir Fry | C58: Migos
B59: O.P.P | C59: Naughty By Nature
B60: Hot in Herre | C60: Nelly
B61: Dragostea Din Tei | C61: O-Zone
B62: Time For Crime | C62: ORION | D62: 43748 | E62: DLC | F62: Part of "4th Anniversary Free DLC Pack"
B63: (Stinn' On) The Dock Of The Day | C63: Otis Redding | D63: 40225 | E63: DLC | F63: Part of "Otis Redding Pack 01"
B64: High Hopes | C64: Panic! At the Disco | D64: 43650 | E64: DLC | F64: DLC Single, and temporarily part of "Season 4 Spotlight Pass Plus" and part of "Guitar Glory Pack"
B65: Wait For Me | C65: Pattern Drama ft. Aquarius Heaven & Hezza Fezza
B66: For An Angel (PvD Remix '09) | C66: Paul van Dyk
B67: Happy | C67: Pharrell Williams | D67: 42661 | E67: DLC | F67: Part of "Rock Band Rivals Pre-Order Bonus"
B68: Give Me Everything | C68: Pitbull ft. Ne-Yo, Afrojack & Nayer
B69: Here Comes Your Man | C69: Pixies | D69: 39623 | E69: DLC | F69: Part of "Doolittle" Album
B70: Better Now | C70: Post Malone
B71: Killing In the Name | C71: Rage Against The Machine | D71: 41037 | E71: DLC | F71: Part of "Rage Against the Machine Pack 01"
B72: Never Gonna Give You Up | C72: Rick Astley | D72: 40953 | E72: DLC | F72: Part of "Gold Star My Heart Pack"
B73: Eyes | C73: RÜFÜS DU SOL
B74: Push It | C74: Salt-N-Pepa
B75: Body Like A Back Road | C75: Sam Hunt | D75: 43118 | E75: DLC | F75: Part of "Going Country 10 Pack"
B76: Temperature | C76: Sean Paul
B77: Any Man of Mine | C77: Shania Twain | D77: 40176 | E77: DLC | F77: Part of "Going Country 02 Pack" and Rock Band Country Track Pack
B78: Cheap Thrills | C78: Sia ft. Sean Paul | D78: 42670 | E78: DLC | F78: DLC Single
B79: All Star | C79: Smash Mouth | D79: 40281 | E79: DLC | F79: DLC Single and part of "Rock Band Hits Pack"
B80: Espresso | C80: Steve Porter
B81: Chaka Zulu | C81: STL GLD ft. Latrell James
B82: Bring Em Out | C82: T.I. ft Jay Z
B83: Dance Monkey | C83: Tones & I
B84: Stressed Out | C84: Twenty One Pilots | D84: 42471 | E84: DLC | F84: Part of "Off the Charts 04" and "Twenty One Pilots Pack 01"
B85: Back to Boston | C85: The Unicorn Princess
B86: Regulate | C86: Warren G & Nate Dogg
B87: Blinding Lights | C87: The Weeknd | D87: 44070 | E87: DLC | F87: DLC Single and Temporarily Part of "Rivals Season 18 Season Pass"
B88: I Wanna Dance With Somebody (Who Loves Me) | C88: Whitney Houston | D88: 42985 | E88: DLC | F88: DLC Single
B89: Bust A Move | C89: Young MC
B90: The Middle | C90: Zedd, Maren Morris & Grey
B93: Songs Released | C93: =COUNT(D:D) -> 32
B94: Total Songs | C94: 89
B95: Percent Complete | C95: =IFERROR(__xludf.DUMMYFUNCTION("TO_PERCENT(C93/C94)"),0.3595505617977528) -> 0.35955056

Sheet Fuser DLC
B2: Song | C2: Artist | D2: Released Date | E2: Source | F2: Notes
B3: A Lot | C3: 21 Savage
B4: Mood | C4: 24kGolldn ft. Iann Dior
B5: Take Over Control | C5: Afrojack ft. Eva Simons
B6: Ironic | C6: Alanis Morissette | D6: 40092 | E6: DLC | F6: DLC SIngle
B7: Leave a Little Love | C7: Alesso & Armin van Buuren
B8: 1 Thing | C8: Amerie
B9: Me Gusta | C9: Anitta ft. Cardi B and Myke Towers
B10: Among the Living | C10: Anthrax | D10: 40449 | E10: DLC | F10: Part of "Anthrax Pack 01"
B11: Your Love (9PM) | C11: ATB, Topic, A7S
B12: Kings & Queens | C12: Ava Max
B13: Loop Pack 06 | C13: Basra Khan
B14: Royce Please | C14: Beast Business
B15: Venus | C15: Bananarama
B16: Baby, I'm Jealous | C16: Bebe Rexha ft. Doja Cat
B17: Poison | C17: Bell Biv DeVoe
B18: Loop Pack 5 | C18: Bignums
B19: Larry's Place (Part II) | C19: Bignums
B20: Therefore I Am | C20: Billie Eilish | D20: 44308 | E20: DLC | F20: DLC Single and Temporarily Part of "Rivals Season 21 Pass"
B21: Holding Out for a Hero | C21: Bonnie Tyler
B22: Soon May the Wellerman Come | C22: Cap'n Spicy Dill
B23: Murder She Wrote | C23: Chaka Demus & Pliers
B24: Tubthumping | C24: Chumbawamba | D24: 40708 | E24: DLC | F24: DLC Single
B25: Should I Stay or Should I Go | C25: The Clash | D25: 39406 | E25: RB1 Export | F25: Export Has Expired
B26: Linger | C26: The Cranberries | D26: 39959 | E26: DLC | F26: DLC Single
B27: Firday I'm in Love | C27: The Cure | D27: 42283 | E27: RB4 | F27: On-Disc Song
B28: Bop | C28: DaBaby
B29: Con Calma | C29: Daddy Yankee ft. Snow
B30: Sandstorm | C30: Darude
B31: Let's Love | C31: David Guetta & Sia
B32: Where Them Girls At | C32: David Guetta ft. Nicki Minaj & Flo Rida
B33: Groove Is in the Heart | C33: Deee-Lite | D33: 44924 | E33: DLC | F33: DLC Single
B34: Smoke on the Water | C34: Deep Purple | D34: 40477 | E34: RB3 Export | F34: Export Has Expired
B35: Days Go By | C35: Dirty Vegas
B36: Latch | C36: Disclosure ft. Sam Smith
B37: Loop Pack 12 | C37: Dissentor
B38: Loco Contigo | C38: DJ Snake, J Balvin & Tyga
B39: New Rules | C39: Dua Lipa
B40: Kiss and Make Up | C40: Dua Lipa & Blackpink
B41: Lips Like Sugar | C41: Echo & the Bunnymen
B42: Lights | C42: Ellie Goulding
B43: Unbelievable | C43: EMF | D43: 40792 | E43: DLC | F43: DLC Single
B44: A Little Respect | C44: Erasure | D44: 40859 | E44: DLC | F44: DLC Single
B45: Bring Me to Life | C45: Evanescence | D45: 39980 | E45: DLC | F45: Part of "Evanescence Pack 01"
B46: Loop Pack 01 | C46: Faint Shadow
B47: Loop Pack 07 | C47: Faint Shadow
B48: Trap Queen | C48: Fetty Wap
B49: She Drives Me Crazy | C49: Fine Young Cannibals | D49: 42684 | E49: DLC | F49: DLC Single
B50: Dreams | C50: Fleetwood Mac | D50: 40645 | E50: DLC | F50: DELISTED
B51: Low | C51: Flo Rida ft. T-Pain
B52: Hard Light | C52: Freda Turner
B53: Don't You Dare | C53: Free Sheets
B54: Unforgettable | C54: French Montana ft. Swae Lee
B55: Mask Off | C55: Future
B56: Gentle on My Mind | C56: Glen Campbell
B57: What Is Love | C57: Haddaway
B58: Maneater | C58: Hall & Oates | D58: 40920 | E58: DLC | F58: Part of "Hall & Oates Pack 01"
B59: Adore You | C59: Harry Styles | D59: 44026 | E59: DLC | F59: DLC Single and Temporarily Part of "Rivals Season 17 Pass Plus"
B60: Golden | C60: Harry Styles | D60: 44194 | E60: DLC | F60: DLC Single
B61: I Love It | C61: Icona Pop ft. Charli XCX
B62: Follow You | C62: Imagine Dragons | D62: 44364 | E62: DLC | F62: DLC Single and Temporarily Part of "Rivals Season 22 Pass"
B63: Here Comes the Hotstepper (Heartical Mix) | C63: Ini Kamoze
B64: No Role Modelz | C64: J. Cole
B65: Always on Time | C65: Ja Rule ft. Ashanti
B66: Whats Poppin' | C66: Jack Harlow
B67: Submerged | C67: Jackson Oak
B68: Take You Dancing | C68: Jason Derulo
B69: Head & Heart | C69: Joel Corry ft. MNEK
B70: Rock Your Body | C70: Justin Timberlake
B71: What Ifs | C71: Kane Brown ft. Lauren Alaina
B72: Whine Up | C72: Kat DeLuna ft. Elephant Man
B73: Walking on Sunshine | C73: Katrina and the Waves | D73: 40120 | E73: LEGO Export | F73: Export Has Expired
B74: Stronger (What Doesn't Kill You) | C74: Kelly Clarkson | D74: 41149 | E74: Blitz/DLC | F74: Part of "Rock Band Blitz" and as a DLC Single
B75: Young Dumb & Broke | C75: Khalid
B76: Mr. Brightside | C76: The Killers | D76: 39777 | E76: DLC | F76: Part of "The Killers Pack 01" and "Rock Band Hits Pack"
B77: Una Noche Mas | C77: La Guerra Naranja
B78: Sour Candy | C78: Lady Gaga & Blackpink
B79: Montero (Call Me By Your Name) | C79: Lil Nas X | D79: 44511 | E79: DLC | F79: DLC Single and Temporarily Part of "Rivals Season 24 Pass"
B80: XO Tour Llif3 | C80: Lil Uzi Vert
B81: Crystal Beach | C81: The Lingala Sound
B82: Numb | C82: Linkin Park | D82: 40554 | E82: DLC | F82: Part of "Linkin Park Part 1"
B83: Juice | C83: Lizzo | D83: 43944 | E83: DLC | F83: DLC Single, and temporaily part of "Season 16 Spotlight Pass Plus"
B84: Moon Lab | C84: Lossage
B85: My Ex's Best Friend | C85: Machine Gun Kelly & Blackbear | D85: 44287 | E85: DLC | F85: DLC Single and Temporarily Part of "Rivals Season 21 Pass"
B86: Nothing Breaks Like a Heart | C86: Mark Ronson ft. Miley Cyrus
B87: This is How You Left Me | C87: Marlon Kane
B88: Maps | C88: Maroon 5
B89: Happier | C89: Marshmello ft. Bastille
B90: Too Much | C90: Marshmello, Imanbek ft. Usher
B91: Animals | C91: Martin Garrix
B92: Feel So Good | C92: Mase
B93: Astronaut in the Ocean | C93: Masked Wolf | D93: 44371 | E93: DLC | F93: DLC Single and Temporarily Part of "Rivals Season 22 Pass"
B94: I Melt with You | C94: Modern English | D94: 41233 | E94: DLC | F94: DLC Single
B95: Hip Hop Hooray | C95: Naughty by Nature
B96: Starships | C96: Nicki Minaj | D96: 42605 | E96: DLC | F96: DLC Single
B97: Self Esteem | C97: The Offspring | D97: 39728 | E97: DLC | F97: Part of "The Offspring Pack 01"
B98: Counting Stars | C98: OneRepublic | D98: 42817 | E98: DLC | F98: DLC SIngle
B99: Daning's Not a Crime | C99: Panic! at the Disco
B100: Just About to Snap | C100: Pinhole Cage
B101: Circles | C101: Post Malone | D101: 43860 | E101: DLC | F101: DLC Single and Temporarily Part of "Rivals Season 15 Pass"
...

Sheet Fortnite Festival
B2: Song | C2: Artist | D2: Release Date | E2: Source | F2: Notes
B3: Dirty Little Secret | C3: The All-American Rejects | D3: 39441 | E3: DLC | F3: DLC Single
B4: Pompeii
B5: Poison | C5: Bell Biv Devoe
B6: Bad Guy | C6: Billie Eilish | D6: 43818 | E6: DLC | F6: Part of "Headliners Pack" and temporaraily part of "Apple Music Spotlight Pass"
B7: Zombie | C7: The Cranberries | D7: 39959 | E7: DLC | F7: DLC Single
B8: Cake By The Ocean | C8: DNCE | D8: 42472 | E8: DLC | F8: Part of "Off The Charts 04"
B9: Brace For Chaos | C9: Epic Games
B10: Butter Barn Hoedown | C10: Epic Games
B11: Run It | C11: Epic Games
B12: Switch Up | C12: Epic Games
B13: Take Me Higher | C13: Epic Games
B14: My Songs Know What You Did In The Dark (Light Em Up) | C14: Fall Out Boy | D14: 42451 | E14: DLC | F14: Part of "Off The Charts Pack 03"
B15: Dog Days Are Over | C15: Florence + The Machine | D15: 41035 | E15: DLC | F15: DLC Single
B16: Highway Tune | C16: Greta Van Fleet
B17: Heat Waves | C17: Glass Animals
B18: Thunder | C18: Imagine Dragons | D18: 43083 | E18: DLC | F18: Part of "Off the Charts Pack 06"
B19: I | C19: Kendrick Lamar
B20: Mr. Brightside | C20: The Killers | D20: 39777 | E20: DLC | F20: Part of "The Killers Pack 01" and "Rock Band Hits Pack"
B21: Suddenly I See | C21: KT Tunstall | D21: 40120 | E21: LEGO Export | F21: Export Has Expired
B22: Bad Romance | C22: Lady Gaga | D22: 40253 | E22: DLC | F22: Part of "Lady Gaga Pack 1"
B23: Party Rock Anthem | C23: LMFAO Ft. Lauren Bennett & Goonrock | D23: 42733 | E23: DLC | F23: Part of "New Year's Eve 2016 Pack"
B24: Emo Girl | C24: Machine Gun Kelly Ft. Willow
B25: The Search | C25: NF
B26: Hand That Feeds You | C26: Nine Inch Nails | D26: 39406 | E26: RB1 Export/DLC | F26: Export Has Expired, but was re-released as a Single
B27: Vampire | C27: Olivia Rodrigo
B28: Counting Stars | C28: OneRepublic | D28: 42817 | E28: DLC | F28: DLC Single
B29: Gangnam Style | C29: PSY
B30: Go With The Flow | C30: Queens of the Stone Age | D30: 39406 | E30: RB1 Export/DLC | F30: Export Has Expired but has been released a Part of "Rock Band Rewind Pack 01" and "Rock Band 15th Anniversary"
B31: Stiches | C31: Shawn Mendes
B32: Cradles | C32: Sub Urban | D32: 44070 | E32: DLC | F32: DLC Single and Temporarily Part of "Rivals Season 18 Season Pass"
B33: Can't Feel My Face | C33: The Weeknd | D33: 42353 | E33: DLC | F33: Part of "Off The Charts 02"
B34: Blinging Lights | C34: The Weeknd
B35: The Hills | C35: The Weeknd | D35: 42471 | E35: DLC | F35: Part of "Off the Charts 04"
B36: Save Your Tears | C36: The Weeknd
B37: Take My Breath | C37: The Weeknd | D37: 44070 | E37: DLC | F37: DLC Single
B38: Buddy Holly | C38: Weezer | D38: 39434 | E38: DLC | F38: DLC Single
B39: Seven Nation Army | C39: The White Stripes | D39: 40246 | E39: DLC | F39: Part of "The White Stripes Pack 02"
B40: Nothing's Alright | C40: Witchgang
B43: Songs Released | C43: =COUNT(D:D) -> 20
B44: Total Songs | C44: 38
B45: Percent Complete | C45: =IFERROR(__xludf.DUMMYFUNCTION("TO_PERCENT(C43/C44)"),0.5263157894736842) -> 0.52631579

Sheet GH1
B2: Song | C2: Artist | D2: Release Date | E2: Source | F2: Notes
B3: Callout | C3: The Acro-Bats
B4: Behind the Mask | C4: Anarchy Club
B5: The Breaking Wheel | C5: Artillery
B6: Cochise* | C6: Audioslave
B7: Caveman Rejoice | C7: The Bags
B8: Infected* | C8: Bad Religion
B9: Fire it Up | C9: Black Label Society
B10: Iron Man* | C10: Black Sabbath
B11: Godzilla* | C11: Blue Oyster Cult | D11: 40204 | E11: DLC | F11: DLC Single and part of "Guitar Glory Pack"
B12: More Than A Feeling* | C12: Boston | D12: 39532 | E12: DLC | F12: Part of "Boston Pack 01"
B13: Heart Full of Black* | C13: Burning Brides
B14: Sail Your Ship By | C14: Count Zero
B15: Crossroads* | C15: Cream
B16: Ziggy Stardust* | C16: David Bowie | D16: 40568 | E16: DLC | F16: Part of "David Bowie Pack 02"
B17: Smoke On the Water* | C17: Deep Purple | D17: 40477 | E17: RB3 Export | F17: Export Has Expired
B18: Fly on the Wall | C18: Din
B19: Take It Off* | C19: The Donnas | D19: 44630 | E19: DLC | F19: DLC Single and Temporarily Part of "Rivals Season 25 Pass"
B20: Decontrol | C20: Drist
B21: Frankenstein* | C21: The Edgar Winter Group | D21: 40925 | E21: DLC | F21: DLC Single
B22: Hey You* | C22: The Exies
B23: Take Me Out* | C23: Franz Ferdinand | D23: 39938 | E23: DLC | F23: Part of "Franz Ferdinand Pack 01" and "Guitar Glory Pack"
B24: Get Ready 2 Rokk | C24: Freezepop | D24: 40065 | E24: DLC | F24: Part of "Freezepop Pack 01" and "30 Song Mega Pack"
B25: Cheat on the Church | C25: Graveyard BBQ | D25: 43059 | E25: DLC | F25: Part of "Rock Band 10th Anniversary Pack"
B26: Unsung* | C26: Helmet
B27: Hey | C27: Honest Bob and the Factory-to-Dealer Incentives | D27: 40798 | E27: RBN | F27: Not compatible with RB4
B28: Stellar* | C28: Incubus | D28: 44616 | E28: DLC | F28: DLC Single and Temporarily Part of "Rivals Season 25 Pass"
B29: Spanish Castle Magic* | C29: Jimi Hendrix | D29: 40267 | E29: DLC | F29: RB has Vocals Included and is Part of "Axis: Bold as Love" Album
B30: I Love Rock N' Roll* | C30: Joan Jett and the Blackhearts | D30: 40477 | E30: RB3 Export | F30: Export Has Expired
B31: You've Got Another Thing Coming* | C31: Judas Priest | D31: 39560 | E31: DLC | F31: Part of "Screaming for Vengence" album and Metal Track Pack
B32: Farewell Myth | C32: Made in Mexico
B33: Symphony of Destruction* | C33: Megadeth | D33: 40960 | E33: DLC | F33: Part of "Megadeth Pack 01"
B34: Story of My Love | C34: The Model Sons
B35: Guitar Hero | C35: Monkey Steals the Peach
B36: Ace of Spades* | C36: Motorhead | D36: 39705 | E36: RB2 Export | F36: Export Has Expired, but Reliscened as a Single
B37: Bark at the Moon* | C37: Ozzy Osbourne | D37: 40694 | E37: DLC | F37: Available exclusively in the "Ozzy 8-Pack"
B38: Cowboys From Hell* | C38: Pantera | D38: 42283 | E38: DLC | F38: RB has "Live From Monsters in Moscow" Version as a Single and part of "Guitar Glory Pack"
B39: Killer Queen* | C39: Queen | D39: 40106 | E39: DLC | F39: Part of "Queen Pack 01" and "Queen RB3 Enhanced Pack"
B40: No One Knows* | C40: Queens of the Stone Age | D40: 40477 | E40: RB3 Export | F40: Export Has Expired
B41: I Wanna Be Sedated* | C41: The Ramones | D41: 40477 | E41: RB3 Export/DLC | F41: Export Has Expired but was re-released in "Solid '70's Pack 2" and in "Guitar Glory Pack"
B42: Higher Ground* | C42: Red Hot Chili Peppers | F42: RB Has Stevie Wonder Version
B43: All of This | C43: Shaimus | D43: 40253 | E43: DLC | F43: DLC Single
B44: Even Rats | C44: The Slip | D44: 40241 | E44: RBN | F44: Not compatible with RB4
B45: Texas Flood* | C45: Stevie Ray Vaughan | D45: 39875 | E45: DLC | F45: Part of "Texan Flood" Album
B46: Fat Lip* | C46: Sum 41 | D46: 40939 | E46: DLC | F46: DLC Single
B47: Thunder Kiss '65* | C47: White Zombie | D47: 40841 | E47: DLC | F47: DLC Single
B48: Eureka, I've Found Love | C48: The Upper Crust
B49: Sharp Dressed Man* | C49: ZZ Top
B52: Songs Released | C52: =COUNT(D:D) -> 26
B53: Total Songs | C53: 47
B54: Percent Complete | C54: =IFERROR(__xludf.DUMMYFUNCTION("TO_PERCENT(C52/C53)"),0.5531914893617021) -> 0.55319149
B56: *Cover version

Sheet GH2
B2: Song | C2: Artist | D2: Release Date | E2: Source | F2: Notes
B3: Laughtrack | C3: The Acro-Brats
B4: Last Child | C4: Aerosmith
B5: Billion Dollar Babies | C5: Alice Cooper | D5: 39952 | E5: DLC | F5: Live Version part of "Alice Cooper Pack 01"
B6: Them Bones | C6: Alice in Chains | D6: 43020 | E6: DLC | F6: Part of "Alice in Chains Pack 03"
B7: Jessica | C7: The Allman Brothers Band | D7: 41233 | E7: DLC | F7: DLC Single
B8: Six | C8: All That Remains
B9: Collide | C9: Anarchy Club | D9: 43059 | E9: DLC | F9: Part of "Rock Band 10th Anniversary Pack"
B10: Madhouse | C10: Anthrax | D10: 40449 | E10: DLC | F10: Live Version part of "Anthrax Pack 01"
B11: Mr. Fix It | C11: The Amazing Crowns
B12: Beast and the Harlot | C12: Avenged Sevenfold | D12: 40477 | E12: RB3 Export/DLC | F12: Export Has Expired, but re-released as a Single
B13: Push Push (Lady Lightning) | C13: Bang Camaro | D13: 42465 | E13: DLC | F13: Part of "30 Song Mega Pack"
B14: War Pigs | C14: Black Sabbath | D14: 39420 | E14: DLC | F14: Cover Part of "Black Sabbath Pack 01"
B15: One for the Road | C15: The Breaking Wheel
B16: Gemini | C16: Brian Kahanek | D16: 41242 | E16: RBN | F16: Not compatible with RB4
B17: Jordan | C17: Buckethead
B18: Who Was in My Room Last Night? | C18: The Butthole Surfers
B19: Radium Eyes | C19: Count Zero
B20: Surrender | C20: Cheap Trick | D20: 40792 | E20: DLC | F20: Part of "Cheap Trick Pack 01"
B21: Mother | C21: Danzig
B22: Hush | C22: Deep Purple
B23: Thunderhorse | C23: Dethklok
B24: Misirlou | C24: Dick Dale
B25: Arterial Black | C25: Drist
B26: The New Black | C26: Every Time I Die
B27: Monkey Wrench | C27: Foo Fighters | D27: 39763 | E27: DLC | F27: Part of "The Colour and the Shape" Album
B28: Less Talk More Rokk | C28: Freezepop | D28: 40066 | E28: DLC | F28: Part of "Freezepop Pack 01" and "30 Song Mega Pack" | I28: Guitar Hero II
B29: Sweet Child o' Mine | C29: Guns N' Roses | I29: 39028
B30: Crazy on You | C30: Heart | D30: 43440 | E30: DLC | F30: DLC Single and Temporarily Part of "Rivals Season 9 Pass"
B31: Soy Bomb | C31: Honest Bob and the Factory-to-Dealer Incentives | D31: 43059 | E31: DLC | F31: Part of "Rock Band 10th Anniversary Pack"
B32: The Trooper | C32: Iron Maiden | D32: 39973 | E32: DLC | F32: Part of "Iron Maiden Pack 01"
B33: Search and Destroy | C33: Iggy Pop and the Stooges
B34: Stop! | C34: Jane's Addiction | D34: 42647 | E34: DLC | F34: DLC Single
B35: Carry On Wayward Son | C35: Kansas | D35: 39705 | E35: RB2 Export/DLC | F35: Export Has Expired but Re-Released in the "Solid '70s Pack 01"
B36: Strutter | C36: Kiss | D36: 40659 | E36: DLC | F36: Live Version as a DLC Single
B37: Laid to Rest | C37: Lamb of God | D37: 39777 | E37: DLC | F37: Part of "Metal Track Pack" and as a DLC Single
B38: Raw Dog | C38: The Last Vegas
B39: Carry Me Home | C39: The Living End
B40: Free Bird | C40: Lynyrd Skynyrd | D40: 40477 | E40: RB3 Export/DLC | F40: Export Has Expired, but re-released as a Single
B41: Yes We Can | C41: Made in Mexico
B42: Girlfriend | C42: Matthew Sweet
B43: Hangar 18 | C43: Megadeth | D43: 40220 | E43: DLC | F43: Part of "Rust in Peace" Album
B44: Red Lottery | C44: Megasus
B45: Shout at the Devil | C45: Mötley Crüe
B46: Dead! | C46: My Chemical Romance
B47: Heart Shaped Box | C47: Nirvana | D47: 40806 | E47: DLC | F47: Part of "Celebrating Nirvana Pack"
B48: Parasite | C48: The Neighborhoods
B49: Kicked to the Curb | C49: Noble Rot
B50: Drink Up | C50: Ounce of Self
B51: Life Wasted | C51: Pearl Jam
B52: Message in a Bottle | C52: The Police | D52: 39553 | E52: DLC | F52: Part of "The Police Tack Pack 01" and "Classic Rock Track Pack"
B53: Tattooed Love Boys | C53: The Pretenders
B54: John the Fisherman | C54: Primus
B55: Killing in the Name | C55: Rage Against the Machine | D55: 41037 | E55: DLC | F55: Part of "Rage Against the Machine Pack 01"
B56: Salvation* | C56: Rancid
B57: Psychobilly Freakout* | C57: Reverend Horton Heat
B58: Rock and Roll, Hoochie Koo | C58: Rick Derringer | D58: 42283 | E58: RB4 | F58: On-Disc Song
B59: Can't You Hear Me Knockin' | C59: The Rolling Stones
B60: YYZ | C60: Rush | D60: 39714 | E60: DLC | F60: Part of "Moving Pictures" Album
B61: The Light That Blinds | C61: Shadows Fall
B62: Tonight I'm Gonna Rock You Tonight* | C62: Spinal Tap | D62: 40029 | E62: DLC | F62: DELISTED
B63: Rock This Town* | C63: Stray Cats | D63: 42563 | E63: DLC | F63: Brian Setzer Re-record Available as a DLC Single and part of "Guitar Glory Pack"
B64: Trippin' on a Hole in a Paper Heart* | C64: Stone Temple Pilots | D64: 40470 | E64: DLC | F64: Part of "Stone Temple Pilots Pack 01"
B65: Trogdor | C65: Strong Bad
B66: Institutionalized | C66: Suicidal Tendencies
B67: Freya | C67: The Sword
B68: Possum Kingdom | C68: Toadies | D68: 41254 | E68: DLC | F68: Part of "The Toadies Pack 01"
B69: Elephant Bones | C69: That Handsome Devil
B70: Bad Reputation | C70: Thin Lizzy
B71: You Really Got Me | C71: Van Halen
B72: X-Stream | C72: Voivod
B73: Cherry Pie* | C73: Warrant | D73: 42521 | E73: DLC | F73: DLC Single
B74: Woman* | C74: Wolfmother | D74: 40113 | E74: DLC | F74: Part of "Wolfmother Pack 01"
B75: FTK | C75: VAGIANT
B76: Fall of Pangea | C76: Valient Thorr
B79: Songs Released | C79: =COUNT(D:D) -> 32
B80: Total Songs | C80: 74
B81: Percent Complete | C81: =IFERROR(__xludf.DUMMYFUNCTION("TO_PERCENT(C79/C80)"),0.43243243243243246) -> 0.43243243
B83: *Cover version

Sheet GH2 DLC
B2: Song | C2: Artist | D2: Release Date | E2: Source | F2: Notes
B3: Ex's and Oh's | C3: Atreyu
B4: Infected* | C4: Bad Religion
B5: You Should Be Ashamed of Myself | C5: The Bled
B6: Smoke on the Water* | C6: Deep Purple | D6: 40477 | E6: RB3 Export | F6: Export Has Expired
B7: Take It Off* | C7: The Donnas | D7: 44630 | E7: DLC | F7: DLC Single and Temporarily Part of "Rivals Season 25 Pass"
B8: The State of Massachusetts | C8: Dropkick Murphys
B9: Frankenstein* | C9: The Edgar Winter Group | D9: 40925 | E9: DLC | F9: DLC Single
B10: Hey You* | C10: The Exies
B11: Stellar* | C11: Incubus | D11: 44616 | E11: DLC | F11: DLC Single and Temporarily Part of "Rivals Season 25 Pass"
B12: You've Got Another Thing Comin'* | C12: Judas Priest | D12: 39560 | E12: DLC | F12: Part of "Screaming for Vengence" album and Metal Track Pack
B13: Sin Documentos | C13: Los Rodríguez
B14: Memories of the Grove | C14: Maylene and the Sons of Disaster
B15: Ace of Spades* | C15: Motörhead | D15: 39705 | E15: RB2 Export/DLC | F15: Export Has Expired, but has been Re-Liscened as a Single
B16: Famous Last Words | C16: My Chemical Romance | D16: 42528 | E16: DLC | F16: DLC Single
B17: Teenagers | C17: My Chemical Romance | D17: 41268 | E17: DLC | F17: Part of "My Chemical Romance Pack 01"
B18: This Is How I Disappear | C18: My Chemical Romance
B19: Bark at the Moon* | C19: Ozzy Osbourne | D19: 40694 | E19: DLC | F19: Available exclusively in the "Ozzy 8-Pack"
B20: Sept | C20: Pleymo
B21: Bury the Hatchet | C21: Protest the Hero
B22: Killer Queen* | C22: Queen | D22: 40106 | E22: DLC | F22: Part of "Queen Pack 01" and "Queen RB3 Enhanced Pack"
B23: I Wanna Be Sedated* | C23: The Ramones | D23: 40477 | E23: RB3 Export/DLC | F23: Export Has Expired but was re-released in "Solid '70's Pack 2" and in "Guitar Glory Pack"
B24: Higher Ground* | C24: Red Hot Chili Peppers | F24: RB has Stevie Wonder Version
B25: Exile | C25: Soilwork
B26: Detonation | C26: Trivium
I28: Guitar Hero II DLC
B29: Songs Released | C29: =COUNT(D:D) -> 11 | I29: Apr. 11, 2007 - Nov. 29,2007
B30: Total Songs | C30: 24
B31: Percent Complete | C31: =IFERROR(__xludf.DUMMYFUNCTION("TO_PERCENT(C29/C30)"),0.4583333333333333) -> 0.45833333
B33: *Cover version

Sheet GH3
B2: Song | C2: Artist | D2: Release Date | E2: Source | F2: Notes
B3: Same Old Song and Dance | C3: Aerosmith
B4: Miss Murder | C4: AFI | D4: 40066 | E4: DLC | F4: DLC Single
B5: School's Out* | C5: Alice Cooper | D5: 39952 | E5: DLC | F5: Live Version Part of "Alice Cooper Pack 01"
B6: Impulse | C6: An Endless Sporadic | D6: 40864 | E6: RBN | F6: Not compatible with RB4
B7: Minus Celsius | C7: Backyard Babies
B8: Sabotage | C8: Beastie Boys | D8: 39406 | E8: RB1 Export/DLC | F8: Export Has Expired but has been released a Part of "Rock Band Rewind Pack 01" and "Rock Band 15th Anniversary"
B9: Paranoid* | C9: Black Sabbath | D9: 39406 | E9: RB1 | F9: Cover that was never Exportable
B10: Helicopter | C10: Bloc Party
B11: Cities on Flame with Rock and Roll* | C11: Blue Öyster Cult
B12: Go That Far | C12: Bret Michaels Band
B13: Sunshine of Your Love* | C13: Cream
B14: Holiday in Cambodia* | C14: Dead Kennedys | D14: 39770 | E14: DLC | F14: Part of "Dead Kennedys Pack 01" and "Classic Rock Track Pack"
B15: Hier kommt Alex | C15: Die Toten Hosen | D15: 39588 | E15: DLC | F15: DELISTED
B16: Stricken | C16: Disturbed | D16: 39945 | E16: DLC | F16: DLC Single
B17: Nothing for Me Here | C17: Dope
B18: Through the Fire and Flames | C18: DragonForce | D18: 40631 | E18: DLC | F18: DLC Single and part of "Rock Band Hits Pack"
B19: Cliffs of Dover | C19: Eric Johnson
B20: F.C.P.R.E.M.I.X. | C20: The Fall of Troy | D20: 44854 | E20: DLC | F20: DLC SIngle and Temporarily Part of "Rivals Season 28 Pass"
B21: Slow Ride | C21: Foghat | D21: 43041 | E21: DLC | F21: Part of 'Solid '70's Pack 2"
B22: In the Belly of a Shark | C22: Gallows
B23: Welcome to the Jungle | C23: Guns N' Roses
B24: Barracuda | C24: Heart | D24: 40757 | E24: DLC | F24: DLC Single
B25: I'm in the Band | C25: Hellacopters
B26: Avalancha | C26: Héroes del Silencio
B27: Take This Life | C27: In Flames
B28: The Number of the Beast | C28: Iron Maiden | D28: 39455 | E28: DLC | F28: Cover as a single and Original is Part of "Iron Maiden Pack 01" | I28: Guitar Hero III: Legends of Rock
B29: Ruby | C29: Kaiser Chiefs | D29: 40120 | E29: LEGO Export | F29: Export Has Expired | I29: 39383
B30: When You Were Young | C30: The Killers | D30: 39406 | E30: RB1 Export/DLC | F30: Export Has Expired but has been re-released as a DLC Single
B31: My Curse | C31: Killswitch Engage | D31: 39672 | E31: DLC | F31: Part of "Roadrunner Records Pack 01"
B32: Rock and Roll All Nite | C32: Kiss | D32: 40659 | E32: DLC | F32: RB has live version as a DLC Single
B33: Down 'n Dirty | C33: L.A. Slum Lords
B34: Closer | C34: Lacuna Coil | D34: 39770 | E34: DLC | F34: Part of "Century Media Girls of Metal Pack" and Metal Track Pack"
B35: Metal Heavy Lady | C35: Lions
B36: Cult of Personality | C36: Living Colour | D36: 41150 | E36: Blitz/DLC | F36: Part of Rock Band Blitz and as a DLC Single
B37: Monsters | C37: Matchbook Romance
B38: One | C38: Metallica
B39: Mississippi Queen | C39: Mountain | D39: 39406 | E39: RB1 Export | F39: Export Has Expired, and it's a cover
B40: Knights of Cydonia | C40: Muse | D40: 44805 | E40: DLC | F40: Part of "Muse Pack 01" and Temporarily Part of "Rivals Season 28 Pass"
B41: Mauvais Garçon | C41: Naast
B42: Hit Me with Your Best Shot | C42: Pat Benatar | D42: 39847 | E42: DLC | F42: Part of "Classic Rock Track Pack" and as a DLC Single
B43: Even Flow | C43: Pearl Jam | D43: 39896 | E43: DLC | F43: Part of "Ten" Album and "Rock Band Hits Pack 02"
B44: Talk Dirty to Me | C44: Poison | D44: 40722 | E44: DLC | F44: Part of "Poison Pack 01"
B45: Lay Down | C45: Priestess
B46: The Way It Ends | C46: Prototype | D46: 40864 | E46: RBN | F46: Not Compatible with RB4
B47: 3's & 7's | C47: Queens of the Stone Age | D47: 39406 | E47: DLC | F47: Part of "Queens of the Stone Age Pack 01"
B48: Bulls on Parade | C48: Rage Against the Machine | D48: 40204 | E48: DLC | F48: Part of "Metal Track Pack" and as DLC Single
B49: Suck My Kiss | C49: Red Hot Chili Peppers | D49: 39721 | E49: DLC | F49: DELISTED
B50: Generation Rock | C50: Revolverheld
B51: Prayer of the Refugee | C51: Rise Against | D51: 40015 | E51: DLC | F51: Part of "Rise Against Pack 01"
B52: Paint It Black | C52: The Rolling Stones
B53: Black Magic Woman | C53: Santana | D53: 40631 | E53: DLC | F53: Part of "Days of Peace Pack 01"
B54: Rock You Like a Hurricane* | C54: Scorpions | D54: 44546 | E54: DLC | F54: DLC Single and Temporarily Part of "Rivals Season 24 Pass"
B55: In Love | C55: Scouts of St. Sebastian
B56: Can't Be Saved | C56: Senses Fail
B57: Anarchy in the U.K. | C57: Sex Pistols
B58: Raining Blood | C58: Slayer | D58: 41009 | E58: DLC | F58: Part of "Slayer Pack 01"
B59: Don't Hold Back | C59: The Sleeping
B60: Before I Forget | C60: Slipknot | D60: 40477 | E60: RB3 Export | F60: Export Has Expired
B61: Cherub Rock | C61: The Smashing Pumpkins | D61: 39406 | E61: RB1 Export/DLC | F61: Export Has Expired but has been released a Part of "Rock Band Rewind Pack 01" and "Rock Band 15th Anniversary"
B62: Story of My Life | C62: Social Distortion | D62: 39945 | E62: DLC | F62: Part of "Social Distortion Pack 01"
B63: Kool Thing | C63: Sonic Youth | D63: 39581 | E63: DLC | F63: DLC Single
B64: The Devil Went Down to Georgia | C64: Steve Ouimette
B65: Pride and Joy | C65: Stevie Ray Vaughan | D65: 39875 | E65: DLC | F65: Part of "Texas Flood" Album
B66: She Bangs the Drums* | C66: The Stone Roses
B67: Reptilia | C67: The Strokes | D67: 39406 | E67: RB1 Export/DLC | F67: Export Has Expired, but re-released as a DLC single
B68: Radio Song | C68: Superbus
B69: The Metal | C69: Tenacious D | D69: 40099 | E69: DLC | F69: Part of "Brutal Legends Pack 01"
B70: My Name Is Jonas | C70: Weezer | D70: 40022 | E70: DLC | F70: Part of "Weezer Pack 02"
B71: Black Sunshine | C71: White Zombie | D71: 39861 | E71: DLC | F71: DLC Single
B72: The Seeker | C72: The Who | D72: 42283 | E72: RB4 | F72: On-Disc Setlist
B73: La Grange* | C73: ZZ Top
B76: Songs Released | C76: =COUNT(D:D) -> 42
B77: Total Songs | C77: 71
B78: Percent Complete | C78: =IFERROR(__xludf.DUMMYFUNCTION("TO_PERCENT(C76/C77)"),0.5915492957746479) -> 0.5915493
B80: *Cover version

Sheet GH3 DLC
B2: Song | C2: Artist | D2: Release | E2: Source | F2: Notes
B3: Dream On | C3: Aerosmith | D3: 41303 | E3: DLC | F3: Live Version is part of "Aerosmith's Greatest Dimensions Pack"
B4: Carcinogen Crush | C4: AFI
B5: Almost Easy | C5: Avenged Sevenfold | D5: 39705 | E5: RB2 Export | F5: Export Has Expired
B6: Peace of Mind | C6: Boston | D6: 39532 | E6: DLC | F6: Part of "Boston Pack 01" and "Classic Rock Track Pack"
B7: Soothsayer | C7: Buckethead
B8: God Put a Smile upon Your Face | C8: Coldplay
B9: Violet Hill | C9: Coldplay
B10: Yellow | C10: Coldplay | D10: 40834 | E10: DLC | F10: Part of "Coldplay Collection 01"
B11: Nine Lives | C11: Def Leppard
B12: Photograph | C12: Def Leppard | D12: 40764 | E12: DLC | F12: Part of "Def Leppard Pack 01"
B13: Rock of Ages | C13: Def Leppard | D13: 40764 | E13: DLC | F13: Part of "Def Leppard Pack 01"
B14: Hole in the Earth | C14: Deftones | D14: 40337 | E14: DLC | F14: Part of "Deftones Pack 01"
B15: Ernten Was Wir Säen | C15: Die Fantastischen Vier
B16: Heroes of Our Time | C16: DragonForce
B17: Operation Ground and Pound | C17: DragonForce | D17: 40631 | E17: DLC | F17: DLC Single
B18: Revolution Deathsquad | C18: DragonForce
B19: Famous For Nothing | C19: Dropkick Murphys
B20: (F)lannigan's Ball | C20: Dropkick Murphys
B21: Johnny, I Hardly Knew Ya | C21: Dropkick Murphys
B22: So Payaso | C22: Extremoduro
B23: Tina | C23: Flyleaf
B24: All My Life | C24: Foo Fighters | D24: 40043 | E24: DLC | F24: Part of "Foo Fighters Pack 02"
B25: The Pretender | C25: Foo Fighters | D25: 40120 | E25: DLC | F25: Part of "Foo Fighters Pack 03"
B26: This Is a Call | C26: Foo Fighters | D26: 39805 | E26: DLC | F26: Part of "Foo Fighters Pack 01"
B27: Jukebox Hero | C27: Foreigner | D27: 39406 | E27: DLC | F27: Cover is a DLC Single
B28: The End Begins (to Rock) | C28: God of War II | I28: Guitar Hero III DLC
B29: Surfing with the Alien | C29: Joe Satriani | D29: 40099 | E29: DLC | F29: DLC Single | I29: Oct. 31, 2007- Sept. 12, 2008
B30: Any Way You Want It | C30: Journey | D30: 39705 | E30: RB2 | F30: Never Exportable From RB2
B31: I Predict a Riot | C31: Kaiser Chiefs | D31: 40043 | E31: DLC | F31: DLC Single
B32: Shoot the Runner | C32: Kasabian | D32: 39714 | E32: DLC | F32: DLC Single
B33: I Am Murloc | C33: L70ETC
B34: No More Sorrow | C34: Linkin Park
B35: Putting Holes in Happiness (Nick Zinner Remix) | C35: Marilyn Manson
B36: Sleeping Giant | C36: Mastodon
B37: All Nightmare Long | C37: Metallica
B38: Broken, Beat & Scarred | C38: Metallica
B39: Cyanide | C39: Metallica
B40: The Day That Never Comes | C40: Metallica
B41: The End of the Line | C41: Metallica
B42: The Judas Kiss | C42: Metallica
B43: My Apocalypse | C43: Metallica
B44: Suicide & Redemption J.H. | C44: Metallica
... B47: The Unforgiven III | C47: Metallica
B48: (We Are) The Road Crew | C48: Motörhead | D48: 40099 | E48: DLC | F48: 2008 Re-Recorded Version is part of "Brutal Legends Pack 01"
B49: Stay Clean | C49: Motörhead
B50: Motorhead | C50: Motörhead
B51: Exo-Politics | C51: Muse
B52: Stockholm Syndrome | C52: Muse
B53: Supermassive Black Hole | C53: Muse
B54: Don't Speak | C54: No Doubt | D54: 39791 | E54: DLC | F54: Part of "Tragic Kingdom" Album and The Singles: "1993 to 2003" Album
B55: Excuse Me Mr. | C55: No Doubt | D55: 39791 | E55: DLC | F55: Part of "Tragic Kingdom" Album and The Singles: "1993 to 2003" Album
B56: Sunday Morning | C56: No Doubt | D56: 39791 | E56: DLC | F56: Part of "Tragic Kingdom" Album and The Singles: "1993 to 2003" Album
B57: Halo Theme MJOLNIR Mix | C57: O'Donnell/Salvatori/Vai
B58: Problems (Live at Brixton) | C58: Sex Pistols
B59: We Three Kings | C59: Steve Ouimette
B60: Top Gun Anthem | C60: Steve Ouimette
B61: For The Love of God | C61: Steve Vai | D61: 43734 | E61: DLC | F61: Live Version available as a DLC Single
B62: Pretty Handsome Awkward | C62: The Used
B63: The Arsonist | C63: Thrice
B64: Antisocial | C64: Trust
B65: Messages | C65: Velvet Revolver
B66: She Builds Quick Machines | C66: Velvet Revolver
B67: Slither | C67: Velvet Revolver
B70: Songs Released | C70: =COUNT(D:D) -> 21
B71: Total Songs | C71: 65
B72: Percent Complete | C72: =IFERROR(__xludf.DUMMYFUNCTION("TO_PERCENT(C70/C71)"),0.3230769230769231) -> 0.32307692

Sheet GH World Tour
B2: Song | C2: Artist | D2: Released Date | E2: Source | F2: Notes
B3: Beautiful Disaster | C3: 311 | D3: 41184 | E3: DLC | F3: Part of "311 Pack 01"
B4: The Kill | C4: 30 Seconds to Mars | D4: 39441 | E4: DLC | F4: DLC Single
B5: Too Much, Too Young, Too Fast | C5: Airbourne
B6: Ramblin' Man | C6: The Allman Brothers Band | D6: 39705 | E6: RB2 Export | F6: Export Has Expired
B7: Good God | C7: Anouk
B8: Never Too Late | C8: The Answer
B9: One Armed Scissor | C9: At the Drive-In | D9: 40477 | E9: RB3 Export | F9: Export Has Expired
B10: No Sleep Till Brooklyn | C10: Beastie Boys | D10: 40757 | E10: DLC | F10: DLC Single
B11: Hail to the Freaks | C11: Beatsteaks
B12: Rebel Yell | C12: Billy Idol | D12: 40050 | E12: DLC | F12: DLC Single
B13: Stillborn | C13: Black Label Society
B14: Weapon of Choice | C14: Black Rebel Motorcycle Club | D14: 39994 | E14: DLC | F14: DLC Single
B15: Dammit | C15: Blink-182 | D15: 39749 | E15: DLC | F15: DLC Single
B16: One Way or Another | C16: Blondie | D16: 39705 | E16: RB2 Export/DLC | F16: Export Has Expired, but re-released as a Single
B17: Hollywood Nights | C17: Bob Seger & The Silver Bullet Band
B18: Livin' on a Prayer | C18: Bon Jovi | D18: 39705 | E18: RB2 Export/DLC | F18: Export Has Expired but re-released as part of "Bon Jovi's Greatest Hit" Album
B19: Scream Aim Fire | C19: Bullet for My Valentine | D19: 41058 | E19: DLC | F19: Part of "Bullet For My Valentine Pack 01"
B20: Shiver | C20: Coldplay | D20: 44049 | E20: DLC | F20: Part of "Coldplay Parachutes to Everyday Life" Pack
B21: Up Around the Bend | C21: Creedence Clearwater Revival | D21: 40365 | E21: DLC | F21: Part of "Creedence Clearwater Revival Pack 01"
B22: Love Removal Machine | C22: The Cult
B23: Feel the Pain | C23: Dinosaur Jr. | D23: 39705 | E23: RB2 Export | F23: Export Has Expired
B24: Love Me Two Times | C24: The Doors | D24: 40477 | E24: DLC | F24: Part of "The Doors Greatest Hits" Album
B25: Pull Me Under | C25: Dream Theater | D25: 42894 | E25: DLC | F25: DLC Single
B26: Hotel California | C26: Eagles
B27: Aggro | C27: The Enemy
B28: Hey Man, Nice Shot | C28: Filter | D28: 40477 | E28: RB3 Export | F28: Export Has Expired | I28: Guitar Hero: World Tour
B29: Go Your Own Way | C29: Fleetwood Mac | D29: 39705 | E29: RB2 Export/DLC | F29: Export Has Expired, but re-released as a Single | I29: 39749
B30: Everlong | C30: Foo Fighters | D30: 39705 | E30: RB2 Export/DLC | F30: Export Has Expired, but re-released as a DLC single and part of "Rock Band Hits Pack"
B31: American Woman | C31: The Guess Who | D31: 39705 | E31: RB2 Export | F31: Export Has Expired
B32: You're Gonna Say Yeah! | C32: HushPuppies | D32: 43727 | E32: DLC | F32: DLC Single and Temporarily Part of "Rivals Season 13 Pass"
B33: Obstacle 1 | C33: Interpol
B34: Mountain Song | C34: Jane's Addiction | D34: 39705 | E34: RB2 Export | F34: Export Has Expired
B35: Purple Haze | C35: The Jimi Hendrix Experience | D35: 40463 | E35: DLC | F35: Part of "Are You Experienced?" Album
B36: The Wind Cries Mary | C36: The Jimi Hendrix Experience | D36: 40463 | E36: DLC | F36: Part of "Are You Experienced?" Album
B37: The Middle | C37: Jimmy Eat World | D37: 39705 | E37: RB2 Export/DLC | F37: Export Has Expired but has been re-released as a DLC Single
B38: Satch Boogie | C38: Joe Satriani | D38: 40099 | E38: DLC | F38: DLC Single
B39: VinterNoll2 | C39: Kent
B40: Freak on a Leash | C40: Korn | D40: 40925 | E40: DLC | F40: DLC Single
B41: Our Truth | C41: Lacuna Coil | D41: 39705 | E41: RB2 Export | F41: Export Has Expired
B42: Are You Gonna Go My Way | C42: Lenny Kravitz | D42: 39826 | E42: DLC | F42: Part of "Lenny Kravitz Pack 01"
B43: What I've Done | C43: Linkin Park | D43: 40554 | E43: DLC | F43: Part of "Linkin Park Pack 01"
B44: Prisoner of Society | C44: The Living End
B45: La Bamba | C45: Los Lobos | D45: 43573 | E45: DLC | F45: DLC Single
B46: Rooftops (A Liberation Broadcast) | C46: Lostprophets | D46: 40120 | E46: LEGO Export | F46: Export Has Expired
B47: Sweet Home Alabama (Live) | C47: Lynyrd Skynyrd | D47: 40512 | E47: DLC | F47: Part of "Lynyrd Skyryrd Pack 01"
B48: Kick Out the Jams | C48: MC5's Wayne Kramer
B49: L'Via L'Viaquez | C49: The Mars Volta
B50: Trapped Under Ice | C50: Metallica
B51: Beat It | C51: Michael Jackson
B52: Float On | C52: Modest Mouse | D52: 39705 | E52: RB2 Export | F52: Export Has Expired
B53: Overkill | C53: Motörhead
B54: Assassin | C54: Muse
B55: Nuvole E Lenzuola | C55: Negramaro
B56: About a Girl (Unplugged) | C56: Nirvana | D56: 40120 | E56: DLC | F56: RB has Studio Version in the "Nirvana Bleach Pack"
B57: Spiderwebs | C57: No Doubt | D57: 39791 | E57: DLC | F57: Part of "Tragic Kingdom" Album and The Single: "1993 to 2003" Album
B58: Soul Doubt | C58: NOFX
B59: Some Might Say | C59: Oasis
B60: Crazy Train | C60: Ozzy Osbourne | D60: 40477 | E60: RB3 Export | F60: Export Has Expired
B61: Mr. Crowley | C61: Ozzy Osbourne | D61: 40694 | E61: DLC | F61: Part of "Ozzy 8-Pack"
B62: Misery Business | C62: Paramore | D62: 40477 | E62: RB3 Export | F62: Export Has Expired but has re-released as a single
B63: Heartbreaker | C63: Pat Benatar | D63: 39903 | E63: DLC | F63: DLC Single
B64: The One I Love | C64: R.E.M. | D64: 42283 | E64: RB4 | F64: RB4 On-Disc
B65: Escuela de Calor | C65: Radio Futura
B66: Re-Education (Through Labor) | C66: Rise Against | D66: 40015 | E66: DLC | F66: Part of "Rise Against Pack 01"
B67: Pretty Vacant | C67: Sex Pistols
B68: Lazy Eye | C68: Silversun Pickups | D68: 39705 | E68: RB2 Export | F68: Export Has Expired
B69: Today | C69: The Smashing Pumpkins | D69: 39705 | E69: RB2 Export | F69: Export Has Expired
B70: Do It Again | C70: Steely Dan
B71: The Joker | C71: Steve Miller Band | D71: 39833 | E71: DLC | F71: Part of "Steve Miller Band Pack 01" and "Classic Rock Track Pack"
B72: Demolition Man | C72: Sting
B73: Love Spreads | C73: The Stone Roses | D73: 39714 | E73: DLC | F73: DLC Single and part of "Classic Rock Track Pack"
B74: Toy Boy | C74: Stuck in the Sound
B75: Santeria | C75: Sublime | D75: 41212 | E75: DLC | F75: Part of "Sublime Pack 01" and "Rock Band Hits Pack"
B76: Eye of the Tiger | C76: Survivor | D76: 39705 | E76: RB2 Export/DLC | F76: Export Has Expired but has re-released as a single
B77: B.Y.O.B. | C77: System of a Down | D77: 39665 | E77: DLC | F77: Delisted
B78: Stranglehold | C78: Ted Nugent | D78: 42978 | E78: DLC | F78: DLC Single and Temporarily Part of "Rivals Season 2 Pass"
B79: Monsoon | C79: Tokio Hotel | D79: 39588 | E79: DLC | F79: Delisted
B80: Parabola | C80: Tool
B81: Schism | C81: Tool
B82: Vicarious | C82: Tool
B83: Antisocial | C83: Trust
B84: Hot for Teacher | C84: Van Halen | D84: 42332 | E84: DLC | F84: Part of "Van Halen Pack 01" and part of "Guitar Glory Pack"
B85: On the Road Again | C85: Willie Nelson | D85: 40211 | E85: DLC | F85: Part of "Going Country Pack 03" and "Country Tack Pack"
B86: Band on the Run | C86: Wings | D86: 40185 | E86: DLC | F86: Part of "Celebrating Band on the Run"
B89: Songs Released | C89: =COUNT(D:D) -> 54
B90: Total Songs | C90: 84
B91: Percent Complete | C91: =IFERROR(__xludf.DUMMYFUNCTION("TO_PERCENT(C89/C90)"),0.6428571428571429) -> 0.64285714

Sheet GH 5
B2: Song | C2: Artist | D2: Release Date | E2: Source | F2: Notes
B3: Kryptonite | C3: 3 Doors Down | D3: 40064 | E3: DLC | F3: DLC Single and part of "Rock Band Hits Pack"
B4: Judith | C4: A Perfect Circle
B5: Medicate | C5: AFI | D5: 40134 | E5: DLC | F5: Part of "AFI Pack 01"
B6: Brianstorm | C6: Arctic Monkeys
B7: You and Me | C7: Attack! Attack!
B8: Cigarettes, Wedding Bands | C8: Band of Horses
B9: Gratitude | C9: Beastie Boys
B10: Gamma Ray | C10: Beck
B11: Dancing with Myself | C11: Billy Idol | D11: 42409 | E11: DLC | F11: DLC Single of Gen X Version
B12: Lonely Is the Night | C12: Billy Squier | D12: 43125 | E12: DLC | F12: DLC Single, and temporarily part of "Season 4 Spotlight Pass Plus" and part of "Guitar Glory Pack"
B13: The Rock Show | C13: Blink-182 | D13: 40022 | E13: DLC | F13: Part of "blink-182 Pack 01"
B14: Song 2 | C14: Blur | D14: 40120 | E14: LEGO Export/DLC | F14: Export Has Expired but Re-Released as a DLC Single
B15: All Along the Watchtower | C15: Bob Dylan | F15: RB has Hendrix Cover
B16: You Give Love a Bad Name | C16: Bon Jovi | D16: 40120 | E16: LEGO Export/DLC | F16: Export Has Expired but re-released as part of "Bon Jovi's Greatest Hit" Album
B17: Sowing Season (Yeah) | C17: Brand New
B18: Six Days a Week | C18: The Bronx
B19: Comedown | C19: Bush | D19: 40946 | E19: DLC | F19: Part of "Bush Pack 01"
B20: Done with Everything, Die for Nothing | C20: Children of Bodom
B21: In My Place | C21: Coldplay
B22: Demon(s) | C22: Darkest Hour
B23: Blue Day | C23: Darker My Love
B24: Fame | C24: David Bowie | D24: 40568 | E24: DLC | F24: Part of "David Bowie Pack 02"
B25: Woman From Tokyo ('99 Remix) | C25: Deep Purple
B26: Younk Funk | C26: The Derek Trucks Band
B27: Sultans of Swing | C27: Dire Straits
B28: Send a Little Love Token | C28: The Duke Spirit | I28: Guitar Hero 5
B29: Hungry Like the Wolf | C29: Duran Duran | D29: 39705 | E29: RB2 Export/DLC | F29: Export Has Expired but re-released as a DLC Single | I29: 40057
B30: Wannabe in L.A. | C30: Eagles of Death Metal
B31: L.A. | C31: Elliott Smith
B32: Saturday Night's Alright for Fighting | C32: Elton John | D32: 40477 | E32: RB3 Export | F32: Export Has Expired
B33: Disconnected | C33: Face to Face
B34: Only Happy When It Rains | C34: Garbage
B35: Feel Good Inc. | C35: Gorillaz | D35: 40036 | E35: DLC | F35: Part of "Gorillaz Pack 01"
B36: Streamline Woman | C36: Gov't Mule
B37: We're an American Band | C37: Grand Funk Railroad | D37: 40638 | E37: DLC | F37: DLC Single
B38: Lust for Life (Live) | C38: Iggy Pop | D38: 42312 | E38: DLC | F38: Original Version as DLC Single
B39: 2 Minutes to Midnight | C39: Iron Maiden | D39: 39973 | E39: DLC | F39: Part of "Iron Maiden Pack 01"
B40: Scatterbrain (Live) | C40: Jeff Beck
B41: Bleed American | C41: Jimmy Eat World | D41: 40470 | E41: DLC | F41: Part of "Jimmy Eat World Pack 02"
B42: Hurts So Good | C42: John Mellencamp
B43: Ring of Fire | C43: Johnny Cash | D43: 40575 | E43: DLC | F43: Part of Country Tack Pack 2, "Country Mega Pack" and "Going Country Pack 6"
B44: Never Miss a Beat | C44: Kaiser Chiefs
B45: All The Pretty Faces | C45: The Killers
B46: 21st Century Schizoid Man | C46: King Crimson
B47: Sex on Fire | C47: Kings of Leon | D47: 40015 | E47: DLC | F47: Part of "Kings of Leon Pack 01"
B48: Shout It Out Loud | C48: KISS
B49: Mirror People | C49: Love and Rockets
B50: Sweating Bullets | C50: Megadeth
B51: Looks That Kill | C51: Mötley Crüe
B52: Plug In Baby | C52: Muse
B53: One Big Holiday | C53: My Morning Jacket | D53: 42283 | E53: DLC | F53: DLC Single
B54: Lithium (Live) | C54: Nirvana | D54: 40148 | E54: DLC | F54: Part of "Nirvana Pack 02"
B55: Smells Like Teen Spirit | C55: Nirvana | D55: 40148 | E55: DLC | F55: Part of "Nirvana Pack 02"
B56: Ex-Girlfriend | C56: No Doubt | D56: 39791 | E56: DLC | F56: Part of "1993-2003: The Singles" Album
B57: Do You Feel Like We Do? (Live) | C57: Peter Frampton | D57: 40682 | E57: DLC | F57: DLC Single
B58: So Lonely | C58: The Police | D58: 40607 | E58: DLC | F58: DLC Single
B59: Bring the Noise 20XX | C59: Public Enemy featuring Zakk Wylde | D59: 44772 | E59: DLC | F59: Remix With Anthrax available as DLC Single and Temporarily Part of "Rivals Season 27 Pass"
B60: Under Pressure | C60: Queen and David Bowie | D60: 40106 | E60: DLC | F60: Part of "Queen Pack 01" and "Queen RB3 Enhanced Pack"
B61: Make It wit Chu | C61: Queens of the Stone Age
B62: Steady, As She Goes | C62: The Raconteurs | D62: 40092 | E62: DLC | F62: Part of "Raconteurs Pack 01"
B63: Du Hast | C63: Rammstein | D63: 40477 | E63: RB3 Export | F63: Export Has Expired
B64: Sympathy for the Devil | C64: The Rolling Stones
B65: Sneak Out | C65: Rose Hill Drive
B66: The Spirit of Radio (Live) | C66: Rush | D66: 40890 | E66: DLC | F66: Part of "Rush Pack 01"
B67: No One to Depend On (Live) | C67: Santana
B68: They Say | C68: Scars on Broadway | D68: 39658 | E68: DLC | F68: DELISTED
B69: Nearly Lost You | C69: Screaming Trees | D69: 39728 | E69: DLC | F69: DLC Single
B70: Bullet with Butterfly Wings | C70: The Smashing Pumpkins
B71: Incinerate | C71: Sonic Youth
B72: In the Meantime | C72: Spacehog | D72: 40477 | E72: RB3 Export | F72: Export Has Expired
B73: Superstition | C73: Stevie Wonder | D73: 40862 | E73: DLC | F73: Part of "Stevie Wonder Pack 01"
B74: What I Got | C74: Sublime | D74: 41212 | E74: DLC | F74: Part of "Sublime Pack 01"
B75: Seven | C75: Sunny Day Real Estate | D75: 43566 | E75: DLC | F75: DLC Single
B76: Maiden, Mother & Crone | C76: The Sword
B77: 20th Century Boy | C77: T. Rex | D77: 40477 | E77: RB3 Export | F77: Export Has Expired
B78: Jailbreak | C78: Thin Lizzy | D78: 39847 | E78: DLC | F78: Live Version part of the "Thin Lizzy Pack 01"
B79: Deadbolt | C79: Thrice
B80: Runnin' Down a Dream | C80: Tom Petty | D80: 40050 | E80: DLC | F80: DLC Single
B81: American Girl | C81: Tom Petty and the Heartbreakers | D81: 40141 | E81: DLC | F81: Live Version Part of "Tom Petty & the Heartbreakers Live Anthology Pack 01"
B82: Wolf Like Me | C82: TV on the Radio | D82: 39966 | E82: DLC | F82: Part of "Boonnaroo Pack 01"
B83: A-Punk | C83: Vampire Weekend | D83: 40120 | E83: LEGO Export | F83: Export Has Expired
B84: Why Bother? | C84: Weezer
B85: Blue Orchid | C85: The White Stripes
B86: Play That Funky Music | C86: Wild Cherry | D86: 43041 | E86: DLC | F86: Part of 'Solid '70's Pack 2"
B87: Back Round | C87: Wolfmother
B90: Songs Released | C90: =COUNT(D:D) -> 42
B91: Total Songs | C91: 85
B92: Percent Complete | C92: =IFERROR(__xludf.DUMMYFUNCTION("TO_PERCENT(C90/C91)"),0.49411764705882355) -> 0.49411765

Sheet GH Warriors of Rock
A1: d
B2: Song | C2: Artist | D2: Release Date | E2: Source | F2: Notes
B3: The Outsider | C3: A Perfect Circle
B4: Cryin' | C4: Aerosmith | D4: 42296 | E4: DLC | F4: Part of "Aerosmith's Hits Pack 02"
B5: Dancing Through Sunday | C5: AFI
B6: No More Mr. Nice Guy | C6: Alice Cooper | D6: 43874 | E6: DLC | F6: DLC Single and Temporarily Part of "Rivals Season 15 Pass"
B7: Ties That Bind | C7: Alter Bridge
B8: The Feel Good Drag | C8: Anberlin | D8: 40274 | E8: DLC | F8: DLC Single
B9: Indians | C9: Anthrax | D9: 40449 | E9: DLC | F9: DLC Single
B10: Nemesis | C10: Arch Enemy | D10: 43601 | E10: DLC | F10: DLC Single
B11: Ravenous | C11: Atreyu
B12: Bat Country | C12: Avenged Sevenfold | D12: 40057 | E12: DLC | F12: DLC Single
B13: Re-Ignition (Live) | C13: Bad Brains
B14: I Know What I Am | C14: Band of Skulls | D14: 44098 | E14: DLC | F14: DLC Single and Temporarily Part of "Rivals Season 18 Season Pass"
B15: Children of the Grave | C15: Black Sabbath
B16: Tones of Home | C16: Blind Melon
B17: Burnin' for You | C17: Blue Öyster Cult | D17: 43006 | E17: DLC | F17: DLC Single and Temporarily Part of "Rivals Season 2 Pass"
B18: Machinehead | C18: Bush | D18: 40946 | E18: DLC | F18: Part of "Bush Pack 01"
B19: What Do I Get? | C19: Buzzcocks
B20: If You Want Peace... Prepare for War | C20: Children of Bodom
B21: Fortunate Son | C21: Creedence Clearwater Revival | D21: 40365 | E21: DLC | F21: Part of "Creedence Clearwater Revival Pack 01" and "Rock Band Hits Pack 02" and a cover as a Single
B22: Fascination Street | C22: The Cure
B23: Burn | C23: Deep Purple
B24: Pour Some Sugar on Me (Live) | C24: Def Leppard | D24: 40764 | E24: DLC | F24: Part of "Def Leppard Pack 01"
B25: Bloodlines | C25: Dethklok
B26: Setting Fire to Sleeping Giants | C26: The Dillinger Escape Plan
B27: Money for Nothing | C27: Dire Straits
B28: Fury of the Storm | C28: DragonForce
B29: Bodies | C29: Drowning Pool | D29: 43244 | E29: DLC | F29: DLC Single
B30: Free Ride | C30: The Edgar Winter Group | D30: 40925 | E30: DLC | F30: DLC Single
B31: Dance, Dance | C31: Fall Out Boy | D31: 40771 | E31: DLC | F31: Part of "Fall Out Boy Pack 01"
B32: Hard to See | C32: Five Finger Death Punch | D32: 43293 | E32: DLC | F32: DLC Single
B33: Again | C33: Flyleaf | D33: 40295 | E33: DLC | F33: DLC Single
B34: No Way Back | C34: Foo Fighters
B35: Feels Like the First Time | C35: Foreigner | D35: 39994 | E35: DLC | F35: Part of "Foreinger Pack 01"
B36: Move It On Over | C36: George Thorogood and the Destroyers
B37: Tick Tick Boom | C37: The Hives | D37: 40120 | E37: LEGO Export | F37: Export Has Expired
B38: Slow Hands | C38: Interpol
B39: Been Caught Stealing | C39: Jane's Addiction | D39: 40477 | E39: RB3 Export | F39: Export Has Expired
B40: Aqualung | C40: Jethro Tull | D40: 39705 | E40: RB2 Export | F40: Export Has Expired
B41: Black Widow of La Porte | C41: John 5 featuring Jim Root
B42: Love Gun | C42: Kiss
B43: Bleed It Out | C43: Linkin Park
B44: Call Me the Breeze (Live) | C44: Lynyrd Skynyrd
B45: Holy Wars... The Punishment Due | C45: Megadeth | D45: 40218 | E45: DLC | F45: Part of "Rust in Peace" Album
B46: Sudden Death | C46: Megadeth
B47: This Day We Fight! | C47: Megadeth
B48: Paranoid (Live) | C48: Metallica & Ozzy Osbourne
B49: Uprising | C49: Muse
B50: I'm Not Okay (I Promise) | C50: My Chemical Romance | D50: 40449 | E50: DLC | F50: DLC Single
B51: Rockin' in the Free World | C51: Neil Young
B52: How You Remind Me | C52: Nickelback | D52: 40869 | E52: DLC | F52: Part of "Nickelback Now & Then Pack 01"
B53: (You Can Still) Rock in America | C53: Night Ranger | D53: 40148 | E53: DLC | F53: DLC Single
B54: Wish | C54: Nine Inch Nails
B55: Self Esteem | C55: The Offspring | D55: 39728 | E55: DLC | F55: Part of "The Offspring Pack 01"
B56: Suffocated | C56: Orianthi
B57: I'm Broken | C57: Pantera | D57: 40682 | E57: DLC | F57: Part of "Pantera Pack 01"
B58: Lasso | C58: Phoenix | D58: 40477 | E58: RB3 Export | F58: Export Has Expired
B59: Unskinny Bop | C59: Poison | D59: 40722 | E59: DLC | F59: Part of "Poison Pack 01"
B60: Bohemian Rhapsody | C60: Queen | D60: 40477 | E60: RB3 Export | F60: Export Has Expired
B61: Jet City Woman | C61: Queensrÿche
B62: Losing My Religion | C62: R.E.M. | D62: 39882 | E62: DLC | F62: DLC Single
B63: Waidmanns Heil | C63: Rammstein
B64: Theme from Spiderman | C64: Ramones
B65: Lunatic Fringe | C65: Red Rider
B66: Savior | C66: Rise Against | D66: 40015 | E66: DLC | F66: Part of "Rise Against Pack 01"
B67: Stray Cat Blues | C67: The Rolling Stones
B68: 2112 | C68: Rush | D68: 40908 | E68: DLC | F68: Only Available in "2112" Pack
B69: Cherry Bomb | C69: The Runaways | D69: 39406 | E69: DLC | F69: Cover Available as DLC Single
B70: It's Only Another Parsec... | C70: RX Bandits
B71: There's No Secrets This Year | C71: Silversun Pickups
B72: Ghost | C72: Slash featuring Ian Astbury
B73: Chemical Warfare | C73: Slayer
B74: Psychosocial | C74: Slipknot | D74: 40155 | E74: DLC | F74: Part of "Slipknot Pack 01"
B75: Deadfall | C75: Snot
B76: Black Rain | C76: Soundgarden
B77: Speeding (Vault Version) | C77: Steve Vai
B78: Interstate Love Song | C78: Stone Temple Pilots | D78: 39455 | E78: DLC | F78: DLC Single
B79: Calling | C79: Strung Out
B80: Renegade | C80: Styx | D80: 39924 | E80: DLC | F80: DELISTED
B81: Motivation | C81: Sum 41
B82: Modern Day Cowboy | C82: Tesla
B83: Scumbag Blues | C83: Them Crooked Vultures
B84: Graduate | C84: Third Eye Blind
B85: Listen to Her Heart | C85: Tom Petty and the Heartbreakers
B86: We're Not Gonna Take It | C86: Twisted Sister | D86: 42521 | E86: DLC | F86: DLC Single
B87: Get Free | C87: The Vines | D87: 40477 | E87: RB3 Export | F87: Export Has Expired
B88: Seven Nation Army | C88: The White Stripes | D88: 40246 | E88: DLC | F88: Part of "The White Stripes Pack 02"
B89: Sharp Dressed Man | C89: ZZ Top
B92: Songs Released | C92: =COUNT(D:D) -> 39
B93: Total Songs | C93: 87
B94: Percent Complete | C94: =IFERROR(__xludf.DUMMYFUNCTION("TO_PERCENT(C92/C93)"),0.4482758620689655) -> 0.44827586

Sheet Guitar Hero 456 DLC
B2: Song | C2: Artist | D2: Release Date | E2: Source | F2: Notes
B3: Lycanthrope | C3: =44 -> 44
B4: 2nd Sucks | C4: A Day to Remember | D4: 40843 | E4: RBN | F4: Not compatible with RB4
B5: All I Want | C5: A Day to Remember | D5: 43300 | E5: DLC | F5: DLC Single
B6: Downfall of Us All | C6: A Day to Remember | D6: 39987 | E6: DLC | F6: Part of "Warped Tour 2009 Pack 01"
B7: NJ Legion Iced Tea | C7: A Day to Remember
B8: Livin' on the Edge | C8: Aerosmith | D8: 42726 | E8: DLC | F8: Part of "Aerosmith Hits Pack 03"
B9: Love in an Elevator | C9: Aerosmith | D9: 42296 | E9: DLC | F9: Part of "Aerosmtih Hits Pack 02"
B10: Rag Doll | C10: Aerosmith | D10: 42726 | E10: DLC | F10: Part of "Aerosmith Hits Pack 03"
B11: Beautiful Thieves | C11: AFI | D11: 40134 | E11: DLC | F11: Part of "AFI Pack 01"
B12: Girl's Not Grey | C12: AFI | D12: 39705 | E12: RB2 Export | F12: Export Has Expired
B13: The Missing Frame | C13: AFI
B14: New Wave | C14: Against Me!
B15: Young Cardinals | C15: Alexisonfire
B16: Elected | C16: Alice Cooper
B17: I'm Eighteen | C17: Alice Cooper | D17: 39952 | E17: DLC | F17: Live Version part of "Alice Cooper Pack 01"
B18: Poison | C18: Alice Cooper | D18: 39952 | E18: DLC | F18: Part of "Alice Cooper Pack 01"
B19: School's Out | C19: Alice Cooper | D19: 39952 | E19: DLC | F19: Live Version part of "Alice Cooper Pack 01"
B20: Welcome to My Nightmare | C20: Alice Cooper
B21: Gives You Hell | C21: The All-American Rejects | D21: 40162 | E21: DLC | F21: DLC Single
B22: Damned If I Do Ya (Damned If I Don't) | C22: All Time Low
B23: Dear Maria, Count Me In | C23: All Time Low | D23: 44294 | E23: DLC | F23: DLC Single and Temporarily Part of "Rivals Season 21 Pass"
B24: Weightless | C24: All Time Low | D24: 40225 | E24: DLC | F24: DLC Single
B25: Face Down | C25: Alpha Rev
B26: Twilight of the Thunder God | C26: Amon Amarth | D26: 43069 | E26: DLC | F26: DLC Single and Temporarily Part of "Rivals Season 3 Pass"
B27: Anything | C27: An Endless Sporadic | D27: 41088 | E27: RBN | F27: Not compatible with RB4
B28: From the Blue/Point of No Return | C28: An Endless Sporadic | D28: 41081 | E28: RBN | F28: Not compatible with RB4
B29: The Triangular Race Through Space | C29: An Endless Sporadic | D29: 41152 | E29: RBN | F29: Not compatible with RB4
B30: Everything's Magic | C30: Angels & Airwaves
B31: Afterlife | C31: Avenged Sevenfold | D31: 39616 | E31: DLC | F31: DLC Single and Part of "Track Pack Vol.2"
B32: Almost Easy | C32: Avenged Sevenfold | D32: 39705 | E32: RB2 Export | F32: Export Has Expired
B33: Scream | C33: Avenged Sevenfold | D33: 40356 | E33: DLC | F33: Part of "Avenged Sevenfold Pack 01"
B34: The Silence Is Deafening | C34: Awaken
B35: Degenerated | C35: Backyard Babies
B36: 21st Century (Digital Boy) | C36: Bad Religion | D36: 39987 | E36: DLC | F36: Part of "Warped Tour 2009 Pack 01"
B37: Sorrow | C37: Bad Religion | D37: 39714 | E37: DLC | F37: DLC Single
B38: Dis-Moi | C38: BB Brunes | D38: 40533 | E38: DLC | F38: DLC Single
B39: Fly One Time | C39: Ben Harper and Relentless7
B40: Number with No Name | C40: Ben Harper and Relentless7
B41: Shimmer & Shine | C41: Ben Harper and Relentless7 | D41: 39966 | E41: DLC | F41: Part of "Bonnaroo Pack 01'
B42: Everybody Wants You | C42: Billy Squier | D42: 41191 | E42: DLC | F42: DLC Single
B43: The Stroke | C43: Billy Squier | D43: 41191 | E43: DLC | F43: DLC Single
B44: When She Comes to Me | C44: Billy Squier
B45: Black Sunday | C45: Black Label Society
B46: Crazy Horse | C46: Black Label Society
B47: Parade of the Dead | C47: Black Label Society
B48: After Forever | C48: Black Sabbath
B49: Into the Void | C49: Black Sabbath
B50: Sweet Leaf | C50: Black Sabbath | D50: 39420 | E50: DLC | F50: Cover part of "Black Sabbath Pack 01"
B51: No Rain | C51: Blind Melon | D51: 40043 | E51: DLC | F51: DLC Single
B52: Adam's Song | C52: Blink-182 | D52: 40183 | E52: DLC | F52: Part of "blink-182 Pack 02"
B53: All the Small Things | C53: Blink-182 | D53: 39462 | E53: DLC | F53: DLC Single
B54: First Date | C54: Blink-182 | D54: 40183 | E54: DLC | F54: Part of "blink-182 Pack 02"
B55: What's My Age Again? | C55: Blink-182 | D55: 40099 | E55: DLC | F55: DLC Single
B56: There's No Other Way | C56: Blur | D56: 40043 | E56: DLC | F56: DLC Single
B57: Get Out of Denver | C57: Bob Seger
B58: Her Strut | C58: Bob Seger & the Silver Bullet Band
B59: Old Time Rock and Roll | C59: Bob Seger & the Silver Bullet Band
B60: Rock and Roll Band | C60: Boston | D60: 39532 | E60: DLC | F60: Part of "Boston Pack 01" and "Classic Rock Track Pack" and "Guitar Glory Pack"
B61: Ticks | C61: Brad Paisley
B62: Sic Transit Gloria... Glory Fades | C62: Brand New
B63: Give Me a Sign | C63: Breaking Benjamin
B64: Sooner or Later | C64: Breaking Benjamin | D64: 40848 | E64: DLC | F64: Part of "Breaking Benjamin Pack 02"
B65: Until the End | C65: Breaking Benjamin | D65: 40848 | E65: DLC | F65: Part of "Breaking Benjamin Pack 02"
B66: Hillbilly Deluxe | C66: Brooks & Dunn | D66: 39798 | E66: DLC | F66: Part of "Country Track Pack 01" and "Going Country Pack 01"
B67: Born to Run | C67: Bruce Springsteen
B68: My Lucky Day | C68: Bruce Springsteen
B69: Lemon Frosting | C69: Bunny Knutson
B70: Low Day | C70: Capra
B71: Blooddrunk | C71: Children of Bodom
B72: Living Dead Beat | C72: Children of Bodom
B73: Was It Worth It | C73: Children of Bodom
B74: On Broken Glass | C74: Chimaira
B75: Look Good in Leather | C75: Cody ChesnuTT
B76: Bad Moon Rising | C76: Creedence Clearwater Revival | D76: 40365 | E76: DLC | F76: Part of "Creedence Clearwater Revival Pack 01"
B77: Commotion | C77: Creedence Clearwater Revival
B78: Proud Mary | C78: Creedence Clearwater Revival | D78: 40365 | E78: DLC | F78: Part of "Creedence Clearwater Revival Pack 01"
B79: Travelin' Band | C79: Creedence Clearwater Revival | D79: 40365 | E79: DLC | F79: Part of "Creedence Clearwater Revival Pack 01"
B80: We've Got a Situation Here | C80: The Damned Things
B81: Beyond the Life You Know | C81: Darkest Hour
B82: Doomsayer | C82: Darkest Hour
B83: Savor the Kill | C83: Darkest Hour
B84: You Really Like Me | C84: Davidicus
B85: Here We Go Again | C85: Demi Lovato
B86: Laser Cannon Deth Sentence | C86: Dethklok
B87: Dez Moines | C87: The Devil Wears Prada
B88: Johnny | C88: Di-rect
B89: Hier kommt Alex | C89: Die Toten Hosen | D89: 39588 | E89: DLC | F89: DELISTED
B90: Down With The Sickness | C90: Disturbed | D90: 39705 | E90: RB2 Export/DLC | F90: Export Has Expired but released as a DLC Single
B91: Indestructible | C91: Disturbed | D91: 39602 | E91: DLC | F91: Part of "Rock Band Track Pack Vol.2" and "Disturbed Pack 01"
B92: Stricken | C92: Disturbed | D92: 39945 | E92: DLC | F92: DLC Single
B93: The Infection | C93: Disturbed
B94: Love Holds It Down | C94: Dom Liberati
B95: I'm Shipping Up to Boston | C95: Dropkick Murphys | D95: 40043 | E95: DLC | F95: DLC Single
B96: Frail Grasp on the Big Picture | C96: Eagles
B97: Life in the Fast Lane | C97: Eagles
B98: One of These Nights | C98: Eagles
B99: Anything 'Cept the Truth | C99: Eagles of Death Metal
B100: Cherry Cola | C100: Eagles of Death Metal
B101: I Only Want You | C101: Eagles of Death Metal | D101: 40393 | E101: DLC | F101: DLC Single
...

Sheet GH Live
B2: Song | C2: Artist | D2: Release Date | E2: Source | F2: Notes
B3: Girls | C3: The 1975
B4: R U Mine? | C4: Arctic Monkeys | D4: 42017 | E4: DLC | F4: DLC Single
B5: Here's to Never Growing Up | C5: Avril Lavigne
B6: Victory Over the Sun | C6: Biffy Clyro
B7: Gold on the Ceiling | C7: The Black Keys | D7: 42936 | E7: DLC | F7: DLC Single
B8: The Rock Show | C8: Blink-182 | D8: 40022 | E8: DLC | F8: Part of "blink-182 Pack 01"
B9: Shadow Moses | C9: Bring Me the Horizon
B10: Lies | C10: Deap Vally
B11: Grounds for Divorce | C11: Elbow
B12: Berzerk | C12: Eminem
B13: My Songs Know What You Did in the Dark (Light Em Up) | C13: Fall Out Boy | D13: 42451 | E13: DLC | F13: Part of "Off The Charts Pack 03"
B14: 45 | C14: The Gaslight Anthem
B15: The Anthem | C15: Good Charlotte | D15: 40974 | E15: DLC | F15: DLC Single
B16: Nuclear Family | C16: Green Day
B17: Love Bites (So Do I) | C17: Halestorm
B18: Demons | C18: Imagine Dragons
B19: Lazaretto | C19: Jack White | D19: 42283 | E19: RB4 | F19: RB4 On-Disc
B20: Club Foot | C20: Kasabian | D20: 40127 | E20: DLC | F20: DLC Single
B21: Waking Up in Vegas | C21: Katy Perry | D21: 44644 | E21: DLC | F21: DLC Single and Temporarily Part of "Rivals Season 26 Pass"
B22: When You Were Young | C22: The Killers | D22: 39406 | E22: RB1 Export/DLC | F22: Export Has Expired but has been re-released as a DLC Single
B23: Wastelands | C23: Linkin Park
B24: Ho Hey | C24: The Lumineers
B25: I Will Wait | C25: Mumford & Sons | D25: 42817 | E25: DLC | F25: DLC Single and part of "Guitar Glory Pack"
B26: Everybody Talks | C26: Neon Trees | D26: 42451 | E26: DLC | F26: Part of "Off The Charts Pack 03"
B27: Bones Exposed | C27: Of Mice & Men
B28: Mountain Sound | C28: Of Monsters and Men | D28: 45043 | E28: DLC | F28: DLC Single and Temporarily Part of "Rivals Season 31 Pass"
B29: Counting Stars | C29: OneRepublic | D29: 42817 | E29: DLC | F29: DLC Single
B30: Now | C30: Paramore
B31: Mind Your Manners | C31: Pearl Jam
B32: King for a Day (ft. Kellin Quinn) | C32: Pierce the Veil | D32: 42283 | E32: DLC | F32: DLC Single
B33: Tie Your Mother Down | C33: Queen | D33: 40106 | E33: DLC | F33: Part of "Queen Pack 01"
B34: California King Bed | C34: Rihanna
B35: Tragedy + Time | C35: Rise Against
B36: Keep on Swinging | C36: Rival Sons
B37: Paint It Black | C37: The Rolling Stones
B38: Little Monster | C38: Royal Blood
B39: Bangarang (ft. Sirah) | C39: Skrillex
B40: Been Away Too Long | C40: Soundgarden
B41: The Kill | C41: Thirty Seconds to Mars | D41: 39441 | E41: DLC | F41: DLC Single
B42: Won't Get Fooled Again | C42: The Who | D42: 39406 | E42: RB1 Export/ DLC | F42: Export Has Expired, but was re-released as a Single
B43: Sundial | C43: Wolfmother | D43: 40113 | E43: DLC | F43: Part of "Wolfmother Pack 01"
B44: Lived a Lie | C44: You Me at Six
B47: Songs Released | C47: =COUNT(D:D) -> 18
B48: Total Songs | C48: 42
B49: Percent Complete | C49: =IFERROR(__xludf.DUMMYFUNCTION("TO_PERCENT(C47/C48)"),0.42857142857142855) -> 0.42857143

Sheet GH TV
B2: Song | C2: Artist | D2: Release Date | E2: Source | F2: Notes
B3: Chocolate | C3: The 1975
B4: Girls | C4: The 1975
B5: Love Me | C5: The 1975
B6: In the Dark | C6: 3 Doors Down
B7: Kryptonite | C7: 3 Doors Down | D7: 39699 | E7: DLC | F7: DLC Single and part of "Rock Band Hits Pack"
B8: Also Am I | C8: 36 Crazyfist
B9: She Looks So Perfect | C9: 5 Seconds of Summer | D9: 42451 | E9: DLC | F9: Part of "Off the Charts Pack 03"
B10: Right Back at It Again | C10: A Day to Remember
B11: Dog on a Leach | C11: Adelita's Way
B12: Girl's Not Grey | C12: AFI | D12: 39705 | E12: RB2 Export | F12: Export Has Expired
B13: Black Me Out | C13: Against Me!
B14: Back in the Game | C14: Airbourne
B15: Man in the Box | C15: Alice in Chains | D15: 39705 | E15: RB2 Export/DLC | F15: Export Has Expired, but re-released in "Alice in Chains Pack 03" and "Guitar Glory Pack"
B16: No Excuses | C16: Alice in Chains | D16: 40085 | E16: DLC | F16: Part of "Alice in Chains Pack 01"
B17: Stone | C17: Alice in Chains
B18: Them Bones | C18: Alice in Chains | D18: 43020 | E18: DLC | F18: Part of "Alice in Chains Pack 03"
B19: Movies | C19: Alien Ant Farm | D19: 40829 | E19: RBN | F19: Not compatible with RB4
B20: Move Along | C20: The All-American Rejects | D20: 39441 | E20: DLC | F20: DLC Single and part of "Rock Band Hits Pack 02"
B21: Merry Christmas, Kiss My Ass | C21: All Time Low
B22: Left Hand Free | C22: alt-J
B23: Addicted to Pain | C23: Alter Bridge
B24: Cry of Achilles | C24: Alter Bridge
B25: Drop Dead Cynical | C25: Amaranthe
B26: Here It Comes Again | C26: The Amazing Snakeheads
B27: Best Day of My Life | C27: American Authors
B28: Believer | C28: American Authors
B29: Flavor of the Weak | C29: American Hi-Fi | D29: 44504 | E29: DLC | F29: DLC Single and Temporarily Part of "Rivals Season 24 Pass"
B30: You Know I'm No Good | C30: Amy Winehouse
B31: Party Hard | C31: Andrew W.K. | D31: 41273 | E31: DLC | F31: DLC Single
B32: Your Rules | C32: Andrew W.K.
B33: A Heartbreak | C33: Angus & Julia Stone
B34: Got the Time | C34: Anthrax
B35: Brandenburg Gate (ft. Tim Armstrong) | C35: Anti-Flag
B36: My Apocalypse | C36: Arch Enemy
B37: War Enternal | C37: Arch Enemy
B38: Gravedigger | C38: Architects
B39: Burn Baby Burn | C39: Ash
B40: Greyhound | C40: Ashley Clark
B41: The Final Episode (Let's Change the Channel) | C41: Asking Alexandria | D41: 43679 | E41: DLC | F41: DLC Single
B42: So Others May Live | C42: Atreyu
B43: Cochise | C43: Audioslave
B44: Like a Stone | C44: Audioslave | D44: 42317 | E44: DLC | F44: DLC Single
B45: Identity | C45: August Burns Red
B46: Turn Up the Radio | C46: Autograph
B47: Buried Alive (Live) | C47: Avenged Sevenfold
B48: Nightmare (Live) | C48: Avenged Sevenfold | D48: 40386 | E48: DLC | F48: Original is available as part of the "Avenged Sevenfold Pack 01"
B49: Shepherd of Fire (Live) | C49: Avenged Sevenfold | D49: 42017 | E49: DLC | F49: Original is available as a DLC Single
B50: Another is Waiting | C50: The Avett Brothers
B51: Asleep at the Wheel | C51: Band of Skulls
B52: Don't Let Me Be Lonely | C52: The Band Perry
B53: I Have a Problem | C53: Beartooth
B54: The Lines | C54: Beartooth
B55: Violent Shiver | C55: Benjamin Booker | D55: 42283 | E55: RB4 | F55: On-Disc Song
B56: Black Chandelier | C56: Biffy Clyro
B57: Sounds Like Ballons | C57: Biffy Clyro
B58: Hey Girl | C58: Billy Currington
B59: Gold on the Ceiling | C59: The Black Keys | D59: 42936 | E59: DLC | F59: DLC Single
B60: Tighten Up | C60: The Black Keys | D60: 41142 | E60: DLC | F60: Part of "The Black Keys Pack 02"
B61: Glass Built Castles | C61: Black Peaks
B62: Me and Mary Jane | C62: Black Stone Cherry
B63: That Fire | C63: Black Tide
B64: Walking Dead Man | C64: Black Tide
B65: Fallen Angels | C65: Black Veil Brides
B66: Fallen Angels (Live) | C66: Black Veil Brides
B67: Goodbye Agony | C67: Black Veil Brides
B68: Heart of Fire | C68: Black Veil Brides
B69: Heart of Fire (Live) | C69: Black Veil Brides
B70: In The End | C70: Black Veil Brides
B71: In The End (Live) | C71: Black Veil Brides
B72: Rollercoasters | C72: Bleachers | D72: 44868 | E72: DLC | F72: DLC Single
B73: No Rain | C73: Blind Melon | D73: 40043 | E73: DLC | F73: DLC Single
B74: All the Small Things | C74: blink-182 | D74: 39462 | E74: DLC | F74: DLC Single
B75: Dammit | C75: blink-182 | D75: 39749 | E75: DLC | F75: DLC Single
B76: The Rock Show | C76: blink-182 | D76: 39291 | E76: DLC | F76: Part of "blink-182 Pack 01"
B77: Sometimes | C77: Blitz Kids
B78: Hanging on the Telephone | C78: Blondie | D78: 39581 | E78: DLC | F78: DLC Single
B79: Cut Me and I'll Bleed | C79: Blossoms
B80: Take Me Away | C80: Blue Öyster Cult
B81: Thunder on the Mountain | C81: Bob Dylan
B82: Because We Can | C82: Bon Jovi
B83: I'll Sleep When I'm Dead | C83: Bon Jovi
B84: Livin' on a Prayer | C84: Bon Jovi | D84: 39705 | E84: RB2 Export/DLC | F84: Export Has Expired but re-released as part of "Bon Jovi's Greatest Hit" Album
B85: You Give Love a Bad Name | C85: Bon Jovi | D85: 40120 | E85: LEGO Export/DLC | F85: Export Has Expired but re-released as part of "Bon Jovi's Greatest Hit" Album
B86: More Than a Feeling | C86: Boston | D86: 39532 | E86: DLC | F86: Part of "Boston Pack 01"
B87: Blinded | C87: The Bots
B88: Drown | C88: Bring Me the Horizon | D88: 43531 | E88: DLC | F88: Part of "Bring Me The Horizon Pack 01"
B89: Girlschool | C89: Britny Fox
B90: Leave It Alone | C90: Broken Bells
B91: The Lazy Song | C91: Bruno Mars
B92: Raising Hell | C92: Bullet for My Valentine
B93: Tears Don't Fall | C93: Bullet for My Valentine | D93: 41058 | E93: DLC | F93: Part of "Bullet For My Valentine Pack 01"
B94: Temper Temper | C94: Bullet for My Valentine
B95: Your Betrayal | C95: Bullet for My Valentine | D95: 41058 | E95: DLC | F95: Part of "Bullet For My Valentine Pack 01"
B96: Trying | C96: Bully
B97: Electric Love | C97: BØRNS | D97: 42339 | E97: DLC | F97: Part of "Off The Charts Pack 01" and part of "Rock Band Sampler Pack"
B98: Feel So Close | C98: Calvin Harris
B99: Before He Cheats | C99: Carrie Underwood | D99: 41086 | E99: DLC | F99: Part of "Carrie Underwood Pack 01"
B100: Good Girl | C100: Carrie Underwood | D100: 41086 | E100: DLC | F100: Part of "Carrie Underwood Pack 01"
B101: Something in the Water | C101: Carrie Underwood
...

Sheet GH Aerosmith
B2: Song | C2: Artist | D2: Release Date | E2: Source | F2: Notes
B3: Back in the Saddle | C3: Aerosmith | D3: 41303 | E3: DLC | F3: Part of "Aerosmith's Greatest Dimension Pack"
B4: Beyond Beautiful | C4: Aerosmith
B5: Bright Light Fright | C5: Aerosmith
B6: Combination | C6: Aerosmith
B7: Draw the Line | C7: Aerosmith
B8: Dream On | C8: Aerosmith | D8: 41303 | E8: DLC | F8: Live Version in "Aerosmith's Greatest Dimension Pack"
B9: Kings and Queens | C9: Aerosmith
B10: Let the Music Do the Talking | C10: Aerosmith
B11: Love in an Elevator | C11: Aerosmith | D11: 42296 | E11: DLC | F11: Part of "Aerosmtih Hits Pack 02"
B12: Livin' on the Edge | C12: Aerosmith | D12: 42726 | E12: DLC | F12: Part of "Aerosmtih Hits Pack 03"
B13: Make It | C13: Aerosmith
B14: Mama Kin | C14: Aerosmith
B15: Movin' Out | C15: Aerosmith
B16: No Surprize | C16: Aerosmith
B17: Nobody's Fault | C17: Aerosmith
B18: Pandora's Box | C18: Aerosmith
B19: Pink | C19: Aerosmith
B20: Rag Doll | C20: Aerosmith | D20: 42726 | E20: DLC | F20: Part of "Aerosmith Hits Pack 03"
B21: Rats in the Cellar | C21: Aerosmith | D21: 42286 | E21: DLC | F21: Part of "Aerosmith Hits Pack 02"
B22: Sweet Emotion | C22: Aerosmith | D22: 41303 | E22: DLC | F22: Part of "Aerosmith's Greatest Dimension Pack"
B23: Toys in the Attic | C23: Aerosmith | D23: 42283 | E23: RB4 | F23: RB4 On-Disc
B24: Train Kept A-Rollin' | C24: Aerosmith | D24: 39406 | E24: RB1 Export | F24: Cover Version in Expired RB1 Export
B25: Uncle Salty | C25: Aerosmith
B26: Walk This Way | C26: Aerosmith | D26: 41303 | E26: DLC | F26: Part of "Aerosmith's Greatest Dimension Pack"
B27: Walk This Way | C27: Aerosmith feat. Run-D.M.C.
B28: Hard to Handle* | C28: The Black Crowes | D28: 39448 | E28: DLC | F28: Cover Version Available as DLC Single
B29: Dream Police | C29: Cheap Trick | D29: 40792 | E29: DLC | F29: Part of "Cheap Trick Pack 01"
B30: Complete Control | C30: The Clash | D30: 39490 | E30: DLC | F30: Part of "(Arguably) Punk Pack 02"
B31: She Sells Sanctuary | C31: The Cult | D31: 39714 | E31: DLC | F31: DLC Single
B32: I Hate Myself for Loving You | C32: Joan Jett | D32: 42409 | E32: DLC | F32: DLC Single
B33: Mercy | C33: Joe Perry
B34: Shakin' My Cage | C34: Joe Perry
B35: Talk Talkin | C35: Joe Perry
B36: All Day and All of the Night | C36: The Kinks
B37: Always on the Run | C37: Lenny Kravitz and Slash
B38: All the Young Dudes | C38: Mott the Hoople
B39: Personality Crisis | C39: New York Dolls
B40: King of Rock | C40: Run-D.M.C. | D40: 40673 | E40: DLC | F40: DLC Single
B41: Sex Type Thing | C41: Stone Temple Pilots | D41: 39497 | E41: DLC | F41: DLC Single
B42: Cat Scratch Fever | C42: Ted Nugent
B45: Songs Released | C45: =COUNT(D:D) -> 17
B46: Total Songs | C46: 40
B47: Percent Complete | C47: =IFERROR(__xludf.DUMMYFUNCTION("TO_PERCENT(C45/C46)"),0.425) -> 0.425

Sheet GH Metallica
B2: Song | C2: Artist | D2: Release Date | E2: Source | F2: Notes
B3: No Excuses | C3: Alice in Chains | D3: 40085 | E3: DLC | F3: Part of "Alice in Chains Pack 01"
B4: Turn the Page (Live) | C4: Bob Seger and the Silver Bullet Band
B5: Albatross | C5: Corrosion of Conformity
B6: Am I Evil? | C6: Diamond Head
B7: Stacked Actors | C7: Foo Fighters | D7: 40673 | E7: DLC | F7: Part of "Foo Fighter Pack 04"
B8: Hell Bent for Leather | C8: Judas Priest
B9: Demon Cleaner | C9: Kyuss
B10: Tuesday's Gone | C10: Lynyrd Skynyrd | D10: 40512 | E10: DLC | F10: Part of "Lynyrd Skynyrd Part 01"
B11: Beautiful Mourning | C11: Machine Head
B12: Blood and Thunder | C12: Mastodon | D12: 40652 | E12: DLC | F12: DLC Single
B13: Evil | C13: Mercyful Fate
B14: All Nightmare Long | C14: Metallica
B15: Battery | C15: Metallica | D15: 39705 | E15: RB2 | F15: Never Exportable
B16: Broken, Beat & Scarred | C16: Metallica
B17: Creeping Death | C17: Metallica
B18: Cyanide | C18: Metallica
B19: Disposable Heroes | C19: Metallica
B20: Dyers Eve | C20: Metallica
B21: Enter Sandman | C21: Metallica | D21: 39406 | E21: RB1 | F21: Never Exportable
B22: Fade to Black | C22: Metallica
B23: Fight Fire With Fire | C23: Metallica
B24: For Whom the Bell Tolls | C24: Metallica
B25: Frantic | C25: Metallica
B26: Fuel | C26: Metallica
B27: Hit the Lights | C27: Metallica
B28: King Nothing | C28: Metallica
B29: Master of Puppets | C29: Metallica
B30: The Memory Remains | C30: Metallica
B31: Mercyful Fate | C31: Metallica
B32: My Apocalypse | C32: Metallica
B33: No Leaf Clover | C33: Metallica
... B45: Armed and Ready | C45: Michael Schenker Group
B46: Ace of Spades | C46: Motörhead | D46: 39705 | E46: RB2 Export/DLC | F46: Export Has Expired, but Re-Liscened as a Single
B47: Stone Cold Crazy | C47: Queen | D47: 40883 | E47: DLC | F47: Part of "Queen Extravaganza 02"
B48: Mother of Mercy | C48: Samhain
B49: War Ensemble | C49: Slayer
B50: Mommy's Little Monster (Live) | C50: Social Distortion
B51: War Inside My Head | C51: Suicidal Tendencies
B52: The Black River | C52: The Sword
B53: Toxicity | C53: System of a Down | D53: 39665 | E53: DLC | F53: Delisted
B54: The Boys Are Back in Town | C54: Thin Lizzy | D54: 39847 | E54: DLC | F54: Part of "Thin Lizzy Pack 01"
B57: Songs Released | C57: =COUNT(D:D) -> 10
B58: Total Songs | C58: 52
B59: Percent Complete | C59: =IFERROR(__xludf.DUMMYFUNCTION("TO_PERCENT(C57/C58)"),0.19230769230769232) -> 0.19230769

Sheet GH Van Halen
B2: Song | C2: Artist | D2: Release Date | E2: Source | F2: Notes
B3: Come to Life | C3: Alter Bridge
B4: White Wedding (Part 1) | C4: Billy Idol | D4: 39705 | E4: RB2 Export | F4: Export Has Expired
B5: First Date | C5: blink-182 | D5: 40183 | E5: DLC | F5: Part of "blink-182 Pack 02"
B6: Safe European Home | C6: The Clash
B7: Space Truckin' | C7: Deep Purple | D7: 39812 | E7: DLC | F7: DLC Single
B8: Best of You | C8: Foo Fighters | D8: 40120 | E8: DLC | F8: Part of Foo "Fighters Pack 03"
B9: Double Vision | C9: Foreigner
B10: Stacy's Mom | C10: Fountains of Wayne | D10: 44182 | E10: DLC | F10: DLC Single and Temporarily Part of "Rivals Season 19 Season Pass"
B11: Pain | C11: Jimmy Eat World | D11: 40470 | E11: DLC | F11: Part of "Jimmy Eat World Pack 02"
B12: Painkiller | C12: Judas Priest | D12: 39705 | E12: RB2 Export | F12: Export Has Expired
B13: The End of Heartache | C13: Killswitch Engage | D13: 41121 | E13: DLC | F13: Part of "Killswitch Engage Pack 01"
B14: Rock and Roll Is Dead | C14: Lenny Kravitz
B15: Pretty Fly (for a White Guy) | C15: The Offspring | D15: 39728 | E15: DLC | F15: Part "The Offspring Pack 01"
B16: I Want It All | C16: Queen | D16: 40106 | E16: DLC | F16: Part of "Queen Pack 01" and "Queen RB3 Enhanced Pack"
B17: Sick, Sick, Sick | C17: Queens of the Stone Age | D17: 39406 | E17: DLC | F17: Part of "Queens of Stone Age Pack 01"
B18: Master Exploder | C18: Tenacious D | D18: 39705 | E18: RB2 Export | F18: Export Has Expired
B19: Ain't Talkin' 'Bout Love | C19: Van Halen | D19: 42332 | E19: DLC | F19: Part of "Van Halen Hits Pack 01"
B20: And the Cradle Will Rock... | C20: Van Halen | D20: 42332 | E20: DLC | F20: Part of "Van Halen Hits Pack 01"
B21: Atomic Punk | C21: Van Halen
B22: Beautiful Girls | C22: Van Halen
B23: Cathedral | C23: Van Halen
B24: Dance the Night Away | C24: Van Halen | D24: 42332 | E24: DLC | F24: Part of "Van Halen Hits Pack 01"
B25: Eruption | C25: Van Halen
B26: Everybody Wants Some!! | C26: Van Halen
B27: Feel Your Love Tonight | C27: Van Halen
B28: Hang ‘Em High | C28: Van Halen
B29: Hear About It Later | C29: Van Halen
B30: Hot for Teacher | C30: Van Halen | D30: 42332 | E30: DLC | F30: Part of "Van Halen Pack 01" and part of "Guitar Glory Pack"
B31: Ice Cream Man | C31: Van Halen
B32: I'm the One | C32: Van Halen
B33: Intruder/(Oh) Pretty Woman | C33: Van Halen
B34: Jamie's Cryin' | C34: Van Halen
B35: Jump | C35: Van Halen
B36: Little Guitars | C36: Van Halen
B37: Loss of Control | C37: Van Halen
B38: Mean Street | C38: Van Halen
B39: Panama | C39: Van Halen | D39: 42283 | E39: RB4 | F39: On-Disc Song
B40: Romeo Delight | C40: Van Halen
B41: Runnin' with the Devil | C41: Van Halen | D41: 42332 | E41: DLC | F41: Part of "Van Halen Hits Pack 01"
B42: So This Is Love? | C42: Van Halen
B43: Somebody Get Me a Doctor | C43: Van Halen
B44: Spanish Fly | C44: Van Halen
B45: Unchained | C45: Van Halen | D45: 42332 | E45: DLC | F45: Part of "Van Halen Hits Pack 01"
B46: You Really Got Me | C46: Van Halen
B47: Semi-Charmed Life | C47: Third Eye Blind | D47: 43454 | E47: DLC | F47: DLC Single and Temporarily Part of "Rivals Season 9 Pass"
B48: Dope Nose | C48: Weezer | D48: 42486 | E48: DLC | F48: DLC Single
B49: The Takedown | C49: Yellowcard
B52: Songs Released | C52: =COUNT(D:D) -> 21
B53: Total Songs | C53: 47
B54: Percent Complete | C54: =IFERROR(__xludf.DUMMYFUNCTION("TO_PERCENT(C52/C53)"),0.44680851063829785) -> 0.44680851

Sheet Rocks the 80s
B2: Song | C2: Artist | D2: Release Date | E2: Source | F2: Notes
B3: Hold on Loosely* | C3: .38 Special | D3: 40512 | E3: DLC | F3: DLC Single
B4: Balls to the Wall* | C4: Accept
B5: Caught in a Mosh* | C5: Anthrax | D5: 40477 | E5: RB3 Export | F5: Export Has Expired
B6: Heat of the Moment* | C6: Asia | D6: 43013 | E6: DLC | F6: DLC Single and Temporarily Part of "Rivals Season 2 Pass"
B7: Lonely Is the Night | C7: Billy Squier | D7: 43125 | E7: DLC | F7: DLC Single, and temporarily part of "Season 4 Spotlight Pass Plus" and part of "Guitar Glory Pack"
B8: Police Truck* | C8: Dead Kennedys | D8: 39760 | E8: DLC | F8: Part of "Dead Kennedys Pack 01"
B9: Holy Diver* | C9: Dio | D9: 40435 | E9: DLC | F9: DLC Single
B10: Shakin'* | C10: Eddie Money
B11: Play with Me* | C11: Extreme
B12: Bathroom Wall* | C12: Faster Pussycat
B13: I Ran (So Far Away) | C13: A Flock of Seagulls | D13: 41191 | E13: DLC | F13: Single
B14: We Got The Beat | C14: The Go-Go's | D14: 39705 | E14: RB2 Export/DLC | F14: Export Has Expired, but re-released as a single
B15: Wrathchild* | C15: Iron Maiden
B16: Electric Eye | C16: Judas Priest | D16: 39560 | E16: DLC | F16: Part of "Screaming for Vengance" Album
B17: Ballroom Blitz* | C17: Krokus | F17: RB1 has Sweet Cover
B18: Because, It's Midnite | C18: Limozeen
B19: Only a Lad* | C19: Oingo Boingo
B20: Ain't Nothin' But a Good Time* | C20: Poison | D20: 40722 | E20: DLC | F20: Part of "Poison Pack 01"
B21: Synchronicity II* | C21: The Police | D21: 39406 | E21: DLC | F21: Part of "The Police Pack 01"
B22: (Bang Your Head) Metal Health* | C22: Quiet Riot | D22: 41150 | E22: Blitz | F22: Part of Rock Band Blitz or as DLC Single
B23: Round and Round* | C23: Ratt | D23: 39705 | E23: RB2 Export/DLC | F23: Export Has Expired but was re-released as a DLC Single and part of "Guitar Glory Pack"
B24: What I Like About You* | C24: The Romantics | D24: 42486 | E24: DLC | F24: DLC Single
B25: The Warrior | C25: Scandal | D25: 42283 | E25: RB4 | F25: On-Disc Song
B26: No One Like You* | C26: Scorpions | D26: 42283 | E26: RB4 | F26: On-Disc Song
B27: 18 and Life* | C27: Skid Row | D27: 43090 | E27: DLC | F27: DLC Single, and temporarily part of "Season 4 Spotlight Pass Plus"
B28: I Wanna Rock | C28: Twisted Sister | D28: 42768 | E28: DLC | F28: DLC Single
B29: Turning Japanese* | C29: The Vapors | D29: 40729 | E29: DLC | F29: DLC Single
B30: Radar Love* | C30: White Lion | F30: RB3 has Golden Earring cover
B31: Seventeen* | C31: Winger | D31: 42612 | E31: DLC | F31: DLC Single
B32: Los Angeles* | C32: X | D32: 40260 | E32: DLC | F32: Part of "X Pack 01"
B35: Songs Released | C35: =COUNT(D:D) -> 21
B36: Total Songs | C36: 30
B37: Percent Complete | C37: =IFERROR(__xludf.DUMMYFUNCTION("TO_PERCENT(C35/C36)"),0.7) -> 0.7

Sheet GH Smash Hits
B2: Song | C2: Artist | D2: Release Date | E2: Source | F2: Notes
B3: Bark at the Moon | C3: Ozzy Osbourne | D3: 40694 | E3: DLC | F3: Guitar Hero | G3: Available exclusively in the "Ozzy 8-Pack"
B4: Cowboys from Hell | C4: Pantera | D4: 42283 | E4: DLC | F4: Guitar Hero | G4: RB has "Live From Monsters in Moscow" Version as a Single and part of "Guitar Glory Pack"
B5: Godzilla | C5: Blue Öyster Cult | D5: 40204 | E5: DLC | F5: Guitar Hero | G5: DLC Single and part of "Guitar Glory Pack"
B6: Hey You | C6: The Exies | F6: Guitar Hero
B7: I Love Rock 'n Roll | C7: Joan Jett and the Blackhearts | D7: 40477 | E7: RB3 | F7: Guitar Hero | G7: Export Has Expired
B8: Killer Queen | C8: Queen | D8: 40106 | E8: DLC | F8: Guitar Hero | G8: Part of "Queen Pack 01" and "Queen RB3 Enhanced Pack"
B9: More Than a Feeling | C9: Boston | D9: 39532 | E9: DLC | F9: Guitar Hero | G9: Part of "Boston Pack 01"
B10: No One Knows | C10: Queens of the Stone Age | D10: 40477 | E10: RB3 | F10: Guitar Hero | G10: Export Has Expired
B11: Smoke on the Water | C11: Deep Purple | D11: 40477 | E11: RB3 | F11: Guitar Hero | G11: Export Has Expired
B12: Stellar | C12: Incubus | D12: 44616 | E12: DLC | F12: Guitar Hero | G12: DLC Single and Temporarily Part of "Rivals Season 25 Pass"
B13: Take It Off | C13: The Donnas | D13: 44630 | E13: DLC | F13: Guitar Hero | G13: DLC Single and Temporarily Part of "Rivals Season 25 Pass"
B14: Take Me Out | C14: Franz Ferdinand | D14: 39938 | E14: DLC | F14: Guitar Hero | G14: Part of "Franz Ferdinand Pack 01" and "Guitar Glory Pack"
B15: Thunder Kiss '65 | C15: White Zombie | D15: 40841 | E15: DLC | F15: Guitar Hero | G15: DLC Single
B16: Unsung | C16: Helmet | F16: Guitar Hero
B17: Beast and the Harlot | C17: Avenged Sevenfold | D17: 40477 | E17: RB3 Export/DLC | F17: Guitar Hero II | G17: Export Has Expired, but re-liscened as a Single
B18: Carry On Wayward Son | C18: Kansas | D18: 39705 | E18: RB2 Export | F18: Guitar Hero II | G18: Export Has Expired but Re-Released in the "Solid '70s Pack 01"
B19: Cherry Pie | C19: Warrant | D19: 42521 | E19: DLC | F19: Guitar Hero II | G19: DLC Single
B20: Free Bird | C20: Lynyrd Skynyrd | D20: 40477 | E20: RB3 Export/DLC | F20: Guitar Hero II | G20: Export Has Expired, but re-released as a Single
B21: Freya | C21: The Sword | F21: Guitar Hero II
B22: Heart-Shaped Box | C22: Nirvana | D22: 40806 | E22: DLC | F22: Guitar Hero II | G22: Part of "Celebrating Nirvana Pack"
B23: Killing in the Name | C23: Rage Against the Machine | D23: 41037 | E23: DLC | F23: Guitar Hero II | G23: Part of "Rage Against the Machine Pack 01"
B24: Laid to Rest | C24: Lamb of God | D24: 39777 | E24: DLC | F24: Guitar Hero II | G24: Part of "Metal Track Pack 01" and as a DLC Single
B25: Message in a Bottle | C25: The Police | D25: 39553 | E25: DLC | F25: Guitar Hero II | G25: Part of "The Police Tack Pack 01" and "Classic Rock Track Pack"
B26: Monkey Wrench | C26: Foo Fighters | D26: 39763 | E26: DLC | F26: Guitar Hero II | G26: Part of "The Colour and the Shape" Album
B27: Mother | C27: Danzig | F27: Guitar Hero II
B28: Psychobilly Freakout | C28: Reverend Horton Heat | F28: Guitar Hero II
B29: Shout at the Devil | C29: Mötley Crüe | F29: Guitar Hero II
B30: Stop! | C30: Jane's Addiction | D30: 42647 | E30: DLC | F30: Guitar Hero II | G30: DLC Single
B31: Them Bones | C31: Alice in Chains | D31: 43013 | E31: DLC | F31: Guitar Hero II | G31: DLC Single
B32: Trippin' on a Hole in a Paper Heart | C32: Stone Temple Pilots | D32: 40470 | E32: DLC | F32: Guitar Hero II | G32: Part of "Stone Temple Pilots Pack 01"
B33: Woman | C33: Wolfmother | D33: 40113 | E33: DLC | F33: Guitar Hero II | G33: Part of "Wolfmother Pack 01"
B34: YYZ | C34: Rush | D34: 39714 | E34: DLC | F34: Guitar Hero II | G34: Part of "Moving Pictures" Album
B35: The Trooper | C35: Iron Maiden | D35: 39973 | E35: DLC | F35: Guitar Hero II | G35: Part of "Iron Maiden Pack 01"
B36: Caught in a Mosh | C36: Anthrax | D36: 40477 | E36: RB3 Export | F36: Guitar Hero Encore: Rocks the 80s | G36: Export Has Expired
B37: Electric Eye | C37: Judas Priest | D37: 39560 | E37: DLC | F37: Guitar Hero Encore: Rocks the 80s | G37: Part of "Screaming for Vengance" Album
B38: I Wanna Rock | C38: Twisted Sister | D38: 42768 | E38: DLC | F38: Guitar Hero Encore: Rocks the 80s | G38: DLC Single
B39: Nothin' but a Good Time | C39: Poison | D39: 40722 | E39: DLC | F39: Guitar Hero Encore: Rocks the 80s | G39: Part of "Poison Pack 01"
B40: Play with Me | C40: Extreme | F40: Guitar Hero Encore: Rocks the 80s
B41: Round and Round | C41: Ratt | D41: 39705 | E41: RB2 Export | F41: Guitar Hero Encore: Rocks the 80s | G41: Export Has Expired but was re-released as a DLC Single and part of "Guitar Glory Pack"
B42: Barracuda | C42: Heart | D42: 40757 | E42: DLC | F42: Guitar Hero III: Legends of Rock | G42: DLC Single
B43: Cult of Personality | C43: Living Colour | D43: 41150 | E43: Blitz/DLC | F43: Guitar Hero III: Legends of Rock | G43: Part of Rock Band Blitz and as a DLC Single
B44: Hit Me with Your Best Shot | C44: Pat Benatar | D44: 39847 | E44: DLC | F44: Guitar Hero III: Legends of Rock | G44: Part of "Classic Rock Track Pack" and as a DLC Single
B45: Lay Down | C45: Priestess | F45: Guitar Hero III: Legends of Rock
B46: Miss Murder | C46: AFI | D46: 40066 | E46: DLC | F46: Guitar Hero III: Legends of Rock | G46: DLC Single
B47: Raining Blood | C47: Slayer | D47: 41009 | E47: DLC | F47: Guitar Hero III: Legends of Rock | G47: Part of "Slayer Pack 01"
B48: Rock and Roll All Nite | C48: Kiss | D48: 40659 | E48: DLC | F48: Guitar Hero III: Legends of Rock | G48: RB has live version as a DLC Single
B49: Through the Fire and Flames | C49: DragonForce | D49: 40631 | E49: DLC | F49: Guitar Hero III: Legends of Rock | G49: DLC Single and part of "Rock Band Hits Pack"
B50: Back in the Saddle | C50: Aerosmith | D50: 41303 | E50: DLC | F50: Guitar Hero: Aerosmith | G50: Part of "Aerosmith's Greatest Dimension Pack"
B53: Songs Released | C53: =COUNT(D:D) -> 40
B54: Total Songs | C54: 48
B55: Percent Complete | C55: =IFERROR(__xludf.DUMMYFUNCTION("TO_PERCENT(C53/C54)"),0.8333333333333334) -> 0.83333333

Sheet Band Hero
B2: Song | C2: Artist | D2: Release Date | E2: Source | F2: Notes
B3: When I'm Gone | C3: 3 Doors Down | D3: 40722 | E3: DLC | F3: Part of "3 Doors Down Pack 01"
B4: Gasoline | C4: The Airborne Toxic Event
B5: Dirty Little Secret | C5: The All-American Rejects | D5: 39441 | E5: DLC | F5: DLC Single
B6: Fascination | C6: Alphabeat | D6: 40225 | E6: DLC | F6: DLC Single
B7: Like Whoa | C7: Aly & AJ
B8: The Adventure | C8: Angels & Airwaves | D8: 41079 | E8: DLC | F8: DLC Single
B9: Steal My Kisses | C9: Ben Harper and the Innocent Criminals
B10: In a Big Country | C10: RB3 Export/DLC | D10: 40477 | E10: RB3 Export | F10: Export Has Expired, but re-released as a DLC single
B11: Believe | C11: The Bravery
B12: Kung Fu Fighting | C12: Carl Douglas | D12: 40120 | E12: LEGO Export | F12: Export Has Expired
B13: I Want You to Want Me (Live) | C13: Cheap Trick | D13: 40792 | E13: DLC | F13: Part of "Cheap Trick Pack 01" and "Guitar Glory Pack"
B14: Hang Me Up to Dry | C14: Cold War Kids
B15: Put Your Records On | C15: Corinne Bailey Rae
B16: Angels of the Silences | C16: Counting Crows
B17: Do You Really Want to Hurt Me | C17: Culture Club | D17: 40666 | E17: DLC | F17: DLC SIngle
B18: Hands Down | C18: Dashboard Confessional | D18: 39707 | E18: DLC | F18: Part of "Rock Band Live 2008 Tour Pack"
B19: Let's Dance | C19: David Bowie | D19: 40120 | E19: LEGO Export | F19: Export Has Expired
B20: Whip It | C20: Devo | D20: 40477 | E20: RB3 Export | F20: Export Has Expired
B21: American Pie | C21: Don McLean | D21: 41366 | E21: DLC | F21: DLC Single
B22: Warwick Avenue | C22: Duffy
B23: Rio | C23: Duran Duran | D23: 39679 | E23: DLC | F23: Part of "Rock Band Track Pack Vol.2" and as a Single
B24: Bring Me to Life | C24: Evanescence | D24: 39980 | E24: DLC | F24: Part of "Evanescence Pack 01"
B25: Santa Monica | C25: Everclear | D25: 40974 | E25: DLC | F25: DLC Single
B26: Sugar, We're Goin Down | C26: Fall Out Boy | D26: 40771 | E26: DLC | F26: Part of "Fall Out Boy Pack 01"
B27: Take a Picture | C27: Filter
B28: Paralyzer | C28: Finger Eleven | D28: 43405 | E28: DLC | F28: DLC Single
B29: Our Lips Are Sealed | C29: The Go-Go's | D29: 40141 | E29: DLC | F29: DLC SIngle
B30: So Yesterday | C30: Hilary Duff
B31: Lips of an Angel | C31: Hinder | D31: 42553 | E31: DLC | F31: DLC Single
B32: ABC | C32: The Jackson 5 | D32: 40064 | E32: DLC | F32: DLC Single
B33: Black Cat | C33: Janet Jackson
B34: Beautiful Soul | C34: Jesse McCartney
B35: Bad Reputation | C35: Joan Jett | D35: 39705 | E35: RB2 Export/DLC | F35: Export Has Expired but has been re-released as a DLC Single
B36: You Had Me | C36: Joss Stone
B37: Walking on Sunshine | C37: Katrina and the Waves | D37: 40120 | E37: LEGO Export | F37: Export Has Expired
B38: Naïve | C38: The Kooks | D38: 40120 | E38: LEGO Export | F38: Export Has Expired
B39: Black Horse and the Cherry Tree | C39: KT Tunstall
B40: Pictures of You | C40: The Last Goodnight
B41: Take What You Take | C41: Lily Allen
B42: She Will Be Loved | C42: Maroon 5
B43: I Heard It Through the Grapevine | C43: Marvin Gaye | F43: RB has CCR
B44: The Impression That I Get | C44: The Mighty Mighty Bosstones | D44: 42283 | E44: RB4 | F44: On-Disc Song
B45: Rock Star | C45: N.E.R.D.
B46: Turn Off the Light | C46: Nelly Furtado
B47: Don't Speak | C47: No Doubt | D47: 39791 | E47: DLC | F47: Part of "Tragic Kingdom" Album and The Singles: "1993 to 2003" Album
B48: Just a Girl | C48: No Doubt | D48: 39791 | E48: DLC | F48: Part of "Tragic Kingdom" Album and The Singles: "1993 to 2003" Album
B49: A Million Ways | C49: OK Go
B50: Lifeline | C50: Papa Roach | D50: 39889 | E50: DLC | F50: DLC Single
B51: Back Again | C51: Parachute
B52: Love Is a Battlefield | C52: Pat Benatar | D52: 40596 | E52: DLC | F52: Part of "Pat Benatar Pack 01"
B53: Every Rose Has Its Thorn | C53: Poison | D53: 40953 | E53: DLC | F53: Part of "Gold Star My Heart Pack"
B54: Kids | C54: Robbie Williams and Kylie Minogue
B55: Oh, Pretty Woman | C55: Roy Orbison | D55: 39819 | E55: DLC | F55: Part of "Roy Orbison Pack 01"
B56: L.E.S. Artistes | C56: Santigold
B57: Take Back the City | C57: Snow Patrol | D57: 39812 | E57: DLC | F57: DLC Single
B58: Wannabe | C58: Spice Girls
B59: Mr. Roboto | C59: Styx
B60: Love Story (Pop Mix) | C60: Taylor Swift
B61: Picture to Burn | C61: Taylor Swift
B62: You Belong with Me | C62: Taylor Swift
B63: Honky Tonk Women | C63: The Rolling Stones
B64: If You Could Only See | C64: Tonic | D64: 42598 | E64: DLC | F64: DLC Single
B65: Happy Together | C65: The Turtles
B66: Y.M.C.A. | C66: Village People
B67: Ocean Avenue | C67: Yellowcard | D67: 40169 | E67: DLC | F67: DLC Single
B70: Songs Released | C70: =COUNT(D:D) -> 33
B71: Total Songs | C71: 65
B72: Percent Complete | C72: =IFERROR(__xludf.DUMMYFUNCTION("TO_PERCENT(C70/C71)"),0.5076923076923077) -> 0.50769231

Sheet Guitar Hero On Tour
B2: Artist | C2: Song | D2: Release Date | E2: Source | F2: Notes
B3: Monster | C3: Beatsteaks
B4: All the Small Things | C4: blink-182 | D4: 39462 | E4: DLC | F4: DLC Single
B5: Helicopter | C5: Bloc Party
B6: What I Want | C6: Daughtry ft. Slash
B7: China Grove | C7: The Doobie Brothers | D7: 40477 | E7: RB3 Export | F7: Export Has Expired
B8: Rock the Night | C8: Europe
B9: I Am Not Your Gameboy | C9: Freezepop
B10: Avalancha | C10: Héroes del Silencio
B11: Anna Molly | C11: Incubus
B12: Are You Gonna Be My Girl | C12: Jet | D12: 39406 | E12: RB1 Export | F12: Export Has Expired
B13: Rock and Roll All Nite | C13: KISS | D13: 40659 | E13: DLC | F13: Live Version available as a Single
B14: Heaven | C14: Los Lonely Boys
B15: I Know a Little | C15: Lynyrd Skynyrd
B16: Ça me vexe | C16: Mademoiselle K
B17: This Love | C17: Maroon 5 | D17: 40715 | E17: DLC | F17: Part of "Maroon 5 Pack 01"
B18: Breed | C18: Nirvana | D18: 39744 | E18: DLC | F18: Part of "Nirvana Pack 01"
B19: Spiderwebs | C19: No Doubt | D19: 39793 | E19: DLC | F19: Part of "Tragic Kingdom" Album and The Single: "1993 to 2003" Album
B20: Do What You Want | C20: OK Go
B21: I Don't Wanna Stop | C21: Ozzy Osbourne | D21: 40344 | E21: DLC | F21: Part of "Ozzy Osbourne Pack 01"
B22: Hit Me With Your Best Shot | C22: Pat Benatar | D22: 39849 | E22: DLC | F22: Part of "Classic Rock Track Pack" and as a DLC Single
B23: Knock Me Down | C23: Red Hot Chili Peppers
B24: Jessie's Girl | C24: Rick Springfield | D24: 41149 | E24: Blitz/DLC | F24: Part of "Rock Band Blitz" and "Rick Springfield Pack 01"
B25: Black Magic Woman | C25: Santana | D25: 40631 | E25: DLC | F25: Only "Black Magic Woman" is part of "Days of Peace Pack"
B26: Youth Gone Wild | C26: Skid Row
B27: All Star | C27: Smash Mouth | D27: 40281 | E27: DLC | F27: DLC Single and part of "Rock Band Hits Pack"
B28: Jet Airliner | C28: Steve Miller Band
B29: Pride and Joy | C29: Stevie Ray Vaughan | D29: 39877 | E29: DLC | F29: Part of "Texas Flood" Album
B30: Stray Cat Strut | C30: Stray Cats | D30: 40227 | E30: DLC | F30: Brian Stezer version available as a DLC Single
B31: Monsoon | C31: Tokio Hotel | D31: 39590 | E31: DLC | F31: DELISTED
B32: We're Not Gonna Take It | C32: Twisted Sister | D32: 42521 | E32: DLC | F32: DLC Single
B33: La Grange | C33: ZZ Top
B36: Songs Released | C36: =COUNT(D:D) -> 16
B37: Total Songs | C37: 31
B38: Percent Complete | C38: =IFERROR(__xludf.DUMMYFUNCTION("TO_PERCENT(C36/C37)"),0.5161290322580645) -> 0.51612903

Sheet Guitar Hero On Tour Decades
B2: Artist | C2: Song | D2: Release Date | E2: Source | F2: Notes
B3: Smooth Criminal | C3: Alien Ant Farm | D3: 39940 | E3: DLC | F3: DELISTED
B4: Dirty Little Secret | C4: The All-American Rejects | D4: 39441 | E4: DLC | F4: DLC Single
B5: No Rain | C5: Blind Melon | D5: 40043 | E5: DLC | F5: DLC Single
B6: One Way or Another | C6: Blondie | D6: 39705 | E6: RB2 Export/DLC | F6: Export Has Expired, But Re-released as a DLC Single
B7: You Give Love a Bad Name | C7: Bon Jovi | D7: 40120 | E7: LEGO Export/DLC | F7: Export Has Expired but re-released as part of "Bon Jovi's Greatest Hit" Album
B8: Rock and Roll Band | C8: Boston | D8: 39534 | E8: DLC | F8: Part of "Boston Pack 01" and "Classic Rock Track Pack" and "Guitar Glory Pack"
B9: I Believe in a Thing Called Love | C9: The Darkness | D9: 40841 | E9: DLC | F9: DLC Single
B10: Free Ride | C10: The Edgar Winter Group | D10: 40925 | E10: DLC | F10: DLC Single
B11: The Take Over, The Breaks Over | C11: Fall Out Boy
B12: Diventerai una star | C12: Finley
B13: The Pretender | C13: Foo Fighters | D13: 40122 | E13: DLC | F13: Part of "Foo Fighters Pack 03"
B14: All Right Now | C14: Free | D14: 39730 | E14: DLC | F14: Part of "Classic Rock Track Pack" and as a Single
B15: You Can't Stop Me | C15: Guano Apes
B16: The Middle | C16: Jimmy Eat World | D16: 39705 | E16: RB2 Export/DLC | F16: Export Has Expired but has been re-released as a DLC Single
B17: Satch Boogie | C17: Joe Satriani | D17: 40101 | E17: DLC | F17: DLC Single
B18: Any Way You Want It | C18: Journey | D18: 39705 | E18: RB2 | F18: Never Exportable
B19: Are You Gonna Go My Way | C19: Lenny Kravitz | D19: 39828 | E19: DLC | F19: Part of "Lenny Kravitz Pack 01"
B20: One Step Closer | C20: Linkin Park | D20: 39705 | E20: RB2 Export/DLC | F20: Export Has Expired but has been re-released as a DLC Single
B21: La Bamba | C21: Los Lobos | D21: 43573 | E21: DLC | F21: DLC Single
B22: Sweet Home Alabama | C22: Lynyrd Skynyrd | D22: 40512 | E22: DLC | F22: Live Version Part of "Lynyrd Skynyrd Pack 01"
B23: Some Might Say | C23: Oasis
B24: Crushcrushcrush | C24: Paramore | D24: 39520 | E24: DLC | F24: DLC Single
B25: Estrella Polar | C25: Pereza
B26: Everything is Everything | C26: Phoenix
B27: We Are the Champions | C27: Queen | D27: 40120 | E27: LEGO Export/DLC | F27: Export Has Expired but was Re-Liscened for "Queen Extravaganza Pack 01"
B28: The One I Love | C28: R.E.M. | D28: 42283 | E28: RB4 | F28: On-Disc Song
B29: Can't Stop | C29: Red Hot Chili Peppers
B30: I Can't Drive 55 | C30: Sammy Hagar | D30: 44546 | E30: DLC | F30: DLC Single and Temporarily Part of "Rivals Season 24 Pass"
B31: Remedy | C31: Seether | D31: 43482 | E31: DLC | F31: DLC Single and Temporarily Part of "Rivals Season 9 Pass"
B32: Tarantula | C32: The Smashing Pumpkins
B33: Down | C33: Stone Temple Pilots
B34: Eye of the Tiger | C34: Survivor | D34: 39705 | E34: RB2 Export/DLC | F34: Export Has Expired but has been Re-released as a Single
B35: Ready, Set, Go! | C35: Tokio Hotel | D35: 39786 | E35: DLC | F35: DELISTED
B36: Volcano Girls | C36: Veruca Salt
B37: Buddy Holly | C37: Weezer | D37: 39434 | E37: DLC | F37: DLC Single
B40: Songs Released | C40: =COUNT(D:D) -> 25
B41: Total Songs | C41: 35
B42: Percent Complete | C42: =IFERROR(__xludf.DUMMYFUNCTION("TO_PERCENT(C40/C41)"),0.7142857142857143) -> 0.71428571

Sheet Guitar Hero On Tour Modern Hits
B2: Artist | C2: Song | D2: Release Date | E2: Source | F2: Notes
B3: Adrenaline | C3: 12 Stones
B4: Miss Murder | C4: AFI | D4: 40064 | E4: DLC | F4: DLC Single
B5: Call to Arms | C5: Angels and Airwaves
B6: Falling Down | C6: Atreyu
B7: When You're Gone | C7: Avril Lavigne
B8: Shockwave | C8: Black Tide | D8: 39520 | E8: DLC | F8: Part of "Metal Track Pack" and DLC Single
B9: Unconditional | C9: The Bravery
B10: Scream Aim Fire | C10: Bullet for My Valentine | D10: 41058 | E10: DLC | F10: Part of "Bullet for My Valentine Pack 01"
B11: Violet Hill | C11: Coldplay
B12: Bohemian Like You | C12: The Dandy Warhols | D12: 40247 | E12: RBN | F12: Never officially released but you can buy it, but it won't work for RB4
B13: Que no | C13: Deluxe
B14: What Do I Have to Do | C14: The Donnas
B15: Lassoo | C15: The Duke Spirit
B16: I Wanna Be Your Man | C16: Endeverafter | D16: 39790 | E16: 20 Free Songs | F16: DELISTED
B17: Sweet Sacrifice | C17: Evanescence
B18: This Ain't a Scene, It's an Arms Race | C18: Fall Out Boy | D18: 39576 | E18: DLC | F18: Part of "Track Pack Vol. 2" and "The Scene Pack 01"
B19: Paralyzer | C19: Finger Eleven | D19: 43405 | E19: DLC | F19: DLC Single
B20: All My Life | C20: Foo Fighters | D20: 40043 | E20: DLC | F20: Part of "Foo Fighters Pack 02"
B21: The Fallen | C21: Franz Ferdinand
B22: Chelsea Dagger | C22: The Fratellis | D22: 44539 | E22: DLC | F22: DLC Single and Temporarily Part of "Rivals Season 24 Pass"
B23: Ruby | C23: Kaiser Chiefs | D23: 40120 | E23: LEGO Export | F23: Export Has Expired
B24: On Call | C24: Kings of Leon
B25: Golden Skans | C25: Klaxons
B26: Always Where I Need to Be | C26: The Kooks
B27: Where Are We Runnin'? | C27: Lenny Kravitz
B28: Our Velocity | C28: Maxïmo Park
B29: Dashboard | C29: Modest Mouse
B30: Via Le Mani Dagli Occhi | C30: Negramaro
B31: Half-Truism | C31: The Offspring
B32: Do the Panic | C32: Phantom Planet
B33: Napoleon Says | C33: Phoenix
B34: The Bitter End | C34: Placebo
B35: In the Shadows | C35: The Rasmus
B36: 54, '74, '90, 2010 | C36: Sportfreunde Stiller
B37: Reptillia | C37: The Strokes | D37: 39406 | E37: RB1 Export | F37: Export Has Expired
B38: Still Waiting | C38: Sum 41 | D38: 40939 | E38: DLC | F38: DLC Single
B39: The Metal | C39: Tenacious D | D39: 40101 | E39: DLC | F39: Part of "Brutal Legends Pack 01"
B40: Everybody Get Dangerous | C40: Weezer
B41: Dimension | C41: Wolfmother
B42: Lights and Sounds | C42: Yellowcard
B45: Songs Released | C45: =COUNT(D:D) -> 13
B46: Total Songs | C46: 40
B47: Percent Complete | C47: =IFERROR(__xludf.DUMMYFUNCTION("TO_PERCENT(C45/C46)"),0.325) -> 0.325

Sheet Band Hero DS
B2: Song | C2: Artist | D2: Release Date | E2: Source | F2: Notes
B3: Believe | C3: The All-American Rejects
B4: Fascination | C4: Alphabeat | D4: 40227 | E4: DLC | F4: DLC Single
B5: Girlfriend | C5: Avril Lavigne
B6: Let's Get It Started | C6: The Black Eyed Peas
B7: First Date | C7: blink-182 | D7: 40183 | E7: DLC | F7: Part of "blink-182 Pack 02"
B8: Song 2 | C8: Blur | D8: 40120 | E8: LEGO Export/DLC | F8: Export Has Expired but Re-Released as a DLC Single
B9: The Great Escape | C9: Boys Like Girls | D9: 40337 | E9: DLC | F9: DLC Single
B10: My Favourite Game | C10: The Cardigans
B11: Yellow | C11: Coldplay | D11: 40834 | E11: DLC | F11: Part of "Coldplay Collection 01"
B12: Hungry Like the Wolf | C12: Duran Duran | D12: 39705 | E12: RB2 Export/DLC | F12: Export Has Expired but re-released as a DLC Single
B13: Wannabe in L.A. | C13: Eagles of Death Metal
B14: Munich | C14: Editors
B15: Call Me When You're Sober | C15: Evanescence | D15: 39980 | E15: DLC | F15: Part of "Evanescence Pack 01"
B16: Thnks fr th Mmrs | C16: Fall Out Boy | D16: 40771 | E16: DLC | F16: Part of "Fall Out Boy Pack 01"
B17: Monkey Wrench | C17: Foo Fighters | D17: 39765 | E17: DLC | F17: Part of "The Colour and the Shape" Album
B18: Feel Good Inc. | C18: Gorillaz | D18: 40036 | E18: DLC | F18: Part of "Gorillaz Pack 01"
B19: I Predict a Riot | C19: Kaiser Chiefs | D19: 40043 | E19: DLC | F19: DLC Single
B20: Club Foot | C20: Kasabian | D20: 40129 | E20: DLC | F20: DLC Single
B21: Spaceman | C21: The Killers | D21: 39777 | E21: DLC | F21: Part of "The Killers Pack 01"
B22: Manhattan | C22: Kings of Leon
B23: Suddenly I See | C23: KT Tunstall | D23: 40120 | E23: LEGO Export | F23: Export Has Expired
B24: Our Truth | C24: Lacuna Coil | D24: 39705 | E24: RB2 Export | F24: Export Has Expired
B25: The Age of the Understatement | C25: The Last Shadow Puppets
B26: Fly Away | C26: Lenny Kravitz
B27: Take What You Take | C27: Lily Allen
B28: She Will Be Loved | C28: Maroon 5
B29: Grace Kelly | C29: Mika
B30: Windows | C30: N*E*R*D
B31: Excuse Me Mr. | C31: No Doubt | D31: 39793 | E31: DLC | F31: Part of "Tragic Kingdom" Album and The Singles: "1993 to 2003" Album
B32: So What | C32: P!nk | D32: 40120 | E32: LEGO Export | F32: Export Has Expired
B33: Lump | C33: The Presidents of the United States of America | D33: 39705 | E33: RB2 Export | F33: Export Has Expired
B34: Boots of Chinese Plastic | C34: The Pretenders
B35: Crazy Little Thing Called Love | C35: Queen | D35: 40108 | E35: DLC | F35: Part of "Queen Pack 01"
B36: No One Knows | C36: Queens of the Stone Age | D36: 40477 | E36: RB3 Export | F36: Export Has Expired
B37: Golden Touch | C37: Razorlight
B38: You Better Pray | C38: The Red Jumpsuit Apparatus
B39: Tripping | C39: Robbie Williams
B40: Under My Thumb (Live) | C40: The Rolling Stones
B41: Two Princes | C41: Spin Doctors | D41: 40120 | E41: LEGO Export/DLC | F41: Export Has Expired, but re-released as a DLC single
B42: All You Need | C42: Sublime
B43: In Too Deep | C43: Sum 41 | D43: 40120 | E43: LEGO Export/DLC | F43: Export Has Expired but re-released as a Single
B44: Everything About You | C44: Ugly Kid Joe
B45: A-Punk | C45: Vampire Weekend | D45: 40120 | E45: LEGO Export | F45: Export Has Expired
B46: Get Free | C46: The Vines | D46: 40477 | E46: RB3 Export | F46: Export Has Expired
B47: Troublemaker | C47: Weezer | D47: 39625 | E47: DLC | F47: Part of "Weezer Pack 01"
B50: Songs Released | C50: =COUNT(D:D) -> 25
B51: Total Songs | C51: 45
B52: Percent Complete | C52: =IFERROR(__xludf.DUMMYFUNCTION("TO_PERCENT(C50/C51)"),0.5555555555555556) -> 0.55555556

Sheet GH 3 Mobile
B2: Song | C2: Artist | D2: Release Date | E2: Source | F2: Notes
B3: Miss Murder | C3: AFI | D3: 40066 | E3: DLC | F3: DLC Single
B4: School's Out | C4: Alice Cooper | D4: 39952 | E4: DLC | F4: Live Version Part of "Alice Cooper Pack 01"
B5: Jessica | C5: The Allman Brothers Band | D5: 41233 | E5: DLC | F5: DLC Single
B6: Paranoid | C6: Black Sabbath | D6: 39406 | E6: RB1 | F6: Cover that was never Exportable
B7: Strutter | C7: Kiss | D7: 40659 | E7: DLC | F7: Live Version as a DLC Single
B8: Monsters | C8: Matchbook Romance
B9: Shout at the Devil | C9: Mötley Crüe
B10: Hit Me with Your Best Shot | C10: Pat Benatar | D10: 39847 | E10: DLC | F10: Part of "Classic Rock Track Pack" and as a DLC Single
B11: Suck My Kiss | C11: Red Hot Chili Peppers | D11: 39721 | E11: DLC | F11: DELISTED
B12: Black Magic Woman | C12: Santana | D12: 40631 | E12: DLC | F12: Part of "Days of Peace Pack 01"
B13: Rock You Like a Hurricane | C13: Scorpions | D13: 44546 | E13: DLC | F13: DLC Single and Temporarily Part of "Rivals Season 24 Pass"
B14: Cherub Rock | C14: The Smashing Pumpkins | D14: 39406 | E14: RB1 Export/DLC | F14: Export Has Expired but has been released a Part of "Rock Band Rewind Pack 01" and "Rock Band 15th Anniversary"
B15: Trippin' on a Hole in a Paper Heart | C15: Stone Temple Pilots | D15: 40470 | E15: DLC | F15: Part of "Stone Temple Pilots Pack 01"
B16: You Really Got Me | C16: Van Halen
B17: Woman | C17: Wolfmother | D17: 40113 | E17: DLC | F17: Part of "Wolfmother Pack 01"
B20: Songs Released | C20: =COUNT(D:D) -> 12
B21: Total Songs | C21: 15
B22: Percent Complete | C22: =IFERROR(__xludf.DUMMYFUNCTION("TO_PERCENT(C20/C21)"),0.8) -> 0.8

Sheet GH 3 Mobile DLC
B2: Song | C2: Artist | D2: Release Date | E2: Source | F2: Notes
B3: Last Child | C3: Aerosmith
B4: Madhouse | C4: Anthrax | D4: 40449 | E4: DLC | F4: Live Version part of "Anthrax Pack 01"
B5: War Pigs | C5: Black Sabbath | D5: 39420 | E5: DLC | F5: Cover Part of "Black Sabbath Pack 01"
B6: Cities on Flame with Rock and Roll | C6: Blue Öyster Cult
B7: Mother | C7: Danzig
B8: Misirlou | C8: Dick Dale
B9: Stricken | C9: Disturbed | D9: 39945 | E9: DLC | F9: DLC Single
B10: Cliffs of Dover | C10: Eric Johnson
B11: F.C.P.R.E.M.I.X. | C11: The Fall of Troy | D11: 44854 | E11: DLC | F11: DLC SIngle and Temporarily Part of "Rivals Season 28 Pass"
B12: Slow Ride | C12: Foghat | D12: 43041 | E12: DLC | F12: Part of 'Solid '70's Pack 2"
B13: Barracuda | C13: Heart | D13: 40757 | E13: DLC | F13: DLC Single
B14: Crazy on You | C14: Heart | D14: 43440 | E14: DLC | F14: DLC Single and Temporarily Part of "Rivals Season 9 Pass"
B15: Search and Destroy | C15: Iggy Pop and the Stooges
B16: Stop! | C16: Jane's Addiction | D16: 42647 | E16: DLC | F16: DLC Single
B17: Carry on Wayward Son | C17: Kansas | D17: 39705 | E17: RB2 Export/DLC | F17: Export Has Expired but Re-Released in the "Solid '70s Pack 01"
B18: Rock and Roll All Nite | C18: Kiss | D18: 40659 | E18: DLC | F18: RB has live version as a DLC Single
B19: Closer | C19: Lacuna Coil | D19: 39770 | E19: DLC | F19: Part of "Centurt Media Girls of Metal Pack" and Metal Track Pack"
B20: Laid to Rest | C20: Lamb of God | D20: 39777 | E20: DLC | F20: Part of "Metal Track Pack" and as a DLC Single
B21: Metal Heavy Lady | C21: Lions
B22: Free Bird | C22: Lynyrd Skynyrd | D22: 40477 | E22: RB3 Export | F22: Export Has Expired, but Re-Released as a DLC Single
B23: Girlfriend | C23: Matthew Sweet
B24: Mississippi Queen | C24: Mountain | D24: 39406 | E24: RB1 Export | F24: Export Has Expired, and it's a cover
B25: Life Wasted | C25: Pearl Jam
B26: Talk Dirty to Me | C26: Poison | D26: 40722 | E26: DLC | F26: Part of "Poison Pack 01"
B27: John The Fisherman | C27: Primus
B28: Psychobilly Freakout | C28: The Reverend Horton Heat
B29: Rock and Roll, Hoochie Koo | C29: Rick Derringer | D29: 42283 | E29: RB4 | F29: On-Disc Song
B30: YYZ | C30: Rush | D30: 39714 | E30: DLC | F30: Part of "Moving Pictures" Album
B31: Tonight I'm Gonna Rock You Tonight | C31: Spinal Tap | D31: 40029 | E31: DLC | F31: DELISTED
B32: Pride and Joy | C32: Stevie Ray Vaughan | D32: 39875 | E32: DLC | F32: Part of "Texas Flood" Album
B33: She Bangs the Drums | C33: The Stone Roses
B34: Freya | C34: The Sword
B35: The Arsonist | C35: Thrice
B36: Black Sunshine | C36: White Zombie | D36: 39861 | E36: DLC | F36: DLC Single
B37: The Seeker | C37: The Who | D37: 42283 | E37: RB4 | F37: On-Disc Song
B38: La Grange | C38: ZZ Top
B41: Songs Released | C41: =COUNT(D:D) -> 21
B42: Total Songs | C42: 36
B43: Percent Complete | C43: =IFERROR(__xludf.DUMMYFUNCTION("TO_PERCENT(C41/C42)"),0.5833333333333334) -> 0.58333333

Sheet GH World Tour Mobile
B2: Song | C2: Artist | D2: Release Date | E2: Source | F2: Notes
B3: Stillborn | C3: Black Label Society
B4: One Way or Another | C4: Blondie | D4: 39705 | E4: RB2 Export/DLC | F4: Export Has Expired, but has been re-released as a single
B5: Hollywood Nights | C5: Bob Seger & the Silver Bullet Band
B6: Up Around the Bend | C6: Creedence Clearwater Revival | D6: 40365 | E6: DLC | F6: Part of "Creedence Clearwater Revival Pack 01"
B7: Obstacle 1 | C7: Interpol
B8: Are You Gonna Go My Way | C8: Lenny Kravitz | D8: 39826 | E8: DLC | F8: Part of "Lenny Kravitz Pack 01"
B9: Sweet Home Alabama (live) | C9: Lynyrd Skynyrd | D9: 40512 | E9: DLC | F9: Part of "Lynyrd Skyryrd Pack 01"
B10: Overkill | C10: Motörhead
B11: Spiderwebs | C11: No Doubt | D11: 39791 | E11: DLC | F11: Part of "Tragic Kingdom" Album and The Single: "1993 to 2003" Album
B12: Some Might Say | C12: Oasis
B13: Re-Education Through Labor | C13: Rise Against | D13: 40015 | E13: DLC | F13: Part of "Rise Against Pack 01"
B14: Lazy Eye | C14: Silversun Pickups | D14: 39705 | E14: RB2 Export | F14: Export Has Expired
B15: Today | C15: Smashing Pumpkins | D15: 39705 | E15: RB2 Export | F15: Export Has Expired
B16: Santeria | C16: Sublime | D16: 41212 | E16: DLC | F16: Part of "Sublime Pack 01" and "Rock Band Hits Pack"
B17: Stranglehold | C17: Ted Nugent | D17: 42978 | E17: DLC | F17: DLC Single and Temporarily Part of "Rivals Season 2 Pass"
B20: Songs Released | C20: =COUNT(D:D) -> 10
B21: Total Songs | C21: 15
B22: Percent Complete | C22: =IFERROR(__xludf.DUMMYFUNCTION("TO_PERCENT(C20/C21)"),0.6666666666666666) -> 0.66666667

Sheet GH World Tour Mobile DLC
B2: Song | C2: Artist | D2: Release Date | E2: Source | F2: Notes
B3: You're Gonna Say Yeah! | C3: HushPuppies | D3: 43727 | E3: DLC | F3: DLC Single and Temporarily Part of "Rivals Season 13 Pass"
B4: Our Truth | C4: Lacuna Coil | D4: 39705 | E4: RB2 Export | F4: Export Has Expired
B5: Nuvole E Lenzuola | C5: Negramaro
B6: Jimi | C6: Slightly Stoopid
B7: G.L.O.W. | C7: Smashing Pumpkins
B8: The Joker | C8: Steve Miller | D8: 39833 | E8: DLC | F8: Part of "Steve Miller Band Pack 01" and Classic Rock Track Pack
B9: Demolition Man (Live) | C9: Sting
B10: Toy Boy | C10: Stuck in the Sound
B11: Band on the Run | C11: Wings | D11: 40185 | E11: DLC | F11: Part of "Celebrating Band on the Run Pack"
B12: Gimme All Your Lovin' | C12: ZZ Top
B15: Songs Released | C15: =COUNT(D:D) -> 4
B16: Total Songs | C16: 10
B17: Percent Complete | C17: =IFERROR(__xludf.DUMMYFUNCTION("TO_PERCENT(C15/C16)"),0.4) -> 0.4

Sheet GH 5 Mobile
B2: Song | C2: Artist | D2: Release Date | E2: Source | F2: Notes
B3: Kryptonite | C3: 3 Doors Down | D3: 40064 | E3: DLC | F3: DLC Single and part of "Rock Band Hits Pack"
B4: You and Me | C4: Attack! Attack!
B5: The Rock Show | C5: blink-182 | D5: 40022 | E5: DLC | F5: Part of "blink-182 Pack 01"
B6: Comedown | C6: Bush | D6: 40946 | E6: DLC | F6: Part of "Bush Pack 01"
B7: Blue Day | C7: Darker My Love
B8: Demon(s) | C8: Darkest Hour
B9: Fame | C9: David Bowie | D9: 40568 | E9: DLC | F9: Part of "David Bowie Pack 02"
B10: Younk Funk | C10: The Derek Trucks Band
B11: Disconnected | C11: Face to Face
B12: Only Happy When It Rains | C12: Garbage
B13: Streamline Woman | C13: Gov't Mule
B14: One Big Holiday | C14: My Morning Jacket | D14: 42283 | E14: DLC | F14: DLC Single
B15: Lithium (live) | C15: Nirvana | D15: 40148 | E15: DLC | F15: Part of "Nirvana Pack 02"
B16: Ex-Girlfriend | C16: No Doubt | D16: 39791 | E16: DLC | F16: Part of "1993-2003: The Singles" Album
B17: Bring the Noise 20XX | C17: Public Enemy featuring Zakk Wylde | D17: 44772 | E17: DLC | F17: Remix With Anthrax available as DLC Single and Temporarily Part of "Rivals Season 27 Pass"
B18: Sneak Out | C18: Rose Hill Drive
B19: The Spirit of Radio (live) | C19: Rush | D19: 40890 | E19: DLC | F19: Part of "Rush Pack 01"
B20: What I Got | C20: Sublime | D20: 41212 | E20: DLC | F20: Part of "Sublime Pack 01"
B21: A-Punk | C21: Vampire Weekend | D21: 40120 | E21: LEGO Export | F21: Export Has Expired
B24: Songs Released | C24: =COUNT(D:D) -> 11
B25: Total Songs | C25: 20
B26: Percent Complete | C26: =IFERROR(__xludf.DUMMYFUNCTION("TO_PERCENT(C24/C25)"),0.55) -> 0.55

Sheet GH Arcade
B2: Song | C2: Artist | D2: Release Date | E2: Source | F2: Notes
B3: Same Old Song and Dance | C3: Aerosmith
B4: School's Out | C4: Alice Cooper | D4: 39952 | E4: DLC | F4: Live Version Part of "Alice Cooper Pack 01"
B5: Almost Easy | C5: Avenged Sevenfold | D5: 39705 | E5: RB2 Export | F5: Export Has Expired
B6: Sabotage | C6: Beastie Boys | D6: 39406 | E6: RB1 Export/DLC | F6: Export Has Expired but has been released a Part of "Rock Band Rewind Pack 01" and "Rock Band 15th Anniversary"
B7: Paranoid | C7: Black Sabbath | D7: 39406 | E7: RB1 | F7: Cover that was never Exportable
B8: Helicopter | C8: Bloc Party
B9: Cities on Flame with Rock and Roll | C9: Blue Öyster Cult
B10: Peace of Mind | C10: Boston | D10: 39532 | E10: DLC | F10: Part of "Boston Pack 01" and "Classic Rock Track Pack"
B11: Yellow | C11: Coldplay | D11: 40834 | E11: DLC | F11: Part of "Coldplay Collection 01"
B12: Sunshine of Your Love | C12: Cream
B13: Holiday in Cambodia | C13: Dead Kennedys | D13: 39770 | E13: DLC | F13: Part of "Dead Kennedys Pack 01" and "Classic Rock Track Pack"
B14: Hole in the Earth | C14: Deftones | D14: 40337 | E14: DLC | F14: Part of "Deftones Pack 01"
B15: Stricken | C15: Disturbed | D15: 39945 | E15: DLC | F15: DLC Single
B16: Cliffs of Dover | C16: Eric Johnson
B17: Slow Ride | C17: Foghat | D17: 43041 | E17: DLC | F17: Part of 'Solid '70's Pack 2"
B18: This Is A Call | C18: Foo Fighters | D18: 39805 | E18: DLC | F18: Part of "Foo Fighters Pack 01"
B19: Jukebox Hero | C19: Foreigner | D19: 39406 | E19: DLC | F19: Cover is a DLC Single
B20: In the Belly of a Shark | C20: Gallows
B21: Barracuda | C21: Heart | D21: 40757 | E21: DLC | F21: DLC Single
B22: Avalancha | C22: Héroes del Silencio
B23: Take This Life | C23: In Flames
B24: Surfing With the Alien | C24: Joe Satriani | D24: 40099 | E24: DLC | F24: DLC Single
B25: Rock and Roll All Nite | C25: Kiss | D25: 40659 | E25: DLC | F25: RB has live version as a DLC Single
B26: Closer | C26: Lacuna Coil | D26: 39770 | E26: DLC | F26: Part of "Centurt Media Girls of Metal Pack" and Metal Track Pack"
B27: No More Sorrow | C27: Linkin Park
B28: Cult of Personality | C28: Living Colour | D28: 41150 | E28: Blitz/DLC | F28: Part of Rock Band Blitz and as a DLC Single
B29: Sleeping Giant | C29: Mastodon
B30: Monsters | C30: Matchbook Romance
B31: Motorhead | C31: Motörhead
B32: Mississippi Queen | C32: Mountain | D32: 39406 | E32: RB1 Export | F32: Export Has Expired
B33: Knights of Cydonia | C33: Muse | D33: 44805 | E33: DLC | F33: Part of "Muse Pack 01" and Temporarily Part of "Rivals Season 28 Pass"
B34: Hit Me With Your Best Shot | C34: Pat Benatar | D34: 39847 | E34: DLC | F34: Part of "Classic Rock Track Pack" and as a DLC Single
B35: Talk Dirty to Me | C35: Poison | D35: 40722 | E35: DLC | F35: Part of "Poison Pack 01"
B36: Lay Down | C36: Priestess
B37: Bulls on Parade | C37: Rage Against the Machine | D37: 40204 | E37: DLC | F37: Part of "Metal Track Pack" and as DLC Single
B38: Paint It, Black | C38: The Rolling Stones
B39: Black Magic Woman | C39: Santana | D39: 40631 | E39: DLC | F39: Part of "Days of Peace Pack 01"
B40: Rock You Like a Hurricane | C40: Scorpions | D40: 44546 | E40: DLC | F40: DLC Single and Temporarily Part of "Rivals Season 24 Pass"
B41: Anarchy in the U.K. | C41: Sex Pistols
B42: Don't Hold Back | C42: The Sleeping
B43: Cherub Rock | C43: The Smashing Pumpkins | D43: 39406 | E43: RB1 Export/DLC | F43: Export Has Expired but has been released a Part of "Rock Band Rewind Pack 01" and "Rock Band 15th Anniversary"
B44: For The Love of God | C44: Steve Vai | D44: 43734 | E44: DLC | F44: Live Version available as a DLC Single
B45: Pride and Joy | C45: Stevie Ray Vaughan | D45: 39875 | E45: DLC | F45: Part of "Texas Flood" Album
B46: She Bangs the Drums | C46: The Stone Roses
B47: Reptilia | C47: The Strokes | D47: 39406 | E47: RB1 Export/DLC | F47: Export Has Expired, but re-released as a DLC single
B48: The Metal | C48: Tenacious D | D48: 40099 | E48: DLC | F48: Part of "Brutal Legends Pack 01"
B49: The Arsonist | C49: Thrice
B50: Pretty Handsome Awkward | C50: The Used
B51: Black Sunshine | C51: White Zombie | D51: 39861 | E51: DLC | F51: DLC Single
B52: La Grange | C52: ZZ Top
B55: Songs Released | C55: =COUNT(D:D) -> 30
B56: Total Songs | C56: 50
B57: Percent Complete | C57: =IFERROR(__xludf.DUMMYFUNCTION("TO_PERCENT(C55/C56)"),0.6) -> 0.6

Sheet DJ Hero
B2: Song | C2: Artist | D2: Release Date | E2: Source | F2: Notes
B3: All Eyez on Me | C3: 2Pac
B4: How Do U Want It | C4: 2Pac
B5: Disco Inferno | C5: 50 Cent
B6: Zulu Nation Throwdown | C6: Afrika Bambaataa
B7: Bittersweet Symphony (Instrumental) | C7: The Aranbee Pop Symphony Orchestra
B8: Brass Monkey | C8: Beastie Boys
B9: Here's a Little Somethin' for Ya | C9: Beastie Boys
B10: Intergalactic | C10: Beastie Boys
B11: Lee Majors Come Again | C11: Beastie Boys
B12: Sabotage | C12: Beastie Boys | D12: 39406 | E12: RB1 Export/DLC | F12: Export Has Expired but has been released a Part of "Rock Band Rewind Pack 01" and "Rock Band 15th Anniversary"
B13: Loser | C13: Beck
B14: Where It's At | C14: Beck
B15: Poison | C15: Bell Biv DeVoe
B16: Satisfaction | C16: Benny Benassi
B17: The Big Beat | C17: Billy Squier
B18: Boom Boom Pow | C18: The Black Eyed Peas
B19: Hey Mama | C19: The Black Eyed Peas ft. Tippa Irie
B20: Atomic | C20: Blondie | D20: 40247 | E20: RBN | F20: Never officially released but you can buy it, but it won't work for RB4
B21: Rapture | C21: Blondie | D21: 40393 | E21: DLC | F21: DLC Single
B22: Ain't No Love in the Heart of the City | C22: Bobby "Blue" Bland
B23: Jack of Spades | C23: Boogie Down Productions
B24: Word Up! | C24: Cameo
B25: Bustin' Loose | C25: Chuck Brown & The Soul Searchers
B26: Spooky | C26: Classics IV
B27: Universal Mind Control | C27: Common
B28: Fuzz and Them | C28: Connie Price & The Keystones
B29: Insane in the Brain | C29: Cypress Hill
B30: Annie's Horn | C30: D-Code
B31: Around the World | C31: Daft Punk
B32: Da Funk | C32: Daft Punk
B33: Robot Rock | C33: Daft Punk
... B37: The Edge | C37: David Axelrod
B38: Let's Dance | C38: David Bowie | D38: 40120 | E38: LEGO Export | F38: Export Has Expired
B39: Fix Up, Look Sharp | C39: Dizzee Rascal
B40: Six Days (Remix) | C40: DJ Shadow
B41: The Number Song (2009 Version) | C41: DJ Shadow
B42: Organ Donor (Extended Overhaul) | C42: DJ Shadow
B43: Six Days (Remix) | C43: DJ Shadow featuring Mos Def
B44: DJ Hero | C44: DJ Z-Trip featuring Murs
B45: My Name Is | C45: Eminem
B46: Eric B. Is President | C46: Eric B. & Rakim
B47: Pjanoo | C47: Eric Prydz
